Workbook

Sheet 2026年2月
A1: 2026年2月市州应收账款情况表
A2: 序号 | B2: 单位 | C2: 2025年收入完成（不含云及IDC直销收入） | E2: 2026年收入预算（不含云及IDC运营中心直销客户的IDC收入） | I2: 应收账款总额占收比 | P2: 产数应收账款占产数收入比 | W2: 分资源型/ICT应收占收比 （注：资源型应收=组网专线+IDC ICT应收=产数应收+合同资产-资源应收 资源型收入=组网专线+IDC-云锦IDC收入 ICT应收=产数收入-组网专线-IDC） | AE2: 基础应收账款占基础收入比 | AL2: 一年以上应收账款占应收总额比 | AS2: 一年以上产数应收 | AY2: 预收账款占收比 | BF2: 本期坏账计提 | BL2: 营业收现率
C3: 收入完成 | D3: 产数收入完成 | E3: 收入 | F3: 产数收入 | G3: 收入同比 | H3: 产数收入同比 | I3: 202502 应收总额 | J3: 202602 应收总额 | K3: 应收总额同比增幅 | L3: 202502 占收比 | M3: 202602 占收比 | N3: 排名 | O3: 占收比同比 | P3: 202502 应收产数 | Q3: 202602 应收产数 | R3: 产数应收账款增幅 | S3: 202502 产数占收比 | T3: 202602 产数占收比 | U3: 排名 | V3: 产数占收比同比 | W3: 202602资源型应收账款总额 | X3: 202602产数ICT应收账款总额 | Y3: 202602资源型收入（剔除云锦IDC收入） | Z3: 202602产数ICT收入 | AA3: 202602资源型应收占收比 | AB3: 排名 | AC3: 202602产数ICT应收占收比 | AD3: 排名 | AE3: 202502 基础应收 | AF3: 202602 基础应收 | AG3: 基础应收同比增幅 | AH3: 202502 基础占收比 | AI3: 202602 基础占收比 | AJ3: 排名 | AK3: 基础占收比同比 | AL3: 202502 一年以上应收 | AM3: 202602 一年以上应收 | AN3: 一年以上同比增幅 | AO3: 排名 | AP3: 202502 一年以上占应收总额比 | AQ3: 202602 一年以上占应收总额比 | AR3: 排名 | AS3: 202502一年以上产数应收 | AT3: 202602一年以上产数应收 | AU3: 202602一年以上产数应收账款结构占比 | AV3: 排名 | AW3: 202602一年以上产数应收同比增幅 | AX3: 排名 | AY3: 202502 预收账款总额 | AZ3: 202602 预收账款总额 | BA3: 同比增幅 | BB3: 202502 占收比 | BC3: 202602 占收比 | BD3: 排名 | BE3: 占收比同比 | BF3: 202502本年坏账计提 | BG3: 202602本年坏账计提 | BH3: 同比增幅 | BI3: 202502本年坏账计提占应收比 | BJ3: 202602本年坏账计提占应收比 | BK3: 排名 | BL3: 202502经营活动现金流入完成 | BM3: 202602经营活动现金流入完成 | BN3: 202502营业收现率 | BO3: 202602营业收现率 | BP3: 排名
A5: 1 | B5: 成都 | C5: 1035002.1 | D5: 180143.51 | E5: 1059462.1 | F5: 200299.18 | G5: =E5/C5-1 -> 0.023632757 | H5: =F5/D5-1 -> 0.11188678 | I5: =VLOOKUP(B5,[4]计算结果表!$B$1:$AA$25,13,0) -> 81543.131 | J5: =VLOOKUP(B5,[2]计算结果表!$B$1:$AA$25,13,0) -> 82522.458 | K5: =J5/I5-1 -> 0.012009917 | L5: =I5/C5 -> 0.078785473 | M5: =J5/E5 -> 0.077890904 | N5: =RANK(M5,$M$5:$M$25,1) -> 4 | O5: =M5-L5 -> -0.00089456986 | P5: =VLOOKUP(B5,[4]计算结果表!$B$1:$AA$25,15,0) -> 54820.637 | Q5: =VLOOKUP(B5,[2]计算结果表!$B$1:$AA$25,15,0) -> 63932.288 | R5: =Q5/P5-1 -> 0.16620842 | S5: =P5/D5 -> 0.30431647 | T5: =Q5/F5 -> 0.31918397 | U5: =RANK(T5,$T$5:$T$25,1) -> 2 | V5: =T5-S5 -> 0.014867494 | W5: =VLOOKUP(B5,[2]计算结果表!$B$1:$T$25,18,0) -> 10976.05 | X5: =VLOOKUP(B5,[2]计算结果表!$B$1:$T$25,19,0) -> 52956.238 | Y5: =VLOOKUP(B5,[1]分ICT资源型数据!$B$1:$P$23,11,0) -> 68355.352 | Z5: =VLOOKUP(B5,[1]分ICT资源型数据!$B$1:$P$23,12,0) -> 107234.61 | AA5: =W5/(Y5/11*12) -> 0.14719226 | AB5: =RANK(AA5,$AA$5:$AA$25,1) -> 3 | AC5: =X5/(Z5/11*12) -> 0.45268238 | AD5: =RANK(AC5,$AC$5:$AC$25,1) -> 3 | AE5: =VLOOKUP(B5,[4]计算结果表!$B$1:$T$25,16,0) -> 26722.495 | AF5: =VLOOKUP(B5,[2]计算结果表!$B$1:$T$25,16,0) -> 18590.169 | AG5: =AF5/AE5-1 -> -0.30432508 | AH5: =AE5/(C5-D5) -> 0.031259549 | AI5: =AF5/(E5-F5) -> 0.021637538 | AJ5: =RANK(AI5,$AI$5:$AI$25,1) -> 4 | AK5: =AI5-AH5 -> -0.0096220113 | AL5: =VLOOKUP(B5,'[5]查询结果(2025年2月)'!$A$2:$L$29,12,0)/10000 -> 15743.061 | AM5: =VLOOKUP(B5,'[3]查询结果(2026年2月)'!$A$2:$L$29,12,0)/10000 -> 16511.89 | AN5: =AM5/AL5-1 -> 0.048836081 | AO5: =RANK(AN5,$AN$5:$AN$25,1) -> 4 | AP5: =AL5/I5 -> 0.19306422 | AQ5: =AM5/J5 -> 0.20008966 | AR5: =RANK(AQ5,$AQ$5:$AQ$25,1) -> 13 | AS5: =VLOOKUP(B5,'[6]查询结果(2025年2月)'!$A$2:$L$29,12,0)/10000 -> 8325.644 | AT5: =VLOOKUP(B5,'[7]查询结果(2026年2月)'!$A$2:$H$25,8,0)/10000 -> 10434.199 | AU5: =AT5/Q5 -> 0.16320704 | AV5: =RANK(AU5,$AU$5:$AU$25,1) -> 8 | AW5: =AT5/AS5-1 -> 0.25326031 | AX5: =RANK(AW5,$AW$5:$AW$25,1) -> 5 | AY5: =VLOOKUP(B5,[4]计算结果表!$B$1:$T$25,17,0) -> 88820.823 | AZ5: =VLOOKUP(B5,[2]计算结果表!$B$1:$T$25,17,0) -> 100298.48 | BA5: =AZ5/AY5-1 -> 0.12922258 | BB5: =AY5/C5 -> 0.085817045 | BC5: =AZ5/E5 -> 0.09466925 | BD5: =RANK(BC5,$BC$5:$BC$25,0) -> 3 | BE5: =BC5-BB5 -> 0.0088522044 | BF5: =VLOOKUP(B5,[4]计算结果表!$B$1:$T$25,9,0) -> 1152.4149 | BG5: =VLOOKUP(B5,[2]计算结果表!$B$1:$T$25,9,0) -> 1949.6893 | BH5: =BG5/BF5-1 -> 0.69182932 | BI5: =BF5/I5 -> 0.014132581 | BJ5: =BG5/J5 -> 0.023626166 | BK5: =RANK(BJ5,$BJ$5:$BJ$25,1) -> 4 | BL5: =VLOOKUP(B5,[8]市州营业收现率202502完成!$B$1:$AH$28,6,0) -> 148792.17 | BM5: =VLOOKUP(B5,[9]市州营业收现率2月完成!$B$1:$AI$28,7,0) -> 154446.04 | BN5: =VLOOKUP(B5,[8]市州营业收现率202502完成!$B$1:$AH$28,5,0) -> 0.80964643 | BO5: =VLOOKUP(B5,[9]市州营业收现率2月完成!$B$1:$AI$28,5,0) -> 0.89820313 | BP5: =RANK(BO5,$BO$5:$BO$25,0) -> 15
A6: 2 | B6: 绵阳 | C6: 181679.31 | D6: 18516.339 | E6: 186047.11 | F6: 22732.105 | G6: =E6/C6-1 -> 0.024041211 | H6: =F6/D6-1 -> 0.22767818 | I6: =VLOOKUP(B6,[4]计算结果表!$B$1:$AA$25,13,0) -> 10908.332 | J6: =VLOOKUP(B6,[2]计算结果表!$B$1:$AA$25,13,0) -> 14376.138 | K6: =J6/I6-1 -> 0.31790429 | L6: =I6/C6 -> 0.060041684 | M6: =J6/E6 -> 0.077271493 | N6: =RANK(M6,$M$5:$M$25,1) -> 3 | O6: =M6-L6 -> 0.017229809 | P6: =VLOOKUP(B6,[4]计算结果表!$B$1:$AA$25,15,0) -> 5534.9355 | Q6: =VLOOKUP(B6,[2]计算结果表!$B$1:$AA$25,15,0) -> 8092.3444 | R6: =Q6/P6-1 -> 0.46204856 | S6: =P6/D6 -> 0.2989217 | T6: =Q6/F6 -> 0.35598746 | U6: =RANK(T6,$T$5:$T$25,1) -> 4 | V6: =T6-S6 -> 0.057065762 | W6: =VLOOKUP(B6,[2]计算结果表!$B$1:$T$25,18,0) -> 1524.199 | X6: =VLOOKUP(B6,[2]计算结果表!$B$1:$T$25,19,0) -> 6568.1454 | Y6: =VLOOKUP(B6,[1]分ICT资源型数据!$B$1:$P$23,11,0) -> 7341.014 | Z6: =VLOOKUP(B6,[1]分ICT资源型数据!$B$1:$P$23,12,0) -> 10540.18 | AA6: =W6/(Y6/11*12) -> 0.19032553 | AB6: =RANK(AA6,$AA$5:$AA$25,1) -> 7 | AC6: =X6/(Z6/11*12) -> 0.57122364 | AD6: =RANK(AC6,$AC$5:$AC$25,1) -> 5 | AE6: =VLOOKUP(B6,[4]计算结果表!$B$1:$T$25,16,0) -> 5373.3966 | AF6: =VLOOKUP(B6,[2]计算结果表!$B$1:$T$25,16,0) -> 6283.7932 | AG6: =AF6/AE6-1 -> 0.16942666 | AH6: =AE6/(C6-D6) -> 0.032932695 | AI6: =AF6/(E6-F6) -> 0.038476522 | AJ6: =RANK(AI6,$AI$5:$AI$25,1) -> 10 | AK6: =AI6-AH6 -> 0.0055438269 | AL6: =VLOOKUP(B6,'[5]查询结果(2025年2月)'!$A$2:$L$29,12,0)/10000 -> 815.06266 | AM6: =VLOOKUP(B6,'[3]查询结果(2026年2月)'!$A$2:$L$29,12,0)/10000 -> 2256.1444 | AN6: =AM6/AL6-1 -> 1.7680625 | AO6: =RANK(AN6,$AN$5:$AN$25,1) -> 14 | AP6: =AL6/I6 -> 0.074719275 | AQ6: =AM6/J6 -> 0.15693676 | AR6: =RANK(AQ6,$AQ$5:$AQ$25,1) -> 8 | AS6: =VLOOKUP(B6,'[6]查询结果(2025年2月)'!$A$2:$L$29,12,0)/10000 -> 377.50273 | AT6: =VLOOKUP(B6,'[7]查询结果(2026年2月)'!$A$2:$H$25,8,0)/10000 -> 1570.813 | AU6: =AT6/Q6 -> 0.19411099 | AV6: =RANK(AU6,$AU$5:$AU$25,1) -> 11 | AW6: =AT6/AS6-1 -> 3.161064 | AX6: =RANK(AW6,$AW$5:$AW$25,1) -> 18 | AY6: =VLOOKUP(B6,[4]计算结果表!$B$1:$T$25,17,0) -> 11137.634 | AZ6: =VLOOKUP(B6,[2]计算结果表!$B$1:$T$25,17,0) -> 12495.648 | BA6: =AZ6/AY6-1 -> 0.12193015 | BB6: =AY6/C6 -> 0.061303811 | BC6: =AZ6/E6 -> 0.067163892 | BD6: =RANK(BC6,$BC$5:$BC$25,0) -> 11 | BE6: =BC6-BB6 -> 0.0058600817 | BF6: =VLOOKUP(B6,[4]计算结果表!$B$1:$T$25,9,0) -> 291.05039 | BG6: =VLOOKUP(B6,[2]计算结果表!$B$1:$T$25,9,0) -> 900.07552 | BH6: =BG6/BF6-1 -> 2.0925076 | BI6: =BF6/I6 -> 0.026681475 | BJ6: =BG6/J6 -> 0.062608994 | BK6: =RANK(BJ6,$BJ$5:$BJ$25,1) -> 15 | BL6: =VLOOKUP(B6,[8]市州营业收现率202502完成!$B$1:$AH$28,6,0) -> 27880.597 | BM6: =VLOOKUP(B6,[9]市州营业收现率2月完成!$B$1:$AI$28,7,0) -> 29229.939 | BN6: =VLOOKUP(B6,[8]市州营业收现率202502完成!$B$1:$AH$28,5,0) -> 0.90303123 | BO6: =VLOOKUP(B6,[9]市州营业收现率2月完成!$B$1:$AI$28,5,0) -> 0.96194828 | BP6: =RANK(BO6,$BO$5:$BO$25,0) -> 10
A7: 3 | B7: 南充 | C7: 179641.91 | D7: 12469.679 | E7: 184491.85 | F7: 16842.183 | G7: =E7/C7-1 -> 0.026997813 | H7: =F7/D7-1 -> 0.3506509 | I7: =VLOOKUP(B7,[4]计算结果表!$B$1:$AA$25,13,0) -> 13775.583 | J7: =VLOOKUP(B7,[2]计算结果表!$B$1:$AA$25,13,0) -> 19561.609 | K7: =J7/I7-1 -> 0.42002039 | L7: =I7/C7 -> 0.076683569 | M7: =J7/E7 -> 0.10602966 | N7: =RANK(M7,$M$5:$M$25,1) -> 12 | O7: =M7-L7 -> 0.029346094 | P7: =VLOOKUP(B7,[4]计算结果表!$B$1:$AA$25,15,0) -> 6959.2669 | Q7: =VLOOKUP(B7,[2]计算结果表!$B$1:$AA$25,15,0) -> 10678.083 | R7: =Q7/P7-1 -> 0.53436898 | S7: =P7/D7 -> 0.55809513 | T7: =Q7/F7 -> 0.63400828 | U7: =RANK(T7,$T$5:$T$25,1) -> 19 | V7: =T7-S7 -> 0.075913152 | W7: =VLOOKUP(B7,[2]计算结果表!$B$1:$T$25,18,0) -> 1230.0327 | X7: =VLOOKUP(B7,[2]计算结果表!$B$1:$T$25,19,0) -> 9448.0506 | Y7: =VLOOKUP(B7,[1]分ICT资源型数据!$B$1:$P$23,11,0) -> 4709.5539 | Z7: =VLOOKUP(B7,[1]分ICT资源型数据!$B$1:$P$23,12,0) -> 9514.6753 | AA7: =W7/(Y7/11*12) -> 0.23941333 | AB7: =RANK(AA7,$AA$5:$AA$25,1) -> 10 | AC7: =X7/(Z7/11*12) -> 0.91024788 | AD7: =RANK(AC7,$AC$5:$AC$25,1) -> 20 | AE7: =VLOOKUP(B7,[4]计算结果表!$B$1:$T$25,16,0) -> 6816.3158 | AF7: =VLOOKUP(B7,[2]计算结果表!$B$1:$T$25,16,0) -> 8883.5252 | AG7: =AF7/AE7-1 -> 0.3032737 | AH7: =AE7/(C7-D7) -> 0.040774211 | AI7: =AF7/(E7-F7) -> 0.052988624 | AJ7: =RANK(AI7,$AI$5:$AI$25,1) -> 18 | AK7: =AI7-AH7 -> 0.012214413 | AL7: =VLOOKUP(B7,'[5]查询结果(2025年2月)'!$A$2:$L$29,12,0)/10000 -> 2750.383 | AM7: =VLOOKUP(B7,'[3]查询结果(2026年2月)'!$A$2:$L$29,12,0)/10000 -> 3941.5567 | AN7: =AM7/AL7-1 -> 0.43309377 | AO7: =RANK(AN7,$AN$5:$AN$25,1) -> 6 | AP7: =AL7/I7 -> 0.19965638 | AQ7: =AM7/J7 -> 0.20149451 | AR7: =RANK(AQ7,$AQ$5:$AQ$25,1) -> 14 | AS7: =VLOOKUP(B7,'[6]查询结果(2025年2月)'!$A$2:$L$29,12,0)/10000 -> 2438.9715 | AT7: =VLOOKUP(B7,'[7]查询结果(2026年2月)'!$A$2:$H$25,8,0)/10000 -> 3067.2601 | AU7: =AT7/Q7 -> 0.28724819 | AV7: =RANK(AU7,$AU$5:$AU$25,1) -> 17 | AW7: =AT7/AS7-1 -> 0.25760391 | AX7: =RANK(AW7,$AW$5:$AW$25,1) -> 6 | AY7: =VLOOKUP(B7,[4]计算结果表!$B$1:$T$25,17,0) -> 7706.4175 | AZ7: =VLOOKUP(B7,[2]计算结果表!$B$1:$T$25,17,0) -> 9912.5397 | BA7: =AZ7/AY7-1 -> 0.28627078 | BB7: =AY7/C7 -> 0.042898773 | BC7: =AZ7/E7 -> 0.053728876 | BD7: =RANK(BC7,$BC$5:$BC$25,0) -> 17 | BE7: =BC7-BB7 -> 0.010830103 | BF7: =VLOOKUP(B7,[4]计算结果表!$B$1:$T$25,9,0) -> 596.68992 | BG7: =VLOOKUP(B7,[2]计算结果表!$B$1:$T$25,9,0) -> 881.89786 | BH7: =BG7/BF7-1 -> 0.47798351 | BI7: =BF7/I7 -> 0.04331504 | BJ7: =BG7/J7 -> 0.045083095 | BK7: =RANK(BJ7,$BJ$5:$BJ$25,1) -> 13 | BL7: =VLOOKUP(B7,[8]市州营业收现率202502完成!$B$1:$AH$28,6,0) -> 29560.44 | BM7: =VLOOKUP(B7,[9]市州营业收现率2月完成!$B$1:$AI$28,7,0) -> 30202.632 | BN7: =VLOOKUP(B7,[8]市州营业收现率202502完成!$B$1:$AH$28,5,0) -> 0.9486663 | BO7: =VLOOKUP(B7,[9]市州营业收现率2月完成!$B$1:$AI$28,5,0) -> 0.98997423 | BP7: =RANK(BO7,$BO$5:$BO$25,0) -> 9
A8: 4 | B8: 泸州 | C8: 162553.55 | D8: 16331.369 | E8: 164815.2 | F8: 18361.204 | G8: =E8/C8-1 -> 0.013913294 | H8: =F8/D8-1 -> 0.12429054 | I8: =VLOOKUP(B8,[4]计算结果表!$B$1:$AA$25,13,0) -> 12522.229 | J8: =VLOOKUP(B8,[2]计算结果表!$B$1:$AA$25,13,0) -> 13657.438 | K8: =J8/I8-1 -> 0.090655544 | L8: =I8/C8 -> 0.077034484 | M8: =J8/E8 -> 0.08286516 | N8: =RANK(M8,$M$5:$M$25,1) -> 6 | O8: =M8-L8 -> 0.0058306757 | P8: =VLOOKUP(B8,[4]计算结果表!$B$1:$AA$25,15,0) -> 7588.0303 | Q8: =VLOOKUP(B8,[2]计算结果表!$B$1:$AA$25,15,0) -> 9443.8637 | R8: =Q8/P8-1 -> 0.24457381 | S8: =P8/D8 -> 0.46462915 | T8: =Q8/F8 -> 0.51433794 | U8: =RANK(T8,$T$5:$T$25,1) -> 13 | V8: =T8-S8 -> 0.049708785 | W8: =VLOOKUP(B8,[2]计算结果表!$B$1:$T$25,18,0) -> 1877.8122 | X8: =VLOOKUP(B8,[2]计算结果表!$B$1:$T$25,19,0) -> 7566.0516 | Y8: =VLOOKUP(B8,[1]分ICT资源型数据!$B$1:$P$23,11,0) -> 4667.5843 | Z8: =VLOOKUP(B8,[1]分ICT资源型数据!$B$1:$P$23,12,0) -> 9556.1832 | AA8: =W8/(Y8/11*12) -> 0.36878344 | AB8: =RANK(AA8,$AA$5:$AA$25,1) -> 18 | AC8: =X8/(Z8/11*12) -> 0.72576542 | AD8: =RANK(AC8,$AC$5:$AC$25,1) -> 14 | AE8: =VLOOKUP(B8,[4]计算结果表!$B$1:$T$25,16,0) -> 4934.1985 | AF8: =VLOOKUP(B8,[2]计算结果表!$B$1:$T$25,16,0) -> 4213.5745 | AG8: =AF8/AE8-1 -> -0.14604682 | AH8: =AE8/(C8-D8) -> 0.033744529 | AI8: =AF8/(E8-F8) -> 0.028770635 | AJ8: =RANK(AI8,$AI$5:$AI$25,1) -> 6 | AK8: =AI8-AH8 -> -0.0049738941 | AL8: =VLOOKUP(B8,'[5]查询结果(2025年2月)'!$A$2:$L$29,12,0)/10000 -> 1848.0054 | AM8: =VLOOKUP(B8,'[3]查询结果(2026年2月)'!$A$2:$L$29,12,0)/10000 -> 4136.8876 | AN8: =AM8/AL8-1 -> 1.238569 | AO8: =RANK(AN8,$AN$5:$AN$25,1) -> 12 | AP8: =AL8/I8 -> 0.147578 | AQ8: =AM8/J8 -> 0.30290363 | AR8: =RANK(AQ8,$AQ$5:$AQ$25,1) -> 19 | AS8: =VLOOKUP(B8,'[6]查询结果(2025年2月)'!$A$2:$L$29,12,0)/10000 -> 1192.0496 | AT8: =VLOOKUP(B8,'[7]查询结果(2026年2月)'!$A$2:$H$25,8,0)/10000 -> 3004.1469 | AU8: =AT8/Q8 -> 0.31810571 | AV8: =RANK(AU8,$AU$5:$AU$25,1) -> 19 | AW8: =AT8/AS8-1 -> 1.5201526 | AX8: =RANK(AW8,$AW$5:$AW$25,1) -> 11 | AY8: =VLOOKUP(B8,[4]计算结果表!$B$1:$T$25,17,0) -> 7850.1624 | AZ8: =VLOOKUP(B8,[2]计算结果表!$B$1:$T$25,17,0) -> 8176.6115 | BA8: =AZ8/AY8-1 -> 0.041585014 | BB8: =AY8/C8 -> 0.048292778 | BC8: =AZ8/E8 -> 0.049610784 | BD8: =RANK(BC8,$BC$5:$BC$25,0) -> 19 | BE8: =BC8-BB8 -> 0.0013180064 | BF8: =VLOOKUP(B8,[4]计算结果表!$B$1:$T$25,9,0) -> 584.4735 | BG8: =VLOOKUP(B8,[2]计算结果表!$B$1:$T$25,9,0) -> 1540.6634 | BH8: =BG8/BF8-1 -> 1.6359851 | BI8: =BF8/I8 -> 0.046674878 | BJ8: =BG8/J8 -> 0.11280764 | BK8: =RANK(BJ8,$BJ$5:$BJ$25,1) -> 21 | BL8: =VLOOKUP(B8,[8]市州营业收现率202502完成!$B$1:$AH$28,6,0) -> 24784.982 | BM8: =VLOOKUP(B8,[9]市州营业收现率2月完成!$B$1:$AI$28,7,0) -> 24775.508 | BN8: =VLOOKUP(B8,[8]市州营业收现率202502完成!$B$1:$AH$28,5,0) -> 0.89787713 | BO8: =VLOOKUP(B8,[9]市州营业收现率2月完成!$B$1:$AI$28,5,0) -> 0.92939689 | BP8: =RANK(BO8,$BO$5:$BO$25,0) -> 12
A9: 5 | B9: 凉山 | C9: 140988.95 | D9: 21848.297 | E9: 143570.12 | F9: 24548.12 | G9: =E9/C9-1 -> 0.018307588 | H9: =F9/D9-1 -> 0.12357131 | I9: =VLOOKUP(B9,[4]计算结果表!$B$1:$AA$25,13,0) -> 9388.6062 | J9: =VLOOKUP(B9,[2]计算结果表!$B$1:$AA$25,13,0) -> 15729.877 | K9: =J9/I9-1 -> 0.675422 | L9: =I9/C9 -> 0.066591077 | M9: =J9/E9 -> 0.10956233 | N9: =RANK(M9,$M$5:$M$25,1) -> 14 | O9: =M9-L9 -> 0.042971256 | P9: =VLOOKUP(B9,[4]计算结果表!$B$1:$AA$25,15,0) -> 6076.6026 | Q9: =VLOOKUP(B9,[2]计算结果表!$B$1:$AA$25,15,0) -> 9593.0773 | R9: =Q9/P9-1 -> 0.57869091 | S9: =P9/D9 -> 0.27812706 | T9: =Q9/F9 -> 0.39078664 | U9: =RANK(T9,$T$5:$T$25,1) -> 6 | V9: =T9-S9 -> 0.11265958 | W9: =VLOOKUP(B9,[2]计算结果表!$B$1:$T$25,18,0) -> 2341.4952 | X9: =VLOOKUP(B9,[2]计算结果表!$B$1:$T$25,19,0) -> 7251.5821 | Y9: =VLOOKUP(B9,[1]分ICT资源型数据!$B$1:$P$23,11,0) -> 8210.713 | Z9: =VLOOKUP(B9,[1]分ICT资源型数据!$B$1:$P$23,12,0) -> 11679.424 | AA9: =W9/(Y9/11*12) -> 0.26141098 | AB9: =RANK(AA9,$AA$5:$AA$25,1) -> 12 | AC9: =X9/(Z9/11*12) -> 0.56914482 | AD9: =RANK(AC9,$AC$5:$AC$25,1) -> 4 | AE9: =VLOOKUP(B9,[4]计算结果表!$B$1:$T$25,16,0) -> 3312.0036 | AF9: =VLOOKUP(B9,[2]计算结果表!$B$1:$T$25,16,0) -> 6136.8001 | AG9: =AF9/AE9-1 -> 0.85289655 | AH9: =AE9/(C9-D9) -> 0.027799106 | AI9: =AF9/(E9-F9) -> 0.051560217 | AJ9: =RANK(AI9,$AI$5:$AI$25,1) -> 17 | AK9: =AI9-AH9 -> 0.023761111 | AL9: =VLOOKUP(B9,'[5]查询结果(2025年2月)'!$A$2:$L$29,12,0)/10000 -> 557.06131 | AM9: =VLOOKUP(B9,'[3]查询结果(2026年2月)'!$A$2:$L$29,12,0)/10000 -> 2401.0917 | AN9: =AM9/AL9-1 -> 3.3102826 | AO9: =RANK(AN9,$AN$5:$AN$25,1) -> 21 | AP9: =AL9/I9 -> 0.05933376 | AQ9: =AM9/J9 -> 0.15264529 | AR9: =RANK(AQ9,$AQ$5:$AQ$25,1) -> 7 | AS9: =VLOOKUP(B9,'[6]查询结果(2025年2月)'!$A$2:$L$29,12,0)/10000 -> 210.26331 | AT9: =VLOOKUP(B9,'[7]查询结果(2026年2月)'!$A$2:$H$25,8,0)/10000 -> 1943.242 | AU9: =AT9/Q9 -> 0.20256712 | AV9: =RANK(AU9,$AU$5:$AU$25,1) -> 13 | AW9: =AT9/AS9-1 -> 8.2419453 | AX9: =RANK(AW9,$AW$5:$AW$25,1) -> 21 | AY9: =VLOOKUP(B9,[4]计算结果表!$B$1:$T$25,17,0) -> 10845.589 | AZ9: =VLOOKUP(B9,[2]计算结果表!$B$1:$T$25,17,0) -> 10805.973 | BA9: =AZ9/AY9-1 -> -0.0036527269 | BB9: =AY9/C9 -> 0.076925096 | BC9: =AZ9/E9 -> 0.075266167 | BD9: =RANK(BC9,$BC$5:$BC$25,0) -> 7 | BE9: =BC9-BB9 -> -0.0016589284 | BF9: =VLOOKUP(B9,[4]计算结果表!$B$1:$T$25,9,0) -> 188.91598 | BG9: =VLOOKUP(B9,[2]计算结果表!$B$1:$T$25,9,0) -> 635.9972 | BH9: =BG9/BF9-1 -> 2.3665611 | BI9: =BF9/I9 -> 0.020121835 | BJ9: =BG9/J9 -> 0.040432432 | BK9: =RANK(BJ9,$BJ$5:$BJ$25,1) -> 10 | BL9: =VLOOKUP(B9,[8]市州营业收现率202502完成!$B$1:$AH$28,6,0) -> 16824.857 | BM9: =VLOOKUP(B9,[9]市州营业收现率2月完成!$B$1:$AI$28,7,0) -> 16426.6 | BN9: =VLOOKUP(B9,[8]市州营业收现率202502完成!$B$1:$AH$28,5,0) -> 0.70105676 | BO9: =VLOOKUP(B9,[9]市州营业收现率2月完成!$B$1:$AI$28,5,0) -> 0.75596444 | BP9: =RANK(BO9,$BO$5:$BO$25,0) -> 18
A10: 6 | B10: 宜宾 | C10: 140557.38 | D10: 15542.303 | E10: 143827.88 | F10: 17370.963 | G10: =E10/C10-1 -> 0.02326806 | H10: =F10/D10-1 -> 0.11765701 | I10: =VLOOKUP(B10,[4]计算结果表!$B$1:$AA$25,13,0) -> 6946.3043 | J10: =VLOOKUP(B10,[2]计算结果表!$B$1:$AA$25,13,0) -> 14258.018 | K10: =J10/I10-1 -> 1.0526049 | L10: =I10/C10 -> 0.049419706 | M10: =J10/E10 -> 0.09913251 | N10: =RANK(M10,$M$5:$M$25,1) -> 9 | O10: =M10-L10 -> 0.049712804 | P10: =VLOOKUP(B10,[4]计算结果表!$B$1:$AA$25,15,0) -> 3982.8561 | Q10: =VLOOKUP(B10,[2]计算结果表!$B$1:$AA$25,15,0) -> 8980.274 | R10: =Q10/P10-1 -> 1.2547322 | S10: =P10/D10 -> 0.25625908 | T10: =Q10/F10 -> 0.51697041 | U10: =RANK(T10,$T$5:$T$25,1) -> 14 | V10: =T10-S10 -> 0.26071133 | W10: =VLOOKUP(B10,[2]计算结果表!$B$1:$T$25,18,0) -> 1655.6159 | X10: =VLOOKUP(B10,[2]计算结果表!$B$1:$T$25,19,0) -> 7324.6581 | Y10: =VLOOKUP(B10,[1]分ICT资源型数据!$B$1:$P$23,11,0) -> 14290.476 | Z10: =VLOOKUP(B10,[1]分ICT资源型数据!$B$1:$P$23,12,0) -> 10162.645 | AA10: =W10/(Y10/11*12) -> 0.10619995 | AB10: =RANK(AA10,$AA$5:$AA$25,1) -> 2 | AC10: =X10/(Z10/11*12) -> 0.66068136 | AD10: =RANK(AC10,$AC$5:$AC$25,1) -> 11 | AE10: =VLOOKUP(B10,[4]计算结果表!$B$1:$T$25,16,0) -> 2963.4482 | AF10: =VLOOKUP(B10,[2]计算结果表!$B$1:$T$25,16,0) -> 5277.7443 | AG10: =AF10/AE10-1 -> 0.78094705 | AH10: =AE10/(C10-D10) -> 0.023704727 | AI10: =AF10/(E10-F10) -> 0.041735515 | AJ10: =RANK(AI10,$AI$5:$AI$25,1) -> 14 | AK10: =AI10-AH10 -> 0.018030788 | AL10: =VLOOKUP(B10,'[5]查询结果(2025年2月)'!$A$2:$L$29,12,0)/10000 -> 635.96602 | AM10: =VLOOKUP(B10,'[3]查询结果(2026年2月)'!$A$2:$L$29,12,0)/10000 -> 2048.8486 | AN10: =AM10/AL10-1 -> 2.2216322 | AO10: =RANK(AN10,$AN$5:$AN$25,1) -> 19 | AP10: =AL10/I10 -> 0.091554587 | AQ10: =AM10/J10 -> 0.14369799 | AR10: =RANK(AQ10,$AQ$5:$AQ$25,1) -> 5 | AS10: =VLOOKUP(B10,'[6]查询结果(2025年2月)'!$A$2:$L$29,12,0)/10000 -> 237.89511 | AT10: =VLOOKUP(B10,'[7]查询结果(2026年2月)'!$A$2:$H$25,8,0)/10000 -> 1572.3023 | AU10: =AT10/Q10 -> 0.175084 | AV10: =RANK(AU10,$AU$5:$AU$25,1) -> 10 | AW10: =AT10/AS10-1 -> 5.6092251 | AX10: =RANK(AW10,$AW$5:$AW$25,1) -> 20 | AY10: =VLOOKUP(B10,[4]计算结果表!$B$1:$T$25,17,0) -> 7330.2701 | AZ10: =VLOOKUP(B10,[2]计算结果表!$B$1:$T$25,17,0) -> 7029.4753 | BA10: =AZ10/AY10-1 -> -0.041034609 | BB10: =AY10/C10 -> 0.052151443 | BC10: =AZ10/E10 -> 0.04887422 | BD10: =RANK(BC10,$BC$5:$BC$25,0) -> 20 | BE10: =BC10-BB10 -> -0.0032772224 | BF10: =VLOOKUP(B10,[4]计算结果表!$B$1:$T$25,9,0) -> -157.97647 | BG10: =VLOOKUP(B10,[2]计算结果表!$B$1:$T$25,9,0) -> 1072.294 | BH10: =BG10/BF10-1 -> -7.7876818 | BI10: =BF10/I10 -> -0.022742521 | BJ10: =BG10/J10 -> 0.075206385 | BK10: =RANK(BJ10,$BJ$5:$BJ$25,1) -> 19 | BL10: =VLOOKUP(B10,[8]市州营业收现率202502完成!$B$1:$AH$28,6,0) -> 23393.046 | BM10: =VLOOKUP(B10,[9]市州营业收现率2月完成!$B$1:$AI$28,7,0) -> 24069.073 | BN10: =VLOOKUP(B10,[8]市州营业收现率202502完成!$B$1:$AH$28,5,0) -> 0.96384241 | BO10: =VLOOKUP(B10,[9]市州营业收现率2月完成!$B$1:$AI$28,5,0) -> 0.99857642 | BP10: =RANK(BO10,$BO$5:$BO$25,0) -> 7
A11: 7 | B11: 达州 | C11: 120354.81 | D11: 12304.33 | E11: 122765.28 | F11: 14143.315 | G11: =E11/C11-1 -> 0.020028035 | H11: =F11/D11-1 -> 0.14945837 | I11: =VLOOKUP(B11,[4]计算结果表!$B$1:$AA$25,13,0) -> 10016.415 | J11: =VLOOKUP(B11,[2]计算结果表!$B$1:$AA$25,13,0) -> 12842.698 | K11: =J11/I11-1 -> 0.28216509 | L11: =I11/C11 -> 0.083224053 | M11: =J11/E11 -> 0.10461181 | N11: =RANK(M11,$M$5:$M$25,1) -> 11 | O11: =M11-L11 -> 0.021387753 | P11: =VLOOKUP(B11,[4]计算结果表!$B$1:$AA$25,15,0) -> 5015.9046 | Q11: =VLOOKUP(B11,[2]计算结果表!$B$1:$AA$25,15,0) -> 6984.4808 | R11: =Q11/P11-1 -> 0.39246683 | S11: =P11/D11 -> 0.40765361 | T11: =Q11/F11 -> 0.49383619 | U11: =RANK(T11,$T$5:$T$25,1) -> 11 | V11: =T11-S11 -> 0.086182571 | W11: =VLOOKUP(B11,[2]计算结果表!$B$1:$T$25,18,0) -> 1509.3704 | X11: =VLOOKUP(B11,[2]计算结果表!$B$1:$T$25,19,0) -> 5475.1104 | Y11: =VLOOKUP(B11,[1]分ICT资源型数据!$B$1:$P$23,11,0) -> 5255.2011 | Z11: =VLOOKUP(B11,[1]分ICT资源型数据!$B$1:$P$23,12,0) -> 6252.9076 | AA11: =W11/(Y11/11*12) -> 0.26328003 | AB11: =RANK(AA11,$AA$5:$AA$25,1) -> 13 | AC11: =X11/(Z11/11*12) -> 0.80264278 | AD11: =RANK(AC11,$AC$5:$AC$25,1) -> 17 | AE11: =VLOOKUP(B11,[4]计算结果表!$B$1:$T$25,16,0) -> 5000.5104 | AF11: =VLOOKUP(B11,[2]计算结果表!$B$1:$T$25,16,0) -> 5858.2168 | AG11: =AF11/AE11-1 -> 0.17152377 | AH11: =AE11/(C11-D11) -> 0.046279391 | AI11: =AF11/(E11-F11) -> 0.053932157 | AJ11: =RANK(AI11,$AI$5:$AI$25,1) -> 19 | AK11: =AI11-AH11 -> 0.0076527655 | AL11: =VLOOKUP(B11,'[5]查询结果(2025年2月)'!$A$2:$L$29,12,0)/10000 -> 1791.2999 | AM11: =VLOOKUP(B11,'[3]查询结果(2026年2月)'!$A$2:$L$29,12,0)/10000 -> 5251.8644 | AN11: =AM11/AL11-1 -> 1.9318734 | AO11: =RANK(AN11,$AN$5:$AN$25,1) -> 18 | AP11: =AL11/I11 -> 0.17883643 | AQ11: =AM11/J11 -> 0.40893779 | AR11: =RANK(AQ11,$AQ$5:$AQ$25,1) -> 21 | AS11: =VLOOKUP(B11,'[6]查询结果(2025年2月)'!$A$2:$L$29,12,0)/10000 -> 1080.5492 | AT11: =VLOOKUP(B11,'[7]查询结果(2026年2月)'!$A$2:$H$25,8,0)/10000 -> 3721.6028 | AU11: =AT11/Q11 -> 0.53283887 | AV11: =RANK(AU11,$AU$5:$AU$25,1) -> 21 | AW11: =AT11/AS11-1 -> 2.4441772 | AX11: =RANK(AW11,$AW$5:$AW$25,1) -> 15 | AY11: =VLOOKUP(B11,[4]计算结果表!$B$1:$T$25,17,0) -> 6801.3577 | AZ11: =VLOOKUP(B11,[2]计算结果表!$B$1:$T$25,17,0) -> 8463.8306 | BA11: =AZ11/AY11-1 -> 0.24443251 | BB11: =AY11/C11 -> 0.056510893 | BC11: =AZ11/E11 -> 0.068943195 | BD11: =RANK(BC11,$BC$5:$BC$25,0) -> 10 | BE11: =BC11-BB11 -> 0.012432303 | BF11: =VLOOKUP(B11,[4]计算结果表!$B$1:$T$25,9,0) -> -176.7159 | BG11: =VLOOKUP(B11,[2]计算结果表!$B$1:$T$25,9,0) -> -84.419841 | BH11: =BG11/BF11-1 -> -0.52228498 | BI11: =BF11/I11 -> -0.01764263 | BJ11: =BG11/J11 -> -0.006573373 | BK11: =RANK(BJ11,$BJ$5:$BJ$25,1) -> 2 | BL11: =VLOOKUP(B11,[8]市州营业收现率202502完成!$B$1:$AH$28,6,0) -> 19778.615 | BM11: =VLOOKUP(B11,[9]市州营业收现率2月完成!$B$1:$AI$28,7,0) -> 21257.25 | BN11: =VLOOKUP(B11,[8]市州营业收现率202502完成!$B$1:$AH$28,5,0) -> 0.9383321 | BO11: =VLOOKUP(B11,[9]市州营业收现率2月完成!$B$1:$AI$28,5,0) -> 1.0866958 | BP11: =RANK(BO11,$BO$5:$BO$25,0) -> 1
A12: 8 | B12: 乐山 | C12: 120556.02 | D12: 16066.625 | E12: 122400.42 | F12: 18070.418 | G12: =E12/C12-1 -> 0.015299071 | H12: =F12/D12-1 -> 0.12471774 | I12: =VLOOKUP(B12,[4]计算结果表!$B$1:$AA$25,13,0) -> 12485.608 | J12: =VLOOKUP(B12,[2]计算结果表!$B$1:$AA$25,13,0) -> 14479.409 | K12: =J12/I12-1 -> 0.15968791 | L12: =I12/C12 -> 0.10356686 | M12: =J12/E12 -> 0.11829542 | N12: =RANK(M12,$M$5:$M$25,1) -> 17 | O12: =M12-L12 -> 0.014728565 | P12: =VLOOKUP(B12,[4]计算结果表!$B$1:$AA$25,15,0) -> 9145.5356 | Q12: =VLOOKUP(B12,[2]计算结果表!$B$1:$AA$25,15,0) -> 10884.227 | R12: =Q12/P12-1 -> 0.19011367 | S12: =P12/D12 -> 0.56922569 | T12: =Q12/F12 -> 0.60232292 | U12: =RANK(T12,$T$5:$T$25,1) -> 18 | V12: =T12-S12 -> 0.033097229 | W12: =VLOOKUP(B12,[2]计算结果表!$B$1:$T$25,18,0) -> 1542.4468 | X12: =VLOOKUP(B12,[2]计算结果表!$B$1:$T$25,19,0) -> 9341.7801 | Y12: =VLOOKUP(B12,[1]分ICT资源型数据!$B$1:$P$23,11,0) -> 5076.3412 | Z12: =VLOOKUP(B12,[1]分ICT资源型数据!$B$1:$P$23,12,0) -> 9917.686 | AA12: =W12/(Y12/11*12) -> 0.27852926 | AB12: =RANK(AA12,$AA$5:$AA$25,1) -> 15 | AC12: =X12/(Z12/11*12) -> 0.86343714 | AD12: =RANK(AC12,$AC$5:$AC$25,1) -> 18 | AE12: =VLOOKUP(B12,[4]计算结果表!$B$1:$T$25,16,0) -> 3340.0728 | AF12: =VLOOKUP(B12,[2]计算结果表!$B$1:$T$25,16,0) -> 3595.1822 | AG12: =AF12/AE12-1 -> 0.076378403 | AH12: =AE12/(C12-D12) -> 0.031965662 | AI12: =AF12/(E12-F12) -> 0.034459717 | AJ12: =RANK(AI12,$AI$5:$AI$25,1) -> 7 | AK12: =AI12-AH12 -> 0.0024940544 | AL12: =VLOOKUP(B12,'[5]查询结果(2025年2月)'!$A$2:$L$29,12,0)/10000 -> 1795.8756 | AM12: =VLOOKUP(B12,'[3]查询结果(2026年2月)'!$A$2:$L$29,12,0)/10000 -> 3495.2904 | AN12: =AM12/AL12-1 -> 0.94628763 | AO12: =RANK(AN12,$AN$5:$AN$25,1) -> 9 | AP12: =AL12/I12 -> 0.14383565 | AQ12: =AM12/J12 -> 0.24139731 | AR12: =RANK(AQ12,$AQ$5:$AQ$25,1) -> 16 | AS12: =VLOOKUP(B12,'[6]查询结果(2025年2月)'!$A$2:$L$29,12,0)/10000 -> 1439.4212 | AT12: =VLOOKUP(B12,'[7]查询结果(2026年2月)'!$A$2:$H$25,8,0)/10000 -> 2951.6896 | AU12: =AT12/Q12 -> 0.27118964 | AV12: =RANK(AU12,$AU$5:$AU$25,1) -> 15 | AW12: =AT12/AS12-1 -> 1.0506087 | AX12: =RANK(AW12,$AW$5:$AW$25,1) -> 8 | AY12: =VLOOKUP(B12,[4]计算结果表!$B$1:$T$25,17,0) -> 6949.4968 | AZ12: =VLOOKUP(B12,[2]计算结果表!$B$1:$T$25,17,0) -> 6880.3957 | BA12: =AZ12/AY12-1 -> -0.0099433213 | BB12: =AY12/C12 -> 0.057645372 | BC12: =AZ12/E12 -> 0.056212192 | BD12: =RANK(BC12,$BC$5:$BC$25,0) -> 16 | BE12: =BC12-BB12 -> -0.0014331807 | BF12: =VLOOKUP(B12,[4]计算结果表!$B$1:$T$25,9,0) -> 390.62763 | BG12: =VLOOKUP(B12,[2]计算结果表!$B$1:$T$25,9,0) -> 644.49704 | BH12: =BG12/BF12-1 -> 0.64990132 | BI12: =BF12/I12 -> 0.031286231 | BJ12: =BG12/J12 -> 0.04451128 | BK12: =RANK(BJ12,$BJ$5:$BJ$25,1) -> 12 | BL12: =VLOOKUP(B12,[8]市州营业收现率202502完成!$B$1:$AH$28,6,0) -> 18122.265 | BM12: =VLOOKUP(B12,[9]市州营业收现率2月完成!$B$1:$AI$28,7,0) -> 19664.989 | BN12: =VLOOKUP(B12,[8]市州营业收现率202502完成!$B$1:$AH$28,5,0) -> 0.85952724 | BO12: =VLOOKUP(B12,[9]市州营业收现率2月完成!$B$1:$AI$28,5,0) -> 1.0428282 | BP12: =RANK(BO12,$BO$5:$BO$25,0) -> 2
A13: 9 | B13: 眉山 | C13: 120948.42 | D13: 19113.598 | E13: 121392.76 | F13: 21043.959 | G13: =E13/C13-1 -> 0.0036737762 | H13: =F13/D13-1 -> 0.10099414 | I13: =VLOOKUP(B13,[4]计算结果表!$B$1:$AA$25,13,0) -> 4685.9477 | J13: =VLOOKUP(B13,[2]计算结果表!$B$1:$AA$25,13,0) -> 12474.001 | K13: =J13/I13-1 -> 1.6620017 | L13: =I13/C13 -> 0.038743356 | M13: =J13/E13 -> 0.10275737 | N13: =RANK(M13,$M$5:$M$25,1) -> 10 | O13: =M13-L13 -> 0.064014016 | P13: =VLOOKUP(B13,[4]计算结果表!$B$1:$AA$25,15,0) -> 2169.3814 | Q13: =VLOOKUP(B13,[2]计算结果表!$B$1:$AA$25,15,0) -> 8494.6949 | R13: =Q13/P13-1 -> 2.9157221 | S13: =P13/D13 -> 0.11349938 | T13: =Q13/F13 -> 0.40366429 | U13: =RANK(T13,$T$5:$T$25,1) -> 7 | V13: =T13-S13 -> 0.29016492 | W13: =VLOOKUP(B13,[2]计算结果表!$B$1:$T$25,18,0) -> 763.5643 | X13: =VLOOKUP(B13,[2]计算结果表!$B$1:$T$25,19,0) -> 7731.1306 | Y13: =VLOOKUP(B13,[1]分ICT资源型数据!$B$1:$P$23,11,0) -> 4509.3063 | Z13: =VLOOKUP(B13,[1]分ICT资源型数据!$B$1:$P$23,12,0) -> 11160.163 | AA13: =W13/(Y13/11*12) -> 0.15521987 | AB13: =RANK(AA13,$AA$5:$AA$25,1) -> 4 | AC13: =X13/(Z13/11*12) -> 0.63501487 | AD13: =RANK(AC13,$AC$5:$AC$25,1) -> 10 | AE13: =VLOOKUP(B13,[4]计算结果表!$B$1:$T$25,16,0) -> 2516.5662 | AF13: =VLOOKUP(B13,[2]计算结果表!$B$1:$T$25,16,0) -> 3979.3058 | AG13: =AF13/AE13-1 -> 0.58124423 | AH13: =AE13/(C13-D13) -> 0.024712237 | AI13: =AF13/(E13-F13) -> 0.039654744 | AJ13: =RANK(AI13,$AI$5:$AI$25,1) -> 12 | AK13: =AI13-AH13 -> 0.014942507 | AL13: =VLOOKUP(B13,'[5]查询结果(2025年2月)'!$A$2:$L$29,12,0)/10000 -> 229.48672 | AM13: =VLOOKUP(B13,'[3]查询结果(2026年2月)'!$A$2:$L$29,12,0)/10000 -> 868.74507 | AN13: =AM13/AL13-1 -> 2.7856006 | AO13: =RANK(AN13,$AN$5:$AN$25,1) -> 20 | AP13: =AL13/I13 -> 0.048973386 | AQ13: =AM13/J13 -> 0.069644462 | AR13: =RANK(AQ13,$AQ$5:$AQ$25,1) -> 1 | AS13: =VLOOKUP(B13,'[6]查询结果(2025年2月)'!$A$2:$L$29,12,0)/10000 -> 121.25646 | AT13: =VLOOKUP(B13,'[7]查询结果(2026年2月)'!$A$2:$H$25,8,0)/10000 -> 574.54565 | AU13: =AT13/Q13 -> 0.06763582 | AV13: =RANK(AU13,$AU$5:$AU$25,1) -> 2 | AW13: =AT13/AS13-1 -> 3.7382685 | AX13: =RANK(AW13,$AW$5:$AW$25,1) -> 19 | AY13: =VLOOKUP(B13,[4]计算结果表!$B$1:$T$25,17,0) -> 7722.5193 | AZ13: =VLOOKUP(B13,[2]计算结果表!$B$1:$T$25,17,0) -> 7005.9634 | BA13: =AZ13/AY13-1 -> -0.092787844 | BB13: =AY13/C13 -> 0.063849692 | BC13: =AZ13/E13 -> 0.057713192 | BD13: =RANK(BC13,$BC$5:$BC$25,0) -> 15 | BE13: =BC13-BB13 -> -0.0061365006 | BF13: =VLOOKUP(B13,[4]计算结果表!$B$1:$T$25,9,0) -> 82.655001 | BG13: =VLOOKUP(B13,[2]计算结果表!$B$1:$T$25,9,0) -> 440.99341 | BH13: =BG13/BF13-1 -> 4.3353507 | BI13: =BF13/I13 -> 0.017638908 | BJ13: =BG13/J13 -> 0.035353005 | BK13: =RANK(BJ13,$BJ$5:$BJ$25,1) -> 8 | BL13: =VLOOKUP(B13,[8]市州营业收现率202502完成!$B$1:$AH$28,6,0) -> 15886.505 | BM13: =VLOOKUP(B13,[9]市州营业收现率2月完成!$B$1:$AI$28,7,0) -> 18495.817 | BN13: =VLOOKUP(B13,[8]市州营业收现率202502完成!$B$1:$AH$28,5,0) -> 0.77275705 | BO13: =VLOOKUP(B13,[9]市州营业收现率2月完成!$B$1:$AI$28,5,0) -> 1.0108906 | BP13: =RANK(BO13,$BO$5:$BO$25,0) -> 6
A14: 10 | B14: 德阳 | C14: 108454.18 | D14: 14837.504 | E14: 112086.05 | F14: 18088.049 | G14: =E14/C14-1 -> 0.033487614 | H14: =F14/D14-1 -> 0.21907629 | I14: =VLOOKUP(B14,[4]计算结果表!$B$1:$AA$25,13,0) -> 10204.38 | J14: =VLOOKUP(B14,[2]计算结果表!$B$1:$AA$25,13,0) -> 13032.556 | K14: =J14/I14-1 -> 0.27715315 | L14: =I14/C14 -> 0.094089321 | M14: =J14/E14 -> 0.11627278 | N14: =RANK(M14,$M$5:$M$25,1) -> 16 | O14: =M14-L14 -> 0.022183454 | P14: =VLOOKUP(B14,[4]计算结果表!$B$1:$AA$25,15,0) -> 7272.0362 | Q14: =VLOOKUP(B14,[2]计算结果表!$B$1:$AA$25,15,0) -> 9532.1095 | R14: =Q14/P14-1 -> 0.31078961 | S14: =P14/D14 -> 0.49011183 | T14: =Q14/F14 -> 0.52698384 | U14: =RANK(T14,$T$5:$T$25,1) -> 15 | V14: =T14-S14 -> 0.036872002 | W14: =VLOOKUP(B14,[2]计算结果表!$B$1:$T$25,18,0) -> 2779.5024 | X14: =VLOOKUP(B14,[2]计算结果表!$B$1:$T$25,19,0) -> 6752.6072 | Y14: =VLOOKUP(B14,[1]分ICT资源型数据!$B$1:$P$23,11,0) -> 6173.3756 | Z14: =VLOOKUP(B14,[1]分ICT资源型数据!$B$1:$P$23,12,0) -> 8441.6019 | AA14: =W14/(Y14/11*12) -> 0.41272025 | AB14: =RANK(AA14,$AA$5:$AA$25,1) -> 19 | AC14: =X14/(Z14/11*12) -> 0.73326011 | AD14: =RANK(AC14,$AC$5:$AC$25,1) -> 15 | AE14: =VLOOKUP(B14,[4]计算结果表!$B$1:$T$25,16,0) -> 2932.3437 | AF14: =VLOOKUP(B14,[2]计算结果表!$B$1:$T$25,16,0) -> 3500.4465 | AG14: =AF14/AE14-1 -> 0.19373677 | AH14: =AE14/(C14-D14) -> 0.031322879 | AI14: =AF14/(E14-F14) -> 0.037239585 | AJ14: =RANK(AI14,$AI$5:$AI$25,1) -> 9 | AK14: =AI14-AH14 -> 0.0059167063 | AL14: =VLOOKUP(B14,'[5]查询结果(2025年2月)'!$A$2:$L$29,12,0)/10000 -> 893.65949 | AM14: =VLOOKUP(B14,'[3]查询结果(2026年2月)'!$A$2:$L$29,12,0)/10000 -> 2520.7687 | AN14: =AM14/AL14-1 -> 1.8207262 | AO14: =RANK(AN14,$AN$5:$AN$25,1) -> 15 | AP14: =AL14/I14 -> 0.08757607 | AQ14: =AM14/J14 -> 0.1934209 | AR14: =RANK(AQ14,$AQ$5:$AQ$25,1) -> 12 | AS14: =VLOOKUP(B14,'[6]查询结果(2025年2月)'!$A$2:$L$29,12,0)/10000 -> 638.04381 | AT14: =VLOOKUP(B14,'[7]查询结果(2026年2月)'!$A$2:$H$25,8,0)/10000 -> 1916.3483 | AU14: =AT14/Q14 -> 0.20104136 | AV14: =RANK(AU14,$AU$5:$AU$25,1) -> 12 | AW14: =AT14/AS14-1 -> 2.0034745 | AX14: =RANK(AW14,$AW$5:$AW$25,1) -> 13 | AY14: =VLOOKUP(B14,[4]计算结果表!$B$1:$T$25,17,0) -> 8445.1103 | AZ14: =VLOOKUP(B14,[2]计算结果表!$B$1:$T$25,17,0) -> 8263.2151 | BA14: =AZ14/AY14-1 -> -0.021538529 | BB14: =AY14/C14 -> 0.077868004 | BC14: =AZ14/E14 -> 0.073722066 | BD14: =RANK(BC14,$BC$5:$BC$25,0) -> 8 | BE14: =BC14-BB14 -> -0.0041459383 | BF14: =VLOOKUP(B14,[4]计算结果表!$B$1:$T$25,9,0) -> 5.03497 | BG14: =VLOOKUP(B14,[2]计算结果表!$B$1:$T$25,9,0) -> 855.26693 | BH14: =BG14/BF14-1 -> 168.86535 | BI14: =BF14/I14 -> 0.00049341263 | BJ14: =BG14/J14 -> 0.065625418 | BK14: =RANK(BJ14,$BJ$5:$BJ$25,1) -> 17 | BL14: =VLOOKUP(B14,[8]市州营业收现率202502完成!$B$1:$AH$28,6,0) -> 14697.057 | BM14: =VLOOKUP(B14,[9]市州营业收现率2月完成!$B$1:$AI$28,7,0) -> 14271.847 | BN14: =VLOOKUP(B14,[8]市州营业收现率202502完成!$B$1:$AH$28,5,0) -> 0.78237014 | BO14: =VLOOKUP(B14,[9]市州营业收现率2月完成!$B$1:$AI$28,5,0) -> 0.81410911 | BP14: =RANK(BO14,$BO$5:$BO$25,0) -> 16
A15: 11 | B15: 内江 | C15: 87486.809 | D15: 8336.977 | E15: 88473.879 | F15: 9659.8786 | G15: =E15/C15-1 -> 0.011282493 | H15: =F15/D15-1 -> 0.15867881 | I15: =VLOOKUP(B15,[4]计算结果表!$B$1:$AA$25,13,0) -> 6492.3187 | J15: =VLOOKUP(B15,[2]计算结果表!$B$1:$AA$25,13,0) -> 6998.6304 | K15: =J15/I15-1 -> 0.077986263 | L15: =I15/C15 -> 0.074209115 | M15: =J15/E15 -> 0.079103917 | N15: =RANK(M15,$M$5:$M$25,1) -> 5 | O15: =M15-L15 -> 0.0048948022 | P15: =VLOOKUP(B15,[4]计算结果表!$B$1:$AA$25,15,0) -> 3954.6354 | Q15: =VLOOKUP(B15,[2]计算结果表!$B$1:$AA$25,15,0) -> 4179.3615 | R15: =Q15/P15-1 -> 0.056825981 | S15: =P15/D15 -> 0.47434885 | T15: =Q15/F15 -> 0.43265155 | U15: =RANK(T15,$T$5:$T$25,1) -> 9 | V15: =T15-S15 -> -0.041697295 | W15: =VLOOKUP(B15,[2]计算结果表!$B$1:$T$25,18,0) -> 766.36026 | X15: =VLOOKUP(B15,[2]计算结果表!$B$1:$T$25,19,0) -> 3413.0012 | Y15: =VLOOKUP(B15,[1]分ICT资源型数据!$B$1:$P$23,11,0) -> 2930.5434 | Z15: =VLOOKUP(B15,[1]分ICT资源型数据!$B$1:$P$23,12,0) -> 5194.1508 | AA15: =W15/(Y15/11*12) -> 0.23971558 | AB15: =RANK(AA15,$AA$5:$AA$25,1) -> 11 | AC15: =X15/(Z15/11*12) -> 0.60232838 | AD15: =RANK(AC15,$AC$5:$AC$25,1) -> 6 | AE15: =VLOOKUP(B15,[4]计算结果表!$B$1:$T$25,16,0) -> 2537.6833 | AF15: =VLOOKUP(B15,[2]计算结果表!$B$1:$T$25,16,0) -> 2819.2689 | AG15: =AF15/AE15-1 -> 0.11096169 | AH15: =AE15/(C15-D15) -> 0.032061764 | AI15: =AF15/(E15-F15) -> 0.035771169 | AJ15: =RANK(AI15,$AI$5:$AI$25,1) -> 8 | AK15: =AI15-AH15 -> 0.0037094045 | AL15: =VLOOKUP(B15,'[5]查询结果(2025年2月)'!$A$2:$L$29,12,0)/10000 -> 1479.1543 | AM15: =VLOOKUP(B15,'[3]查询结果(2026年2月)'!$A$2:$L$29,12,0)/10000 -> 943.91993 | AN15: =AM15/AL15-1 -> -0.36185163 | AO15: =RANK(AN15,$AN$5:$AN$25,1) -> 2 | AP15: =AL15/I15 -> 0.22783144 | AQ15: =AM15/J15 -> 0.13487209 | AR15: =RANK(AQ15,$AQ$5:$AQ$25,1) -> 4 | AS15: =VLOOKUP(B15,'[6]查询结果(2025年2月)'!$A$2:$L$29,12,0)/10000 -> 1213.289 | AT15: =VLOOKUP(B15,'[7]查询结果(2026年2月)'!$A$2:$H$25,8,0)/10000 -> 672.28171 | AU15: =AT15/Q15 -> 0.16085752 | AV15: =RANK(AU15,$AU$5:$AU$25,1) -> 7 | AW15: =AT15/AS15-1 -> -0.44590141 | AX15: =RANK(AW15,$AW$5:$AW$25,1) -> 1 | AY15: =VLOOKUP(B15,[4]计算结果表!$B$1:$T$25,17,0) -> 4416.2998 | AZ15: =VLOOKUP(B15,[2]计算结果表!$B$1:$T$25,17,0) -> 5235.8243 | BA15: =AZ15/AY15-1 -> 0.18556813 | BB15: =AY15/C15 -> 0.050479608 | BC15: =AZ15/E15 -> 0.059179323 | BD15: =RANK(BC15,$BC$5:$BC$25,0) -> 14 | BE15: =BC15-BB15 -> 0.0086997159 | BF15: =VLOOKUP(B15,[4]计算结果表!$B$1:$T$25,9,0) -> -365.89539 | BG15: =VLOOKUP(B15,[2]计算结果表!$B$1:$T$25,9,0) -> 274.34438 | BH15: =BG15/BF15-1 -> -1.7497891 | BI15: =BF15/I15 -> -0.056358199 | BJ15: =BG15/J15 -> 0.039199725 | BK15: =RANK(BJ15,$BJ$5:$BJ$25,1) -> 9 | BL15: =VLOOKUP(B15,[8]市州营业收现率202502完成!$B$1:$AH$28,6,0) -> 14579.126 | BM15: =VLOOKUP(B15,[9]市州营业收现率2月完成!$B$1:$AI$28,7,0) -> 14815.526 | BN15: =VLOOKUP(B15,[8]市州营业收现率202502完成!$B$1:$AH$28,5,0) -> 1.0017809 | BO15: =VLOOKUP(B15,[9]市州营业收现率2月完成!$B$1:$AI$28,5,0) -> 1.0381763 | BP15: =RANK(BO15,$BO$5:$BO$25,0) -> 4
A16: 12 | B16: 巴中 | C16: 77707.532 | D16: 7596.7086 | E16: 78754.27 | F16: 8513.2697 | G16: =E16/C16-1 -> 0.013470215 | H16: =F16/D16-1 -> 0.12065239 | I16: =VLOOKUP(B16,[4]计算结果表!$B$1:$AA$25,13,0) -> 9706.4294 | J16: =VLOOKUP(B16,[2]计算结果表!$B$1:$AA$25,13,0) -> 11225.369 | K16: =J16/I16-1 -> 0.15648802 | L16: =I16/C16 -> 0.12490976 | M16: =J16/E16 -> 0.14253664 | N16: =RANK(M16,$M$5:$M$25,1) -> 20 | O16: =M16-L16 -> 0.017626881 | P16: =VLOOKUP(B16,[4]计算结果表!$B$1:$AA$25,15,0) -> 6668.3593 | Q16: =VLOOKUP(B16,[2]计算结果表!$B$1:$AA$25,15,0) -> 8446.2814 | R16: =Q16/P16-1 -> 0.26662061 | S16: =P16/D16 -> 0.87779585 | T16: =Q16/F16 -> 0.99213131 | U16: =RANK(T16,$T$5:$T$25,1) -> 21 | V16: =T16-S16 -> 0.11433545 | W16: =VLOOKUP(B16,[2]计算结果表!$B$1:$T$25,18,0) -> 1115.2311 | X16: =VLOOKUP(B16,[2]计算结果表!$B$1:$T$25,19,0) -> 7331.0503 | Y16: =VLOOKUP(B16,[1]分ICT资源型数据!$B$1:$P$23,11,0) -> 2237.2388 | Z16: =VLOOKUP(B16,[1]分ICT资源型数据!$B$1:$P$23,12,0) -> 6966.1722 | AA16: =W16/(Y16/11*12) -> 0.45694503 | AB16: =RANK(AA16,$AA$5:$AA$25,1) -> 21 | AC16: =X16/(Z16/11*12) -> 0.96468035 | AD16: =RANK(AC16,$AC$5:$AC$25,1) -> 21 | AE16: =VLOOKUP(B16,[4]计算结果表!$B$1:$T$25,16,0) -> 3038.0701 | AF16: =VLOOKUP(B16,[2]计算结果表!$B$1:$T$25,16,0) -> 2779.0879 | AG16: =AF16/AE16-1 -> -0.085245625 | AH16: =AE16/(C16-D16) -> 0.043332397 | AI16: =AF16/(E16-F16) -> 0.039565039 | AJ16: =RANK(AI16,$AI$5:$AI$25,1) -> 11 | AK16: =AI16-AH16 -> -0.0037673584 | AL16: =VLOOKUP(B16,'[5]查询结果(2025年2月)'!$A$2:$L$29,12,0)/10000 -> 1838.8852 | AM16: =VLOOKUP(B16,'[3]查询结果(2026年2月)'!$A$2:$L$29,12,0)/10000 -> 3371.2939 | AN16: =AM16/AL16-1 -> 0.8333357 | AO16: =RANK(AN16,$AN$5:$AN$25,1) -> 8 | AP16: =AL16/I16 -> 0.18945022 | AQ16: =AM16/J16 -> 0.30032811 | AR16: =RANK(AQ16,$AQ$5:$AQ$25,1) -> 18 | AS16: =VLOOKUP(B16,'[6]查询结果(2025年2月)'!$A$2:$L$29,12,0)/10000 -> 1075.225 | AT16: =VLOOKUP(B16,'[7]查询结果(2026年2月)'!$A$2:$H$25,8,0)/10000 -> 2527.311 | AU16: =AT16/Q16 -> 0.29922174 | AV16: =RANK(AU16,$AU$5:$AU$25,1) -> 18 | AW16: =AT16/AS16-1 -> 1.350495 | AX16: =RANK(AW16,$AW$5:$AW$25,1) -> 9 | AY16: =VLOOKUP(B16,[4]计算结果表!$B$1:$T$25,17,0) -> 6332.8235 | AZ16: =VLOOKUP(B16,[2]计算结果表!$B$1:$T$25,17,0) -> 6543.7815 | BA16: =AZ16/AY16-1 -> 0.033311843 | BB16: =AY16/C16 -> 0.081495619 | BC16: =AZ16/E16 -> 0.083091133 | BD16: =RANK(BC16,$BC$5:$BC$25,0) -> 6 | BE16: =BC16-BB16 -> 0.0015955138 | BF16: =VLOOKUP(B16,[4]计算结果表!$B$1:$T$25,9,0) -> 16.068724 | BG16: =VLOOKUP(B16,[2]计算结果表!$B$1:$T$25,9,0) -> 229.18624 | BH16: =BG16/BF16-1 -> 13.262877 | BI16: =BF16/I16 -> 0.0016554722 | BJ16: =BG16/J16 -> 0.020416811 | BK16: =RANK(BJ16,$BJ$5:$BJ$25,1) -> 3 | BL16: =VLOOKUP(B16,[8]市州营业收现率202502完成!$B$1:$AH$28,6,0) -> 13573.774 | BM16: =VLOOKUP(B16,[9]市州营业收现率2月完成!$B$1:$AI$28,7,0) -> 12768.34 | BN16: =VLOOKUP(B16,[8]市州营业收现率202502完成!$B$1:$AH$28,5,0) -> 0.99183346 | BO16: =VLOOKUP(B16,[9]市州营业收现率2月完成!$B$1:$AI$28,5,0) -> 1.0404483 | BP16: =RANK(BO16,$BO$5:$BO$25,0) -> 3
... A25: 21 | B25: 攀枝花 | C25: 41681.598 | D25: 5590.1337 | E25: 40623.803 | F25: 6186.8028 | G25: =E25/C25-1 -> -0.025377992 | H25: =F25/D25-1 -> 0.1067361 | I25: =VLOOKUP(B25,[4]计算结果表!$B$1:$AA$25,13,0) -> 5444.7847 | J25: =VLOOKUP(B25,[2]计算结果表!$B$1:$AA$25,13,0) -> 4601.2613 | K25: =J25/I25-1 -> -0.15492318 | L25: =I25/C25 -> 0.13062802 | M25: =J25/E25 -> 0.11326516 | N25: =RANK(M25,$M$5:$M$25,1) -> 15 | O25: =M25-L25 -> -0.017362866 | P25: =VLOOKUP(B25,[4]计算结果表!$B$1:$AA$25,15,0) -> 3008.5221 | Q25: =VLOOKUP(B25,[2]计算结果表!$B$1:$AA$25,15,0) -> 2844.9164 | R25: =Q25/P25-1 -> -0.054380754 | S25: =P25/D25 -> 0.53818428 | T25: =Q25/F25 -> 0.45983628 | U25: =RANK(T25,$T$5:$T$25,1) -> 10 | V25: =T25-S25 -> -0.078347998 | W25: =VLOOKUP(B25,[2]计算结果表!$B$1:$T$25,18,0) -> 688.25751 | X25: =VLOOKUP(B25,[2]计算结果表!$B$1:$T$25,19,0) -> 2156.6589 | Y25: =VLOOKUP(B25,[1]分ICT资源型数据!$B$1:$P$23,11,0) -> 1936.2837 | Z25: =VLOOKUP(B25,[1]分ICT资源型数据!$B$1:$P$23,12,0) -> 3160.6951 | AA25: =W25/(Y25/11*12) -> 0.32583176 | AB25: =RANK(AA25,$AA$5:$AA$25,1) -> 17 | AC25: =X25/(Z25/11*12) -> 0.62547548 | AD25: =RANK(AC25,$AC$5:$AC$25,1) -> 8 | AE25: =VLOOKUP(B25,[4]计算结果表!$B$1:$T$25,16,0) -> 2436.2626 | AF25: =VLOOKUP(B25,[2]计算结果表!$B$1:$T$25,16,0) -> 1756.345 | AG25: =AF25/AE25-1 -> -0.27908225 | AH25: =AE25/(C25-D25) -> 0.06750246 | AI25: =AF25/(E25-F25) -> 0.051001683 | AJ25: =RANK(AI25,$AI$5:$AI$25,1) -> 16 | AK25: =AI25-AH25 -> -0.016500777 | AL25: =VLOOKUP(B25,'[5]查询结果(2025年2月)'!$A$2:$L$29,12,0)/10000 -> 2893.8208 | AM25: =VLOOKUP(B25,'[3]查询结果(2026年2月)'!$A$2:$L$29,12,0)/10000 -> 1726.3032 | AN25: =AM25/AL25-1 -> -0.40345194 | AO25: =RANK(AN25,$AN$5:$AN$25,1) -> 1 | AP25: =AL25/I25 -> 0.53148489 | AQ25: =AM25/J25 -> 0.37518042 | AR25: =RANK(AQ25,$AQ$5:$AQ$25,1) -> 20 | AS25: =VLOOKUP(B25,'[6]查询结果(2025年2月)'!$A$2:$L$29,12,0)/10000 -> 1412.9942 | AT25: =VLOOKUP(B25,'[7]查询结果(2026年2月)'!$A$2:$H$25,8,0)/10000 -> 906.67958 | AU25: =AT25/Q25 -> 0.31870166 | AV25: =RANK(AU25,$AU$5:$AU$25,1) -> 20 | AW25: =AT25/AS25-1 -> -0.35832747 | AX25: =RANK(AW25,$AW$5:$AW$25,1) -> 2 | AY25: =VLOOKUP(B25,[4]计算结果表!$B$1:$T$25,17,0) -> 4235.7405 | AZ25: =VLOOKUP(B25,[2]计算结果表!$B$1:$T$25,17,0) -> 3450.4147 | BA25: =AZ25/AY25-1 -> -0.1854046 | BB25: =AY25/C25 -> 0.10162136 | BC25: =AZ25/E25 -> 0.084935788 | BD25: =RANK(BC25,$BC$5:$BC$25,0) -> 5 | BE25: =BC25-BB25 -> -0.016685568 | BF25: =VLOOKUP(B25,[4]计算结果表!$B$1:$T$25,9,0) -> 45.061715 | BG25: =VLOOKUP(B25,[2]计算结果表!$B$1:$T$25,9,0) -> 213.57473 | BH25: =BG25/BF25-1 -> 3.7396051 | BI25: =BF25/I25 -> 0.0082761243 | BJ25: =BG25/J25 -> 0.046416562 | BK25: =RANK(BJ25,$BJ$5:$BJ$25,1) -> 14 | BL25: =VLOOKUP(B25,[8]市州营业收现率202502完成!$B$1:$AH$28,6,0) -> 6610.7527 | BM25: =VLOOKUP(B25,[9]市州营业收现率2月完成!$B$1:$AI$28,7,0) -> 4429.5257 | BN25: =VLOOKUP(B25,[8]市州营业收现率202502完成!$B$1:$AH$28,5,0) -> 0.97704633 | BO25: =VLOOKUP(B25,[9]市州营业收现率2月完成!$B$1:$AI$28,5,0) -> 0.6406632 | BP25: =RANK(BO25,$BO$5:$BO$25,0) -> 19
A26: 22 | B26: 市州合计 | C26: =SUM(C5:C25) -> 3051812 | D26: =SUM(D5:D25) -> 429644.34 | E26: =SUM(E5:E25) -> 3108676.9 | F26: =SUM(F5:F25) -> 486690.27 | I26: =SUM(I5:I25) -> 236950.9 | J26: =SUM(J5:J25) -> 291208.81 | K26: =J26/I26-1 -> 0.22898377 | L26: =I26/C26 -> 0.077642692 | M26: =J26/E26 -> 0.093676126 | O26: =M26-L26 -> 0.016033434 | P26: =SUM(P5:P25) -> 149244.32 | Q26: =SUM(Q5:Q25) -> 201488.41 | R26: =Q26/P26-1 -> 0.3500575 | S26: =P26/D26 -> 0.34736713 | T26: =Q26/F26 -> 0.41399721 | V26: =T26-S26 -> 0.066630082 | W26: =SUM(W5:W25) -> 38316.544 | X26: =SUM(X5:X25) -> 163171.87 | Y26: =SUM(Y5:Y25) -> 171371.33 | Z26: =SUM(Z5:Z25) -> 256134.06 | AA26: =W26/(Y26/11*12) -> 0.20495551 | AC26: =X26/(Z26/11*12) -> 0.58396846 | AE26: =SUM(AE5:AE25) -> 87706.577 | AF26: =SUM(AF5:AF25) -> 89720.395 | AG26: =AF26/AE26-1 -> 0.022960849 | AH26: =AE26/(C26-D26) -> 0.03344812 | AI26: =AF26/(E26-F26) -> 0.034218479 | AK26: =AI26-AH26 -> 0.00077035951 | AL26: =SUM(AL5:AL25) -> 38767.37 | AM26: =SUM(AM5:AM25) -> 58919.519 | AN26: =AM26/AL26-1 -> 0.51982242 | AP26: =AL26/I26 -> 0.1636093 | AQ26: =AM26/J26 -> 0.20232739 | AS26: =SUM(AS5:AS25) -> 23331.019 | AT26: =SUM(AT5:AT25) -> 41407.296 | AU26: =AT26/Q26 -> 0.20550708 | AW26: =AT26/AS26-1 -> 0.77477446 | AY26: =SUM(AY5:AY25) -> 214482.93 | AZ26: =SUM(AZ5:AZ25) -> 234672.16 | BA26: =AZ26/AY26-1 -> 0.094129754 | BB26: =AY26/C26 -> 0.07028052 | BC26: =AZ26/E26 -> 0.075489402 | BE26: =BC26-BB26 -> 0.0052088819 | BF26: =SUM(BF5:BF25) -> 4070.3296 | BG26: =SUM(BG5:BG25) -> 11759.654 | BH26: =BG26/BF26-1 -> 1.8891159 | BI26: =BF26/I26 -> 0.017177945 | BJ26: =BG26/J26 -> 0.040382206 | BL26: =VLOOKUP(B26,[8]市州营业收现率202502完成!$B$1:$AH$28,6,0) -> 447538.88 | BM26: =VLOOKUP(B26,[9]市州营业收现率2月完成!$B$1:$AI$28,7,0) -> 458096.64 | BN26: =VLOOKUP(B26,[8]市州营业收现率202502完成!$B$1:$AH$28,5,0) -> 0.84516231 | BO26: =VLOOKUP(B26,[9]市州营业收现率2月完成!$B$1:$AI$28,5,0) -> 0.91937311
