Workbook

Sheet 2026年1月
A1: 2026年1月市州应收账款情况表
A2: 序号 | B2: 单位 | C2: 2025年收入完成（不含云及IDC直销收入） | E2: 2026年收入预算（不含云及IDC运营中心直销客户的IDC收入） | I2: 应收账款总额占收比 | P2: 产数应收账款占产数收入比 | W2: 分资源型/ICT应收占收比 （注：资源型应收=组网专线+IDC ICT应收=产数应收+合同资产-资源应收 资源型收入=组网专线+IDC-云锦IDC收入 ICT应收=产数收入-组网专线-IDC） | AE2: 基础应收账款占基础收入比 | AL2: 一年以上应收账款占应收总额比 | AS2: 一年以上产数应收 | AY2: 预收账款占收比 | BF2: 本期坏账计提 | BL2: 营业收现率
C3: 收入完成 | D3: 产数收入完成 | E3: 收入 | F3: 产数收入 | G3: 收入同比 | H3: 产数收入同比 | I3: 202501 应收总额 | J3: 202601 应收总额 | K3: 应收总额同比增幅 | L3: 202501 占收比 | M3: 202601 占收比 | N3: 排名 | O3: 占收比同比 | P3: 202501 应收产数 | Q3: 202601 应收产数 | R3: 产数应收账款增幅 | S3: 202501 产数占收比 | T3: 202601 产数占收比 | U3: 排名 | V3: 产数占收比同比 | W3: 202601资源型应收账款总额 | X3: 202601产数ICT应收账款总额 | Y3: 202601资源型收入（剔除云锦IDC收入） | Z3: 202601产数ICT收入 | AA3: 202601资源型应收占收比 | AB3: 排名 | AC3: 202601产数ICT应收占收比 | AD3: 排名 | AE3: 202501 基础应收 | AF3: 202601 基础应收 | AG3: 基础应收同比增幅 | AH3: 202501 基础占收比 | AI3: 202601 基础占收比 | AJ3: 排名 | AK3: 基础占收比同比 | AL3: 202501 一年以上应收 | AM3: 202601 一年以上应收 | AN3: 一年以上同比增幅 | AO3: 排名 | AP3: 202501 一年以上占应收总额比 | AQ3: 202601 一年以上占应收总额比 | AR3: 排名 | AS3: 202501一年以上产数应收 | AT3: 202601一年以上产数应收 | AU3: 202601一年以上产数应收账款结构占比 | AV3: 排名 | AW3: 202601一年以上产数应收同比增幅 | AX3: 排名 | AY3: 202501 预收账款总额 | AZ3: 202601 预收账款总额 | BA3: 同比增幅 | BB3: 202501 占收比 | BC3: 202601 占收比 | BD3: 排名 | BE3: 占收比同比 | BF3: 202501本年坏账计提 | BG3: 202601本年坏账计提 | BH3: 同比增幅 | BI3: 202501本年坏账计提占应收比 | BJ3: 202601本年坏账计提占应收比 | BK3: 排名 | BL3: 202501经营活动现金流入完成 | BM3: 202601经营活动现金流入完成 | BN3: 202501营业收现率 | BO3: 202601营业收现率 | BP3: 排名
A5: 1 | B5: 成都 | C5: 1035002.1 | D5: 180143.51 | E5: 1059462.1 | F5: 200299.18 | G5: =E5/C5-1 -> 0.023632757 | H5: =F5/D5-1 -> 0.11188678 | I5: =VLOOKUP(B5,[2]计算结果表!$B$1:$AA$25,13,0) -> 73348.389 | J5: =VLOOKUP(B5,[3]计算结果表!$B$1:$AA$25,13,0) -> 80806.941 | K5: =J5/I5-1 -> 0.10168665 | L5: =I5/C5 -> 0.070867864 | M5: =J5/E5 -> 0.07627167 | N5: =RANK(M5,$M$5:$M$25,1) -> 4 | O5: =M5-L5 -> 0.0054038056 | P5: =VLOOKUP(B5,[2]计算结果表!$B$1:$AA$25,15,0) -> 45969.809 | Q5: =VLOOKUP(B5,[3]计算结果表!$B$1:$AA$25,15,0) -> 63009.803 | R5: =Q5/P5-1 -> 0.37067794 | S5: =P5/D5 -> 0.25518438 | T5: =Q5/F5 -> 0.31457843 | U5: =RANK(T5,$T$5:$T$25,1) -> 2 | V5: =T5-S5 -> 0.059394052 | W5: =VLOOKUP(B5,[3]计算结果表!$B$1:$T$25,18,0) -> 9826.2415 | X5: =VLOOKUP(B5,[3]计算结果表!$B$1:$T$25,19,0) -> 53183.562 | Y5: =VLOOKUP(B5,[1]分ICT资源型数据!$B$1:$P$23,11,0) -> 68355.352 | Z5: =VLOOKUP(B5,[1]分ICT资源型数据!$B$1:$P$23,12,0) -> 107234.61 | AA5: =W5/(Y5/11*12) -> 0.13177298 | AB5: =RANK(AA5,$AA$5:$AA$25,1) -> 3 | AC5: =X5/(Z5/11*12) -> 0.4546256 | AD5: =RANK(AC5,$AC$5:$AC$25,1) -> 3 | AE5: =VLOOKUP(B5,[2]计算结果表!$B$1:$T$25,16,0) -> 27378.581 | AF5: =VLOOKUP(B5,[3]计算结果表!$B$1:$T$25,16,0) -> 17797.138 | AG5: =AF5/AE5-1 -> -0.34996126 | AH5: =AE5/(C5-D5) -> 0.032027028 | AI5: =AF5/(E5-F5) -> 0.02071451 | AJ5: =RANK(AI5,$AI$5:$AI$25,1) -> 3 | AK5: =AI5-AH5 -> -0.011312518 | AL5: =VLOOKUP(B5,'[5]查询结果(2025年1月)'!$A$2:$M$29,13,0) -> 15678.69 | AM5: =VLOOKUP(B5,'[4]查询结果(2026年1月)'!$A$2:$M$29,13,0) -> 16352.636 | AN5: =AM5/AL5-1 -> 0.042984881 | AO5: =RANK(AN5,$AN$5:$AN$25,1) -> 4 | AP5: =AL5/I5 -> 0.21375643 | AQ5: =AM5/J5 -> 0.20236673 | AR5: =RANK(AQ5,$AQ$5:$AQ$25,1) -> 13 | AS5: =VLOOKUP(B5,'[7]查询结果(2025年1月)'!$A$2:$M$25,13,0) -> 7053.3698 | AT5: =VLOOKUP(B5,'[6]查询结果(2026年1月)'!$A$2:$M$25,13,0) -> 10358.607 | AU5: =AT5/Q5 -> 0.16439675 | AV5: =RANK(AU5,$AU$5:$AU$25,1) -> 11 | AW5: =AT5/AS5-1 -> 0.46860399 | AX5: =RANK(AW5,$AW$5:$AW$25,1) -> 6 | AY5: =VLOOKUP(B5,[2]计算结果表!$B$1:$T$25,17,0) -> 97435.959 | AZ5: =VLOOKUP(B5,[3]计算结果表!$B$1:$T$25,17,0) -> 101492.73 | BA5: =AZ5/AY5-1 -> 0.041635292 | BB5: =AY5/C5 -> 0.094140831 | BC5: =AZ5/E5 -> 0.095796477 | BD5: =RANK(BC5,$BC$5:$BC$25,0) -> 3 | BE5: =BC5-BB5 -> 0.0016556461 | BF5: =VLOOKUP(B5,[2]计算结果表!$B$1:$T$25,9,0) -> 531.03698 | BG5: =VLOOKUP(B5,[3]计算结果表!$B$1:$T$25,9,0) -> 937.251 | BH5: =BG5/BF5-1 -> 0.76494488 | BI5: =BF5/I5 -> 0.0072399269 | BJ5: =BG5/J5 -> 0.011598645 | BK5: =RANK(BJ5,$BJ$5:$BJ$25,1) -> 2 | BL5: =VLOOKUP(B5,[8]市州营业收现率202501完成!$B$1:$AH$28,6,0) -> 79504.698 | BM5: =VLOOKUP(B5,[9]市州营业收现率1月完成!$B$1:$AI$28,7,0) -> 72034.205 | BN5: =VLOOKUP(B5,[8]市州营业收现率202501完成!$B$1:$AH$28,5,0) -> 0.87228122 | BO5: =VLOOKUP(B5,[9]市州营业收现率1月完成!$B$1:$AI$28,5,0) -> 0.80728129 | BP5: =RANK(BO5,$BO$5:$BO$25,0) -> 12
A6: 2 | B6: 绵阳 | C6: 181679.31 | D6: 18516.339 | E6: 186047.11 | F6: 22732.105 | G6: =E6/C6-1 -> 0.024041211 | H6: =F6/D6-1 -> 0.22767818 | I6: =VLOOKUP(B6,[2]计算结果表!$B$1:$AA$25,13,0) -> 10774.632 | J6: =VLOOKUP(B6,[3]计算结果表!$B$1:$AA$25,13,0) -> 13643.081 | K6: =J6/I6-1 -> 0.26622251 | L6: =I6/C6 -> 0.059305769 | M6: =J6/E6 -> 0.073331326 | N6: =RANK(M6,$M$5:$M$25,1) -> 3 | O6: =M6-L6 -> 0.014025557 | P6: =VLOOKUP(B6,[2]计算结果表!$B$1:$AA$25,15,0) -> 5386.0874 | Q6: =VLOOKUP(B6,[3]计算结果表!$B$1:$AA$25,15,0) -> 7884.0499 | R6: =Q6/P6-1 -> 0.46378054 | S6: =P6/D6 -> 0.29088296 | T6: =Q6/F6 -> 0.34682445 | U6: =RANK(T6,$T$5:$T$25,1) -> 5 | V6: =T6-S6 -> 0.055941495 | W6: =VLOOKUP(B6,[3]计算结果表!$B$1:$T$25,18,0) -> 1284.3986 | X6: =VLOOKUP(B6,[3]计算结果表!$B$1:$T$25,19,0) -> 6599.6513 | Y6: =VLOOKUP(B6,[1]分ICT资源型数据!$B$1:$P$23,11,0) -> 7341.014 | Z6: =VLOOKUP(B6,[1]分ICT资源型数据!$B$1:$P$23,12,0) -> 10540.18 | AA6: =W6/(Y6/11*12) -> 0.16038184 | AB6: =RANK(AA6,$AA$5:$AA$25,1) -> 6 | AC6: =X6/(Z6/11*12) -> 0.57396367 | AD6: =RANK(AC6,$AC$5:$AC$25,1) -> 6 | AE6: =VLOOKUP(B6,[2]计算结果表!$B$1:$T$25,16,0) -> 5388.5442 | AF6: =VLOOKUP(B6,[3]计算结果表!$B$1:$T$25,16,0) -> 5759.031 | AG6: =AF6/AE6-1 -> 0.068754541 | AH6: =AE6/(C6-D6) -> 0.033025533 | AI6: =AF6/(E6-F6) -> 0.035263332 | AJ6: =RANK(AI6,$AI$5:$AI$25,1) -> 10 | AK6: =AI6-AH6 -> 0.0022377993 | AL6: =VLOOKUP(B6,'[5]查询结果(2025年1月)'!$A$2:$M$29,13,0) -> 748.04934 | AM6: =VLOOKUP(B6,'[4]查询结果(2026年1月)'!$A$2:$M$29,13,0) -> 1761.9424 | AN6: =AM6/AL6-1 -> 1.3553826 | AO6: =RANK(AN6,$AN$5:$AN$25,1) -> 14 | AP6: =AL6/I6 -> 0.069426907 | AQ6: =AM6/J6 -> 0.12914549 | AR6: =RANK(AQ6,$AQ$5:$AQ$25,1) -> 4 | AS6: =VLOOKUP(B6,'[7]查询结果(2025年1月)'!$A$2:$M$25,13,0) -> 343.57888 | AT6: =VLOOKUP(B6,'[6]查询结果(2026年1月)'!$A$2:$M$25,13,0) -> 1034.9412 | AU6: =AT6/Q6 -> 0.13127026 | AV6: =RANK(AU6,$AU$5:$AU$25,1) -> 5 | AW6: =AT6/AS6-1 -> 2.0122377 | AX6: =RANK(AW6,$AW$5:$AW$25,1) -> 16 | AY6: =VLOOKUP(B6,[2]计算结果表!$B$1:$T$25,17,0) -> 12078.002 | AZ6: =VLOOKUP(B6,[3]计算结果表!$B$1:$T$25,17,0) -> 12640.67 | BA6: =AZ6/AY6-1 -> 0.046586113 | BB6: =AY6/C6 -> 0.066479788 | BC6: =AZ6/E6 -> 0.067943382 | BD6: =RANK(BC6,$BC$5:$BC$25,0) -> 10 | BE6: =BC6-BB6 -> 0.0014635937 | BF6: =VLOOKUP(B6,[2]计算结果表!$B$1:$T$25,9,0) -> 228.94189 | BG6: =VLOOKUP(B6,[3]计算结果表!$B$1:$T$25,9,0) -> 471.65488 | BH6: =BG6/BF6-1 -> 1.0601511 | BI6: =BF6/I6 -> 0.021248233 | BJ6: =BG6/J6 -> 0.034570994 | BK6: =RANK(BJ6,$BJ$5:$BJ$25,1) -> 9 | BL6: =VLOOKUP(B6,[8]市州营业收现率202501完成!$B$1:$AH$28,6,0) -> 13642.349 | BM6: =VLOOKUP(B6,[9]市州营业收现率1月完成!$B$1:$AI$28,7,0) -> 13258.246 | BN6: =VLOOKUP(B6,[8]市州营业收现率202501完成!$B$1:$AH$28,5,0) -> 0.84772611 | BO6: =VLOOKUP(B6,[9]市州营业收现率1月完成!$B$1:$AI$28,5,0) -> 0.89236593 | BP6: =RANK(BO6,$BO$5:$BO$25,0) -> 7
A7: 3 | B7: 南充 | C7: 179641.91 | D7: 12469.679 | E7: 184491.85 | F7: 16842.183 | G7: =E7/C7-1 -> 0.026997813 | H7: =F7/D7-1 -> 0.3506509 | I7: =VLOOKUP(B7,[2]计算结果表!$B$1:$AA$25,13,0) -> 12929.667 | J7: =VLOOKUP(B7,[3]计算结果表!$B$1:$AA$25,13,0) -> 19297.559 | K7: =J7/I7-1 -> 0.49250247 | L7: =I7/C7 -> 0.071974667 | M7: =J7/E7 -> 0.10459844 | N7: =RANK(M7,$M$5:$M$25,1) -> 11 | O7: =M7-L7 -> 0.032623772 | P7: =VLOOKUP(B7,[2]计算结果表!$B$1:$AA$25,15,0) -> 6610.1471 | Q7: =VLOOKUP(B7,[3]计算结果表!$B$1:$AA$25,15,0) -> 10777.189 | R7: =Q7/P7-1 -> 0.63040076 | S7: =P7/D7 -> 0.53009762 | T7: =Q7/F7 -> 0.63989264 | U7: =RANK(T7,$T$5:$T$25,1) -> 19 | V7: =T7-S7 -> 0.10979502 | W7: =VLOOKUP(B7,[3]计算结果表!$B$1:$T$25,18,0) -> 1053.8856 | X7: =VLOOKUP(B7,[3]计算结果表!$B$1:$T$25,19,0) -> 9723.3031 | Y7: =VLOOKUP(B7,[1]分ICT资源型数据!$B$1:$P$23,11,0) -> 4709.5539 | Z7: =VLOOKUP(B7,[1]分ICT资源型数据!$B$1:$P$23,12,0) -> 9514.6753 | AA7: =W7/(Y7/11*12) -> 0.2051281 | AB7: =RANK(AA7,$AA$5:$AA$25,1) -> 9 | AC7: =X7/(Z7/11*12) -> 0.93676637 | AD7: =RANK(AC7,$AC$5:$AC$25,1) -> 19 | AE7: =VLOOKUP(B7,[2]计算结果表!$B$1:$T$25,16,0) -> 6319.5196 | AF7: =VLOOKUP(B7,[3]计算结果表!$B$1:$T$25,16,0) -> 8520.3706 | AG7: =AF7/AE7-1 -> 0.34826239 | AH7: =AE7/(C7-D7) -> 0.037802448 | AI7: =AF7/(E7-F7) -> 0.050822473 | AJ7: =RANK(AI7,$AI$5:$AI$25,1) -> 18 | AK7: =AI7-AH7 -> 0.013020025 | AL7: =VLOOKUP(B7,'[5]查询结果(2025年1月)'!$A$2:$M$29,13,0) -> 2733.6377 | AM7: =VLOOKUP(B7,'[4]查询结果(2026年1月)'!$A$2:$M$29,13,0) -> 3660.3581 | AN7: =AM7/AL7-1 -> 0.33900632 | AO7: =RANK(AN7,$AN$5:$AN$25,1) -> 6 | AP7: =AL7/I7 -> 0.21142368 | AQ7: =AM7/J7 -> 0.18967985 | AR7: =RANK(AQ7,$AQ$5:$AQ$25,1) -> 12 | AS7: =VLOOKUP(B7,'[7]查询结果(2025年1月)'!$A$2:$M$25,13,0) -> 2446.2974 | AT7: =VLOOKUP(B7,'[6]查询结果(2026年1月)'!$A$2:$M$25,13,0) -> 2658.808 | AU7: =AT7/Q7 -> 0.24670701 | AV7: =RANK(AU7,$AU$5:$AU$25,1) -> 17 | AW7: =AT7/AS7-1 -> 0.086870287 | AX7: =RANK(AW7,$AW$5:$AW$25,1) -> 5 | AY7: =VLOOKUP(B7,[2]计算结果表!$B$1:$T$25,17,0) -> 8274.15 | AZ7: =VLOOKUP(B7,[3]计算结果表!$B$1:$T$25,17,0) -> 9450.2954 | BA7: =AZ7/AY7-1 -> 0.14214697 | BB7: =AY7/C7 -> 0.04605913 | BC7: =AZ7/E7 -> 0.051223376 | BD7: =RANK(BC7,$BC$5:$BC$25,0) -> 18 | BE7: =BC7-BB7 -> 0.0051642466 | BF7: =VLOOKUP(B7,[2]计算结果表!$B$1:$T$25,9,0) -> 516.52828 | BG7: =VLOOKUP(B7,[3]计算结果表!$B$1:$T$25,9,0) -> 626.31263 | BH7: =BG7/BF7-1 -> 0.21254277 | BI7: =BF7/I7 -> 0.039949079 | BJ7: =BG7/J7 -> 0.032455536 | BK7: =RANK(BJ7,$BJ$5:$BJ$25,1) -> 8 | BL7: =VLOOKUP(B7,[8]市州营业收现率202501完成!$B$1:$AH$28,6,0) -> 15774.915 | BM7: =VLOOKUP(B7,[9]市州营业收现率1月完成!$B$1:$AI$28,7,0) -> 12827.941 | BN7: =VLOOKUP(B7,[8]市州营业收现率202501完成!$B$1:$AH$28,5,0) -> 1.0017469 | BO7: =VLOOKUP(B7,[9]市州营业收现率1月完成!$B$1:$AI$28,5,0) -> 0.86622416 | BP7: =RANK(BO7,$BO$5:$BO$25,0) -> 8
A8: 4 | B8: 泸州 | C8: 162553.55 | D8: 16331.369 | E8: 164815.2 | F8: 18361.204 | G8: =E8/C8-1 -> 0.013913294 | H8: =F8/D8-1 -> 0.12429054 | I8: =VLOOKUP(B8,[2]计算结果表!$B$1:$AA$25,13,0) -> 11875.628 | J8: =VLOOKUP(B8,[3]计算结果表!$B$1:$AA$25,13,0) -> 12793.977 | K8: =J8/I8-1 -> 0.07733059 | L8: =I8/C8 -> 0.073056714 | M8: =J8/E8 -> 0.077626197 | N8: =RANK(M8,$M$5:$M$25,1) -> 5 | O8: =M8-L8 -> 0.0045694827 | P8: =VLOOKUP(B8,[2]计算结果表!$B$1:$AA$25,15,0) -> 7246.125 | Q8: =VLOOKUP(B8,[3]计算结果表!$B$1:$AA$25,15,0) -> 9097.6646 | R8: =Q8/P8-1 -> 0.25552134 | S8: =P8/D8 -> 0.44369366 | T8: =Q8/F8 -> 0.49548301 | U8: =RANK(T8,$T$5:$T$25,1) -> 11 | V8: =T8-S8 -> 0.051789352 | W8: =VLOOKUP(B8,[3]计算结果表!$B$1:$T$25,18,0) -> 1659.3591 | X8: =VLOOKUP(B8,[3]计算结果表!$B$1:$T$25,19,0) -> 7438.3055 | Y8: =VLOOKUP(B8,[1]分ICT资源型数据!$B$1:$P$23,11,0) -> 4667.5843 | Z8: =VLOOKUP(B8,[1]分ICT资源型数据!$B$1:$P$23,12,0) -> 9556.1832 | AA8: =W8/(Y8/11*12) -> 0.32588146 | AB8: =RANK(AA8,$AA$5:$AA$25,1) -> 18 | AC8: =X8/(Z8/11*12) -> 0.71351151 | AD8: =RANK(AC8,$AC$5:$AC$25,1) -> 13 | AE8: =VLOOKUP(B8,[2]计算结果表!$B$1:$T$25,16,0) -> 4629.5031 | AF8: =VLOOKUP(B8,[3]计算结果表!$B$1:$T$25,16,0) -> 3696.3128 | AG8: =AF8/AE8-1 -> -0.20157461 | AH8: =AE8/(C8-D8) -> 0.031660745 | AI8: =AF8/(E8-F8) -> 0.025238729 | AJ8: =RANK(AI8,$AI$5:$AI$25,1) -> 6 | AK8: =AI8-AH8 -> -0.0064220157 | AL8: =VLOOKUP(B8,'[5]查询结果(2025年1月)'!$A$2:$M$29,13,0) -> 1890.8668 | AM8: =VLOOKUP(B8,'[4]查询结果(2026年1月)'!$A$2:$M$29,13,0) -> 3290.1432 | AN8: =AM8/AL8-1 -> 0.74001847 | AO8: =RANK(AN8,$AN$5:$AN$25,1) -> 7 | AP8: =AL8/I8 -> 0.15922247 | AQ8: =AM8/J8 -> 0.25716344 | AR8: =RANK(AQ8,$AQ$5:$AQ$25,1) -> 18 | AS8: =VLOOKUP(B8,'[7]查询结果(2025年1月)'!$A$2:$M$25,13,0) -> 1285.6852 | AT8: =VLOOKUP(B8,'[6]查询结果(2026年1月)'!$A$2:$M$25,13,0) -> 2112.5394 | AU8: =AT8/Q8 -> 0.23220678 | AV8: =RANK(AU8,$AU$5:$AU$25,1) -> 15 | AW8: =AT8/AS8-1 -> 0.64312342 | AX8: =RANK(AW8,$AW$5:$AW$25,1) -> 7 | AY8: =VLOOKUP(B8,[2]计算结果表!$B$1:$T$25,17,0) -> 8962.5541 | AZ8: =VLOOKUP(B8,[3]计算结果表!$B$1:$T$25,17,0) -> 7912.7693 | BA8: =AZ8/AY8-1 -> -0.11713009 | BB8: =AY8/C8 -> 0.05513601 | BC8: =AZ8/E8 -> 0.048009948 | BD8: =RANK(BC8,$BC$5:$BC$25,0) -> 20 | BE8: =BC8-BB8 -> -0.0071260622 | BF8: =VLOOKUP(B8,[2]计算结果表!$B$1:$T$25,9,0) -> 429.98962 | BG8: =VLOOKUP(B8,[3]计算结果表!$B$1:$T$25,9,0) -> 966.72247 | BH8: =BG8/BF8-1 -> 1.2482461 | BI8: =BF8/I8 -> 0.036207737 | BJ8: =BG8/J8 -> 0.075560746 | BK8: =RANK(BJ8,$BJ$5:$BJ$25,1) -> 21 | BL8: =VLOOKUP(B8,[8]市州营业收现率202501完成!$B$1:$AH$28,6,0) -> 12969.57 | BM8: =VLOOKUP(B8,[9]市州营业收现率1月完成!$B$1:$AI$28,7,0) -> 11256.141 | BN8: =VLOOKUP(B8,[8]市州营业收现率202501完成!$B$1:$AH$28,5,0) -> 0.90571788 | BO8: =VLOOKUP(B8,[9]市州营业收现率1月完成!$B$1:$AI$28,5,0) -> 0.81464981 | BP8: =RANK(BO8,$BO$5:$BO$25,0) -> 11
A9: 5 | B9: 凉山 | C9: 140988.95 | D9: 21848.297 | E9: 143570.12 | F9: 24548.12 | G9: =E9/C9-1 -> 0.018307588 | H9: =F9/D9-1 -> 0.12357131 | I9: =VLOOKUP(B9,[2]计算结果表!$B$1:$AA$25,13,0) -> 8244.4968 | J9: =VLOOKUP(B9,[3]计算结果表!$B$1:$AA$25,13,0) -> 14747.075 | K9: =J9/I9-1 -> 0.78871738 | L9: =I9/C9 -> 0.058476191 | M9: =J9/E9 -> 0.10271688 | N9: =RANK(M9,$M$5:$M$25,1) -> 10 | O9: =M9-L9 -> 0.044240689 | P9: =VLOOKUP(B9,[2]计算结果表!$B$1:$AA$25,15,0) -> 4820.3149 | Q9: =VLOOKUP(B9,[3]计算结果表!$B$1:$AA$25,15,0) -> 9355.6889 | R9: =Q9/P9-1 -> 0.94088747 | S9: =P9/D9 -> 0.22062657 | T9: =Q9/F9 -> 0.38111631 | U9: =RANK(T9,$T$5:$T$25,1) -> 6 | V9: =T9-S9 -> 0.16048974 | W9: =VLOOKUP(B9,[3]计算结果表!$B$1:$T$25,18,0) -> 2175.0397 | X9: =VLOOKUP(B9,[3]计算结果表!$B$1:$T$25,19,0) -> 7180.6492 | Y9: =VLOOKUP(B9,[1]分ICT资源型数据!$B$1:$P$23,11,0) -> 8210.713 | Z9: =VLOOKUP(B9,[1]分ICT资源型数据!$B$1:$P$23,12,0) -> 11679.424 | AA9: =W9/(Y9/11*12) -> 0.24282743 | AB9: =RANK(AA9,$AA$5:$AA$25,1) -> 13 | AC9: =X9/(Z9/11*12) -> 0.56357761 | AD9: =RANK(AC9,$AC$5:$AC$25,1) -> 5 | AE9: =VLOOKUP(B9,[2]计算结果表!$B$1:$T$25,16,0) -> 3424.1819 | AF9: =VLOOKUP(B9,[3]计算结果表!$B$1:$T$25,16,0) -> 5391.3859 | AG9: =AF9/AE9-1 -> 0.57450336 | AH9: =AE9/(C9-D9) -> 0.028740667 | AI9: =AF9/(E9-F9) -> 0.045297389 | AJ9: =RANK(AI9,$AI$5:$AI$25,1) -> 15 | AK9: =AI9-AH9 -> 0.016556722 | AL9: =VLOOKUP(B9,'[5]查询结果(2025年1月)'!$A$2:$M$29,13,0) -> 525.81334 | AM9: =VLOOKUP(B9,'[4]查询结果(2026年1月)'!$A$2:$M$29,13,0) -> 2353.4624 | AN9: =AM9/AL9-1 -> 3.4758514 | AO9: =RANK(AN9,$AN$5:$AN$25,1) -> 21 | AP9: =AL9/I9 -> 0.063777494 | AQ9: =AM9/J9 -> 0.15958842 | AR9: =RANK(AQ9,$AQ$5:$AQ$25,1) -> 8 | AS9: =VLOOKUP(B9,'[7]查询结果(2025年1月)'!$A$2:$M$25,13,0) -> 199.47276 | AT9: =VLOOKUP(B9,'[6]查询结果(2026年1月)'!$A$2:$M$25,13,0) -> 1607.1184 | AU9: =AT9/Q9 -> 0.1717798 | AV9: =RANK(AU9,$AU$5:$AU$25,1) -> 12 | AW9: =AT9/AS9-1 -> 7.0568316 | AX9: =RANK(AW9,$AW$5:$AW$25,1) -> 21 | AY9: =VLOOKUP(B9,[2]计算结果表!$B$1:$T$25,17,0) -> 12608.529 | AZ9: =VLOOKUP(B9,[3]计算结果表!$B$1:$T$25,17,0) -> 11103.577 | BA9: =AZ9/AY9-1 -> -0.11935981 | BB9: =AY9/C9 -> 0.089429197 | BC9: =AZ9/E9 -> 0.077339054 | BD9: =RANK(BC9,$BC$5:$BC$25,0) -> 7 | BE9: =BC9-BB9 -> -0.012090144 | BF9: =VLOOKUP(B9,[2]计算结果表!$B$1:$T$25,9,0) -> 22.309826 | BG9: =VLOOKUP(B9,[3]计算结果表!$B$1:$T$25,9,0) -> 390.988 | BH9: =BG9/BF9-1 -> 16.525372 | BI9: =BF9/I9 -> 0.0027060264 | BJ9: =BG9/J9 -> 0.026512919 | BK9: =RANK(BJ9,$BJ$5:$BJ$25,1) -> 5 | BL9: =VLOOKUP(B9,[8]市州营业收现率202501完成!$B$1:$AH$28,6,0) -> 7855.6358 | BM9: =VLOOKUP(B9,[9]市州营业收现率1月完成!$B$1:$AI$28,7,0) -> 7425.7934 | BN9: =VLOOKUP(B9,[8]市州营业收现率202501完成!$B$1:$AH$28,5,0) -> 0.69002185 | BO9: =VLOOKUP(B9,[9]市州营业收现率1月完成!$B$1:$AI$28,5,0) -> 0.6468699 | BP9: =RANK(BO9,$BO$5:$BO$25,0) -> 17
A10: 6 | B10: 宜宾 | C10: 140557.38 | D10: 15542.303 | E10: 143827.88 | F10: 17370.963 | G10: =E10/C10-1 -> 0.02326806 | H10: =F10/D10-1 -> 0.11765701 | I10: =VLOOKUP(B10,[2]计算结果表!$B$1:$AA$25,13,0) -> 6270.2083 | J10: =VLOOKUP(B10,[3]计算结果表!$B$1:$AA$25,13,0) -> 14395.515 | K10: =J10/I10-1 -> 1.2958591 | L10: =I10/C10 -> 0.044609599 | M10: =J10/E10 -> 0.10008849 | N10: =RANK(M10,$M$5:$M$25,1) -> 9 | O10: =M10-L10 -> 0.055478888 | P10: =VLOOKUP(B10,[2]计算结果表!$B$1:$AA$25,15,0) -> 3333.7578 | Q10: =VLOOKUP(B10,[3]计算结果表!$B$1:$AA$25,15,0) -> 9059.1065 | R10: =Q10/P10-1 -> 1.717386 | S10: =P10/D10 -> 0.21449575 | T10: =Q10/F10 -> 0.52150859 | U10: =RANK(T10,$T$5:$T$25,1) -> 13 | V10: =T10-S10 -> 0.30701284 | W10: =VLOOKUP(B10,[3]计算结果表!$B$1:$T$25,18,0) -> 1677.3408 | X10: =VLOOKUP(B10,[3]计算结果表!$B$1:$T$25,19,0) -> 7381.7658 | Y10: =VLOOKUP(B10,[1]分ICT资源型数据!$B$1:$P$23,11,0) -> 14290.476 | Z10: =VLOOKUP(B10,[1]分ICT资源型数据!$B$1:$P$23,12,0) -> 10162.645 | AA10: =W10/(Y10/11*12) -> 0.1075935 | AB10: =RANK(AA10,$AA$5:$AA$25,1) -> 1 | AC10: =X10/(Z10/11*12) -> 0.66583245 | AD10: =RANK(AC10,$AC$5:$AC$25,1) -> 10 | AE10: =VLOOKUP(B10,[2]计算结果表!$B$1:$T$25,16,0) -> 2936.4506 | AF10: =VLOOKUP(B10,[3]计算结果表!$B$1:$T$25,16,0) -> 5336.4081 | AG10: =AF10/AE10-1 -> 0.81729879 | AH10: =AE10/(C10-D10) -> 0.023488772 | AI10: =AF10/(E10-F10) -> 0.042199417 | AJ10: =RANK(AI10,$AI$5:$AI$25,1) -> 13 | AK10: =AI10-AH10 -> 0.018710646 | AL10: =VLOOKUP(B10,'[5]查询结果(2025年1月)'!$A$2:$M$29,13,0) -> 610.36833 | AM10: =VLOOKUP(B10,'[4]查询结果(2026年1月)'!$A$2:$M$29,13,0) -> 1961.2807 | AN10: =AM10/AL10-1 -> 2.213274 | AO10: =RANK(AN10,$AN$5:$AN$25,1) -> 18 | AP10: =AL10/I10 -> 0.097344186 | AQ10: =AM10/J10 -> 0.13624248 | AR10: =RANK(AQ10,$AQ$5:$AQ$25,1) -> 6 | AS10: =VLOOKUP(B10,'[7]查询结果(2025年1月)'!$A$2:$M$25,13,0) -> 238.62908 | AT10: =VLOOKUP(B10,'[6]查询结果(2026年1月)'!$A$2:$M$25,13,0) -> 1441.0709 | AU10: =AT10/Q10 -> 0.15907429 | AV10: =RANK(AU10,$AU$5:$AU$25,1) -> 10 | AW10: =AT10/AS10-1 -> 5.0389578 | AX10: =RANK(AW10,$AW$5:$AW$25,1) -> 20 | AY10: =VLOOKUP(B10,[2]计算结果表!$B$1:$T$25,17,0) -> 8188.528 | AZ10: =VLOOKUP(B10,[3]计算结果表!$B$1:$T$25,17,0) -> 7589.4806 | BA10: =AZ10/AY10-1 -> -0.073156912 | BB10: =AY10/C10 -> 0.058257546 | BC10: =AZ10/E10 -> 0.0527678 | BD10: =RANK(BC10,$BC$5:$BC$25,0) -> 16 | BE10: =BC10-BB10 -> -0.0054897465 | BF10: =VLOOKUP(B10,[2]计算结果表!$B$1:$T$25,9,0) -> 134.97547 | BG10: =VLOOKUP(B10,[3]计算结果表!$B$1:$T$25,9,0) -> 1061.1453 | BH10: =BG10/BF10-1 -> 6.8617637 | BI10: =BF10/I10 -> 0.021526473 | BJ10: =BG10/J10 -> 0.073713603 | BK10: =RANK(BJ10,$BJ$5:$BJ$25,1) -> 20 | BL10: =VLOOKUP(B10,[8]市州营业收现率202501完成!$B$1:$AH$28,6,0) -> 13183.155 | BM10: =VLOOKUP(B10,[9]市州营业收现率1月完成!$B$1:$AI$28,7,0) -> 10685.055 | BN10: =VLOOKUP(B10,[8]市州营业收现率202501完成!$B$1:$AH$28,5,0) -> 1.039761 | BO10: =VLOOKUP(B10,[9]市州营业收现率1月完成!$B$1:$AI$28,5,0) -> 0.90414609 | BP10: =RANK(BO10,$BO$5:$BO$25,0) -> 5
A11: 7 | B11: 达州 | C11: 120354.81 | D11: 12304.33 | E11: 122765.28 | F11: 14143.315 | G11: =E11/C11-1 -> 0.020028035 | H11: =F11/D11-1 -> 0.14945837 | I11: =VLOOKUP(B11,[2]计算结果表!$B$1:$AA$25,13,0) -> 9749.1282 | J11: =VLOOKUP(B11,[3]计算结果表!$B$1:$AA$25,13,0) -> 13190.978 | K11: =J11/I11-1 -> 0.35304181 | L11: =I11/C11 -> 0.08100323 | M11: =J11/E11 -> 0.10744877 | N11: =RANK(M11,$M$5:$M$25,1) -> 14 | O11: =M11-L11 -> 0.026445539 | P11: =VLOOKUP(B11,[2]计算结果表!$B$1:$AA$25,15,0) -> 4880.5468 | Q11: =VLOOKUP(B11,[3]计算结果表!$B$1:$AA$25,15,0) -> 7633.3406 | R11: =Q11/P11-1 -> 0.56403388 | S11: =P11/D11 -> 0.39665279 | T11: =Q11/F11 -> 0.53971368 | U11: =RANK(T11,$T$5:$T$25,1) -> 15 | V11: =T11-S11 -> 0.14306089 | W11: =VLOOKUP(B11,[3]计算结果表!$B$1:$T$25,18,0) -> 1771.2577 | X11: =VLOOKUP(B11,[3]计算结果表!$B$1:$T$25,19,0) -> 5862.0829 | Y11: =VLOOKUP(B11,[1]分ICT资源型数据!$B$1:$P$23,11,0) -> 5255.2011 | Z11: =VLOOKUP(B11,[1]分ICT资源型数据!$B$1:$P$23,12,0) -> 6252.9076 | AA11: =W11/(Y11/11*12) -> 0.30896114 | AB11: =RANK(AA11,$AA$5:$AA$25,1) -> 17 | AC11: =X11/(Z11/11*12) -> 0.85937236 | AD11: =RANK(AC11,$AC$5:$AC$25,1) -> 17 | AE11: =VLOOKUP(B11,[2]计算结果表!$B$1:$T$25,16,0) -> 4868.5814 | AF11: =VLOOKUP(B11,[3]计算结果表!$B$1:$T$25,16,0) -> 5557.6374 | AG11: =AF11/AE11-1 -> 0.14153117 | AH11: =AE11/(C11-D11) -> 0.045058397 | AI11: =AF11/(E11-F11) -> 0.05116495 | AJ11: =RANK(AI11,$AI$5:$AI$25,1) -> 19 | AK11: =AI11-AH11 -> 0.0061065534 | AL11: =VLOOKUP(B11,'[5]查询结果(2025年1月)'!$A$2:$M$29,13,0) -> 1768.9324 | AM11: =VLOOKUP(B11,'[4]查询结果(2026年1月)'!$A$2:$M$29,13,0) -> 5103.1188 | AN11: =AM11/AL11-1 -> 1.884858 | AO11: =RANK(AN11,$AN$5:$AN$25,1) -> 16 | AP11: =AL11/I11 -> 0.18144519 | AQ11: =AM11/J11 -> 0.38686432 | AR11: =RANK(AQ11,$AQ$5:$AQ$25,1) -> 21 | AS11: =VLOOKUP(B11,'[7]查询结果(2025年1月)'!$A$2:$M$25,13,0) -> 1076.0869 | AT11: =VLOOKUP(B11,'[6]查询结果(2026年1月)'!$A$2:$M$25,13,0) -> 2835.7983 | AU11: =AT11/Q11 -> 0.37150161 | AV11: =RANK(AU11,$AU$5:$AU$25,1) -> 21 | AW11: =AT11/AS11-1 -> 1.6352874 | AX11: =RANK(AW11,$AW$5:$AW$25,1) -> 13 | AY11: =VLOOKUP(B11,[2]计算结果表!$B$1:$T$25,17,0) -> 7116.7867 | AZ11: =VLOOKUP(B11,[3]计算结果表!$B$1:$T$25,17,0) -> 7866.5587 | BA11: =AZ11/AY11-1 -> 0.1053526 | BB11: =AY11/C11 -> 0.059131719 | BC11: =AZ11/E11 -> 0.064078042 | BD11: =RANK(BC11,$BC$5:$BC$25,0) -> 12 | BE11: =BC11-BB11 -> 0.004946323 | BF11: =VLOOKUP(B11,[2]计算结果表!$B$1:$T$25,9,0) -> -234.28594 | BG11: =VLOOKUP(B11,[3]计算结果表!$B$1:$T$25,9,0) -> 415.30313 | BH11: =BG11/BF11-1 -> -2.7726336 | BI11: =BF11/I11 -> -0.024031476 | BJ11: =BG11/J11 -> 0.031483877 | BK11: =RANK(BJ11,$BJ$5:$BJ$25,1) -> 7 | BL11: =VLOOKUP(B11,[8]市州营业收现率202501完成!$B$1:$AH$28,6,0) -> 10732.214 | BM11: =VLOOKUP(B11,[9]市州营业收现率1月完成!$B$1:$AI$28,7,0) -> 8970.6297 | BN11: =VLOOKUP(B11,[8]市州营业收现率202501完成!$B$1:$AH$28,5,0) -> 0.96914033 | BO11: =VLOOKUP(B11,[9]市州营业收现率1月完成!$B$1:$AI$28,5,0) -> 0.95492752 | BP11: =RANK(BO11,$BO$5:$BO$25,0) -> 2
A12: 8 | B12: 乐山 | C12: 120556.02 | D12: 16066.625 | E12: 122400.42 | F12: 18070.418 | G12: =E12/C12-1 -> 0.015299071 | H12: =F12/D12-1 -> 0.12471774 | I12: =VLOOKUP(B12,[2]计算结果表!$B$1:$AA$25,13,0) -> 11490.402 | J12: =VLOOKUP(B12,[3]计算结果表!$B$1:$AA$25,13,0) -> 15711.19 | K12: =J12/I12-1 -> 0.36733157 | L12: =I12/C12 -> 0.095311724 | M12: =J12/E12 -> 0.12835896 | N12: =RANK(M12,$M$5:$M$25,1) -> 19 | O12: =M12-L12 -> 0.033047232 | P12: =VLOOKUP(B12,[2]计算结果表!$B$1:$AA$25,15,0) -> 8184.8525 | Q12: =VLOOKUP(B12,[3]计算结果表!$B$1:$AA$25,15,0) -> 11073.334 | R12: =Q12/P12-1 -> 0.3529058 | S12: =P12/D12 -> 0.50943198 | T12: =Q12/F12 -> 0.61278795 | U12: =RANK(T12,$T$5:$T$25,1) -> 18 | V12: =T12-S12 -> 0.10335597 | W12: =VLOOKUP(B12,[3]计算结果表!$B$1:$T$25,18,0) -> 1443.2348 | X12: =VLOOKUP(B12,[3]计算结果表!$B$1:$T$25,19,0) -> 9630.0996 | Y12: =VLOOKUP(B12,[1]分ICT资源型数据!$B$1:$P$23,11,0) -> 5076.3412 | Z12: =VLOOKUP(B12,[1]分ICT资源型数据!$B$1:$P$23,12,0) -> 9917.686 | AA12: =W12/(Y12/11*12) -> 0.26061393 | AB12: =RANK(AA12,$AA$5:$AA$25,1) -> 14 | AC12: =X12/(Z12/11*12) -> 0.89008578 | AD12: =RANK(AC12,$AC$5:$AC$25,1) -> 18 | AE12: =VLOOKUP(B12,[2]计算结果表!$B$1:$T$25,16,0) -> 3305.5499 | AF12: =VLOOKUP(B12,[3]计算结果表!$B$1:$T$25,16,0) -> 4637.8555 | AG12: =AF12/AE12-1 -> 0.40305113 | AH12: =AE12/(C12-D12) -> 0.031635266 | AI12: =AF12/(E12-F12) -> 0.044453709 | AJ12: =RANK(AI12,$AI$5:$AI$25,1) -> 14 | AK12: =AI12-AH12 -> 0.012818443 | AL12: =VLOOKUP(B12,'[5]查询结果(2025年1月)'!$A$2:$M$29,13,0) -> 1599.6574 | AM12: =VLOOKUP(B12,'[4]查询结果(2026年1月)'!$A$2:$M$29,13,0) -> 3764.1357 | AN12: =AM12/AL12-1 -> 1.3530887 | AO12: =RANK(AN12,$AN$5:$AN$25,1) -> 13 | AP12: =AL12/I12 -> 0.13921683 | AQ12: =AM12/J12 -> 0.23958311 | AR12: =RANK(AQ12,$AQ$5:$AQ$25,1) -> 17 | AS12: =VLOOKUP(B12,'[7]查询结果(2025年1月)'!$A$2:$M$25,13,0) -> 1254.273 | AT12: =VLOOKUP(B12,'[6]查询结果(2026年1月)'!$A$2:$M$25,13,0) -> 2836.5182 | AU12: =AT12/Q12 -> 0.25615755 | AV12: =RANK(AU12,$AU$5:$AU$25,1) -> 18 | AW12: =AT12/AS12-1 -> 1.2614839 | AX12: =RANK(AW12,$AW$5:$AW$25,1) -> 10 | AY12: =VLOOKUP(B12,[2]计算结果表!$B$1:$T$25,17,0) -> 7314.0899 | AZ12: =VLOOKUP(B12,[3]计算结果表!$B$1:$T$25,17,0) -> 6561.1788 | BA12: =AZ12/AY12-1 -> -0.10293982 | BB12: =AY12/C12 -> 0.060669635 | BC12: =AZ12/E12 -> 0.053604219 | BD12: =RANK(BC12,$BC$5:$BC$25,0) -> 15 | BE12: =BC12-BB12 -> -0.0070654161 | BF12: =VLOOKUP(B12,[2]计算结果表!$B$1:$T$25,9,0) -> 100.80615 | BG12: =VLOOKUP(B12,[3]计算结果表!$B$1:$T$25,9,0) -> 621.41456 | BH12: =BG12/BF12-1 -> 5.1644507 | BI12: =BF12/I12 -> 0.0087730742 | BJ12: =BG12/J12 -> 0.039552355 | BK12: =RANK(BJ12,$BJ$5:$BJ$25,1) -> 11 | BL12: =VLOOKUP(B12,[8]市州营业收现率202501完成!$B$1:$AH$28,6,0) -> 9811.2076 | BM12: =VLOOKUP(B12,[9]市州营业收现率1月完成!$B$1:$AI$28,7,0) -> 8738.6618 | BN12: =VLOOKUP(B12,[8]市州营业收现率202501完成!$B$1:$AH$28,5,0) -> 0.90911749 | BO12: =VLOOKUP(B12,[9]市州营业收现率1月完成!$B$1:$AI$28,5,0) -> 0.89607541 | BP12: =RANK(BO12,$BO$5:$BO$25,0) -> 6
A13: 9 | B13: 眉山 | C13: 120948.42 | D13: 19113.598 | E13: 121392.76 | F13: 21043.959 | G13: =E13/C13-1 -> 0.0036737762 | H13: =F13/D13-1 -> 0.10099414 | I13: =VLOOKUP(B13,[2]计算结果表!$B$1:$AA$25,13,0) -> 4615.2392 | J13: =VLOOKUP(B13,[3]计算结果表!$B$1:$AA$25,13,0) -> 11098.399 | K13: =J13/I13-1 -> 1.4047288 | L13: =I13/C13 -> 0.038158739 | M13: =J13/E13 -> 0.091425542 | N13: =RANK(M13,$M$5:$M$25,1) -> 8 | O13: =M13-L13 -> 0.053266803 | P13: =VLOOKUP(B13,[2]计算结果表!$B$1:$AA$25,15,0) -> 2197.1105 | Q13: =VLOOKUP(B13,[3]计算结果表!$B$1:$AA$25,15,0) -> 8269.8432 | R13: =Q13/P13-1 -> 2.7639632 | S13: =P13/D13 -> 0.11495013 | T13: =Q13/F13 -> 0.39297944 | U13: =RANK(T13,$T$5:$T$25,1) -> 7 | V13: =T13-S13 -> 0.27802931 | W13: =VLOOKUP(B13,[3]计算结果表!$B$1:$T$25,18,0) -> 683.45474 | X13: =VLOOKUP(B13,[3]计算结果表!$B$1:$T$25,19,0) -> 7586.3885 | Y13: =VLOOKUP(B13,[1]分ICT资源型数据!$B$1:$P$23,11,0) -> 4509.3063 | Z13: =VLOOKUP(B13,[1]分ICT资源型数据!$B$1:$P$23,12,0) -> 11160.163 | AA13: =W13/(Y13/11*12) -> 0.13893494 | AB13: =RANK(AA13,$AA$5:$AA$25,1) -> 4 | AC13: =X13/(Z13/11*12) -> 0.62312613 | AD13: =RANK(AC13,$AC$5:$AC$25,1) -> 8 | AE13: =VLOOKUP(B13,[2]计算结果表!$B$1:$T$25,16,0) -> 2418.1286 | AF13: =VLOOKUP(B13,[3]计算结果表!$B$1:$T$25,16,0) -> 2828.5553 | AG13: =AF13/AE13-1 -> 0.16972905 | AH13: =AE13/(C13-D13) -> 0.023745597 | AI13: =AF13/(E13-F13) -> 0.028187237 | AJ13: =RANK(AI13,$AI$5:$AI$25,1) -> 7 | AK13: =AI13-AH13 -> 0.0044416396 | AL13: =VLOOKUP(B13,'[5]查询结果(2025年1月)'!$A$2:$M$29,13,0) -> 205.44081 | AM13: =VLOOKUP(B13,'[4]查询结果(2026年1月)'!$A$2:$M$29,13,0) -> 866.13692 | AN13: =AM13/AL13-1 -> 3.2159926 | AO13: =RANK(AN13,$AN$5:$AN$25,1) -> 20 | AP13: =AL13/I13 -> 0.044513577 | AQ13: =AM13/J13 -> 0.078041612 | AR13: =RANK(AQ13,$AQ$5:$AQ$25,1) -> 1 | AS13: =VLOOKUP(B13,'[7]查询结果(2025年1月)'!$A$2:$M$25,13,0) -> 105.00535 | AT13: =VLOOKUP(B13,'[6]查询结果(2026年1月)'!$A$2:$M$25,13,0) -> 455.7919 | AU13: =AT13/Q13 -> 0.055114939 | AV13: =RANK(AU13,$AU$5:$AU$25,1) -> 1 | AW13: =AT13/AS13-1 -> 3.3406541 | AX13: =RANK(AW13,$AW$5:$AW$25,1) -> 19 | AY13: =VLOOKUP(B13,[2]计算结果表!$B$1:$T$25,17,0) -> 9778.9224 | AZ13: =VLOOKUP(B13,[3]计算结果表!$B$1:$T$25,17,0) -> 6238.1692 | BA13: =AZ13/AY13-1 -> -0.3620801 | BB13: =AY13/C13 -> 0.080852007 | BC13: =AZ13/E13 -> 0.051388315 | BD13: =RANK(BC13,$BC$5:$BC$25,0) -> 17 | BE13: =BC13-BB13 -> -0.029463692 | BF13: =VLOOKUP(B13,[2]计算结果表!$B$1:$T$25,9,0) -> -10.857533 | BG13: =VLOOKUP(B13,[3]计算结果表!$B$1:$T$25,9,0) -> 515.25311 | BH13: =BG13/BF13-1 -> -48.455818 | BI13: =BF13/I13 -> -0.0023525396 | BJ13: =BG13/J13 -> 0.046425898 | BK13: =RANK(BJ13,$BJ$5:$BJ$25,1) -> 15 | BL13: =VLOOKUP(B13,[8]市州营业收现率202501完成!$B$1:$AH$28,6,0) -> 10232.114 | BM13: =VLOOKUP(B13,[9]市州营业收现率1月完成!$B$1:$AI$28,7,0) -> 7293.0898 | BN13: =VLOOKUP(B13,[8]市州营业收现率202501完成!$B$1:$AH$28,5,0) -> 0.93536692 | BO13: =VLOOKUP(B13,[9]市州营业收现率1月完成!$B$1:$AI$28,5,0) -> 0.79224488 | BP13: =RANK(BO13,$BO$5:$BO$25,0) -> 13
A14: 10 | B14: 德阳 | C14: 108454.18 | D14: 14837.504 | E14: 112086.05 | F14: 18088.049 | G14: =E14/C14-1 -> 0.033487614 | H14: =F14/D14-1 -> 0.21907629 | I14: =VLOOKUP(B14,[2]计算结果表!$B$1:$AA$25,13,0) -> 9289.142 | J14: =VLOOKUP(B14,[3]计算结果表!$B$1:$AA$25,13,0) -> 12355.076 | K14: =J14/I14-1 -> 0.33005562 | L14: =I14/C14 -> 0.085650385 | M14: =J14/E14 -> 0.11022849 | N14: =RANK(M14,$M$5:$M$25,1) -> 17 | O14: =M14-L14 -> 0.024578102 | P14: =VLOOKUP(B14,[2]计算结果表!$B$1:$AA$25,15,0) -> 6331.7346 | Q14: =VLOOKUP(B14,[3]计算结果表!$B$1:$AA$25,15,0) -> 9253.8237 | R14: =Q14/P14-1 -> 0.461499 | S14: =P14/D14 -> 0.42673853 | T14: =Q14/F14 -> 0.51159877 | U14: =RANK(T14,$T$5:$T$25,1) -> 12 | V14: =T14-S14 -> 0.084860243 | W14: =VLOOKUP(B14,[3]计算结果表!$B$1:$T$25,18,0) -> 2539.3968 | X14: =VLOOKUP(B14,[3]计算结果表!$B$1:$T$25,19,0) -> 6714.4269 | Y14: =VLOOKUP(B14,[1]分ICT资源型数据!$B$1:$P$23,11,0) -> 6173.3756 | Z14: =VLOOKUP(B14,[1]分ICT资源型数据!$B$1:$P$23,12,0) -> 8441.6019 | AA14: =W14/(Y14/11*12) -> 0.37706768 | AB14: =RANK(AA14,$AA$5:$AA$25,1) -> 19 | AC14: =X14/(Z14/11*12) -> 0.72911415 | AD14: =RANK(AC14,$AC$5:$AC$25,1) -> 14 | AE14: =VLOOKUP(B14,[2]计算结果表!$B$1:$T$25,16,0) -> 2957.4075 | AF14: =VLOOKUP(B14,[3]计算结果表!$B$1:$T$25,16,0) -> 3101.2519 | AG14: =AF14/AE14-1 -> 0.048638682 | AH14: =AE14/(C14-D14) -> 0.031590606 | AI14: =AF14/(E14-F14) -> 0.032992743 | AJ14: =RANK(AI14,$AI$5:$AI$25,1) -> 8 | AK14: =AI14-AH14 -> 0.001402137 | AL14: =VLOOKUP(B14,'[5]查询结果(2025年1月)'!$A$2:$M$29,13,0) -> 810.33608 | AM14: =VLOOKUP(B14,'[4]查询结果(2026年1月)'!$A$2:$M$29,13,0) -> 2144.3876 | AN14: =AM14/AL14-1 -> 1.6462941 | AO14: =RANK(AN14,$AN$5:$AN$25,1) -> 15 | AP14: =AL14/I14 -> 0.08723476 | AQ14: =AM14/J14 -> 0.17356329 | AR14: =RANK(AQ14,$AQ$5:$AQ$25,1) -> 9 | AS14: =VLOOKUP(B14,'[7]查询结果(2025年1月)'!$A$2:$M$25,13,0) -> 567.46448 | AT14: =VLOOKUP(B14,'[6]查询结果(2026年1月)'!$A$2:$M$25,13,0) -> 1702.7231 | AU14: =AT14/Q14 -> 0.18400211 | AV14: =RANK(AU14,$AU$5:$AU$25,1) -> 14 | AW14: =AT14/AS14-1 -> 2.0005809 | AX14: =RANK(AW14,$AW$5:$AW$25,1) -> 15 | AY14: =VLOOKUP(B14,[2]计算结果表!$B$1:$T$25,17,0) -> 9124.6468 | AZ14: =VLOOKUP(B14,[3]计算结果表!$B$1:$T$25,17,0) -> 8501.2702 | BA14: =AZ14/AY14-1 -> -0.068317885 | BB14: =AY14/C14 -> 0.084133659 | BC14: =AZ14/E14 -> 0.075845926 | BD14: =RANK(BC14,$BC$5:$BC$25,0) -> 8 | BE14: =BC14-BB14 -> -0.0082877327 | BF14: =VLOOKUP(B14,[2]计算结果表!$B$1:$T$25,9,0) -> -16.880975 | BG14: =VLOOKUP(B14,[3]计算结果表!$B$1:$T$25,9,0) -> 531.16718 | BH14: =BG14/BF14-1 -> -32.465433 | BI14: =BF14/I14 -> -0.0018172803 | BJ14: =BG14/J14 -> 0.04299182 | BK14: =RANK(BJ14,$BJ$5:$BJ$25,1) -> 12 | BL14: =VLOOKUP(B14,[8]市州营业收现率202501完成!$B$1:$AH$28,6,0) -> 7485.9799 | BM14: =VLOOKUP(B14,[9]市州营业收现率1月完成!$B$1:$AI$28,7,0) -> 6405.63 | BN14: =VLOOKUP(B14,[8]市州营业收现率202501完成!$B$1:$AH$28,5,0) -> 0.81323083 | BO14: =VLOOKUP(B14,[9]市州营业收现率1月完成!$B$1:$AI$28,5,0) -> 0.74169494 | BP14: =RANK(BO14,$BO$5:$BO$25,0) -> 15
A15: 11 | B15: 内江 | C15: 87486.809 | D15: 8336.977 | E15: 88473.879 | F15: 9659.8786 | G15: =E15/C15-1 -> 0.011282493 | H15: =F15/D15-1 -> 0.15867881 | I15: =VLOOKUP(B15,[2]计算结果表!$B$1:$AA$25,13,0) -> 6617.0006 | J15: =VLOOKUP(B15,[3]计算结果表!$B$1:$AA$25,13,0) -> 7491.4296 | K15: =J15/I15-1 -> 0.13214885 | L15: =I15/C15 -> 0.075634266 | M15: =J15/E15 -> 0.084673914 | N15: =RANK(M15,$M$5:$M$25,1) -> 6 | O15: =M15-L15 -> 0.0090396484 | P15: =VLOOKUP(B15,[2]计算结果表!$B$1:$AA$25,15,0) -> 4137.4405 | Q15: =VLOOKUP(B15,[3]计算结果表!$B$1:$AA$25,15,0) -> 4495.8385 | R15: =Q15/P15-1 -> 0.086623125 | S15: =P15/D15 -> 0.49627587 | T15: =Q15/F15 -> 0.46541356 | U15: =RANK(T15,$T$5:$T$25,1) -> 10 | V15: =T15-S15 -> -0.030862304 | W15: =VLOOKUP(B15,[3]计算结果表!$B$1:$T$25,18,0) -> 698.68423 | X15: =VLOOKUP(B15,[3]计算结果表!$B$1:$T$25,19,0) -> 3797.1543 | Y15: =VLOOKUP(B15,[1]分ICT资源型数据!$B$1:$P$23,11,0) -> 2930.5434 | Z15: =VLOOKUP(B15,[1]分ICT资源型数据!$B$1:$P$23,12,0) -> 5194.1508 | AA15: =W15/(Y15/11*12) -> 0.21854668 | AB15: =RANK(AA15,$AA$5:$AA$25,1) -> 11 | AC15: =X15/(Z15/11*12) -> 0.67012393 | AD15: =RANK(AC15,$AC$5:$AC$25,1) -> 11 | AE15: =VLOOKUP(B15,[2]计算结果表!$B$1:$T$25,16,0) -> 2479.5601 | AF15: =VLOOKUP(B15,[3]计算结果表!$B$1:$T$25,16,0) -> 2995.5911 | AG15: =AF15/AE15-1 -> 0.20811393 | AH15: =AE15/(C15-D15) -> 0.031327421 | AI15: =AF15/(E15-F15) -> 0.038008363 | AJ15: =RANK(AI15,$AI$5:$AI$25,1) -> 11 | AK15: =AI15-AH15 -> 0.0066809419 | AL15: =VLOOKUP(B15,'[5]查询结果(2025年1月)'!$A$2:$M$29,13,0) -> 1930.6016 | AM15: =VLOOKUP(B15,'[4]查询结果(2026年1月)'!$A$2:$M$29,13,0) -> 1121.7027 | AN15: =AM15/AL15-1 -> -0.41898803 | AO15: =RANK(AN15,$AN$5:$AN$25,1) -> 2 | AP15: =AL15/I15 -> 0.29176386 | AQ15: =AM15/J15 -> 0.14973146 | AR15: =RANK(AQ15,$AQ$5:$AQ$25,1) -> 7 | AS15: =VLOOKUP(B15,'[7]查询结果(2025年1月)'!$A$2:$M$25,13,0) -> 1676.5396 | AT15: =VLOOKUP(B15,'[6]查询结果(2026年1月)'!$A$2:$M$25,13,0) -> 825.92709 | AU15: =AT15/Q15 -> 0.18370924 | AV15: =RANK(AU15,$AU$5:$AU$25,1) -> 13 | AW15: =AT15/AS15-1 -> -0.50736203 | AX15: =RANK(AW15,$AW$5:$AW$25,1) -> 2 | AY15: =VLOOKUP(B15,[2]计算结果表!$B$1:$T$25,17,0) -> 5396.8265 | AZ15: =VLOOKUP(B15,[3]计算结果表!$B$1:$T$25,17,0) -> 5149.1241 | BA15: =AZ15/AY15-1 -> -0.045897781 | BB15: =AY15/C15 -> 0.061687316 | BC15: =AZ15/E15 -> 0.058199371 | BD15: =RANK(BC15,$BC$5:$BC$25,0) -> 14 | BE15: =BC15-BB15 -> -0.0034879449 | BF15: =VLOOKUP(B15,[2]计算结果表!$B$1:$T$25,9,0) -> 64.14032 | BG15: =VLOOKUP(B15,[3]计算结果表!$B$1:$T$25,9,0) -> 381.13766 | BH15: =BG15/BF15-1 -> 4.9422475 | BI15: =BF15/I15 -> 0.0096932619 | BJ15: =BG15/J15 -> 0.050876492 | BK15: =RANK(BJ15,$BJ$5:$BJ$25,1) -> 17 | BL15: =VLOOKUP(B15,[8]市州营业收现率202501完成!$B$1:$AH$28,6,0) -> 7757.6345 | BM15: =VLOOKUP(B15,[9]市州营业收现率1月完成!$B$1:$AI$28,7,0) -> 6738.0544 | BN15: =VLOOKUP(B15,[8]市州营业收现率202501完成!$B$1:$AH$28,5,0) -> 1.0579748 | BO15: =VLOOKUP(B15,[9]市州营业收现率1月完成!$B$1:$AI$28,5,0) -> 0.93951274 | BP15: =RANK(BO15,$BO$5:$BO$25,0) -> 3
A16: 12 | B16: 巴中 | C16: 77707.532 | D16: 7596.7086 | E16: 78754.27 | F16: 8513.2697 | G16: =E16/C16-1 -> 0.013470215 | H16: =F16/D16-1 -> 0.12065239 | I16: =VLOOKUP(B16,[2]计算结果表!$B$1:$AA$25,13,0) -> 8943.0168 | J16: =VLOOKUP(B16,[3]计算结果表!$B$1:$AA$25,13,0) -> 11348.61 | K16: =J16/I16-1 -> 0.26899126 | L16: =I16/C16 -> 0.11508558 | M16: =J16/E16 -> 0.14410152 | N16: =RANK(M16,$M$5:$M$25,1) -> 20 | O16: =M16-L16 -> 0.029015937 | P16: =VLOOKUP(B16,[2]计算结果表!$B$1:$AA$25,15,0) -> 6629.1811 | Q16: =VLOOKUP(B16,[3]计算结果表!$B$1:$AA$25,15,0) -> 8648.5597 | R16: =Q16/P16-1 -> 0.30461962 | S16: =P16/D16 -> 0.87263859 | T16: =Q16/F16 -> 1.0158917 | U16: =RANK(T16,$T$5:$T$25,1) -> 21 | V16: =T16-S16 -> 0.14325307 | W16: =VLOOKUP(B16,[3]计算结果表!$B$1:$T$25,18,0) -> 1072.8831 | X16: =VLOOKUP(B16,[3]计算结果表!$B$1:$T$25,19,0) -> 7575.6766 | Y16: =VLOOKUP(B16,[1]分ICT资源型数据!$B$1:$P$23,11,0) -> 2237.2388 | Z16: =VLOOKUP(B16,[1]分ICT资源型数据!$B$1:$P$23,12,0) -> 6966.1722 | AA16: =W16/(Y16/11*12) -> 0.43959373 | AB16: =RANK(AA16,$AA$5:$AA$25,1) -> 21 | AC16: =X16/(Z16/11*12) -> 0.99687031 | AD16: =RANK(AC16,$AC$5:$AC$25,1) -> 21 | AE16: =VLOOKUP(B16,[2]计算结果表!$B$1:$T$25,16,0) -> 2313.8357 | AF16: =VLOOKUP(B16,[3]计算结果表!$B$1:$T$25,16,0) -> 2700.0504 | AG16: =AF16/AE16-1 -> 0.16691535 | AH16: =AE16/(C16-D16) -> 0.033002547 | AI16: =AF16/(E16-F16) -> 0.038439806 | AJ16: =RANK(AI16,$AI$5:$AI$25,1) -> 12 | AK16: =AI16-AH16 -> 0.0054372597 | AL16: =VLOOKUP(B16,'[5]查询结果(2025年1月)'!$A$2:$M$29,13,0) -> 1593.628 | AM16: =VLOOKUP(B16,'[4]查询结果(2026年1月)'!$A$2:$M$29,13,0) -> 3386.8292 | AN16: =AM16/AL16-1 -> 1.1252319 | AO16: =RANK(AN16,$AN$5:$AN$25,1) -> 11 | AP16: =AL16/I16 -> 0.17819804 | AQ16: =AM16/J16 -> 0.29843559 | AR16: =RANK(AQ16,$AQ$5:$AQ$25,1) -> 19 | AS16: =VLOOKUP(B16,'[7]查询结果(2025年1月)'!$A$2:$M$25,13,0) -> 764.90706 | AT16: =VLOOKUP(B16,'[6]查询结果(2026年1月)'!$A$2:$M$25,13,0) -> 2398.4037 | AU16: =AT16/Q16 -> 0.27731828 | AV16: =RANK(AU16,$AU$5:$AU$25,1) -> 19 | AW16: =AT16/AS16-1 -> 2.1355491 | AX16: =RANK(AW16,$AW$5:$AW$25,1) -> 17 | AY16: =VLOOKUP(B16,[2]计算结果表!$B$1:$T$25,17,0) -> 6378.8563 | AZ16: =VLOOKUP(B16,[3]计算结果表!$B$1:$T$25,17,0) -> 6375.285 | BA16: =AZ16/AY16-1 -> -0.00055986463 | BB16: =AY16/C16 -> 0.082088005 | BC16: =AZ16/E16 -> 0.080951611 | BD16: =RANK(BC16,$BC$5:$BC$25,0) -> 6 | BE16: =BC16-BB16 -> -0.0011363938 | BF16: =VLOOKUP(B16,[2]计算结果表!$B$1:$T$25,9,0) -> 8.278065 | BG16: =VLOOKUP(B16,[3]计算结果表!$B$1:$T$25,9,0) -> 251.35376 | BH16: =BG16/BF16-1 -> 29.36383 | BI16: =BF16/I16 -> 0.00092564569 | BJ16: =BG16/J16 -> 0.022148418 | BK16: =RANK(BJ16,$BJ$5:$BJ$25,1) -> 3 | BL16: =VLOOKUP(B16,[8]市州营业收现率202501完成!$B$1:$AH$28,6,0) -> 7685.2532 | BM16: =VLOOKUP(B16,[9]市州营业收现率1月完成!$B$1:$AI$28,7,0) -> 6206.4503 | BN16: =VLOOKUP(B16,[8]市州营业收现率202501完成!$B$1:$AH$28,5,0) -> 1.1415971 | BO16: =VLOOKUP(B16,[9]市州营业收现率1月完成!$B$1:$AI$28,5,0) -> 0.97545102 | BP16: =RANK(BO16,$BO$5:$BO$25,0) -> 1
... A25: 21 | B25: 攀枝花 | C25: 41681.598 | D25: 5590.1337 | E25: 40623.803 | F25: 6186.8028 | G25: =E25/C25-1 -> -0.025377992 | H25: =F25/D25-1 -> 0.1067361 | I25: =VLOOKUP(B25,[2]计算结果表!$B$1:$AA$25,13,0) -> 5513.2764 | J25: =VLOOKUP(B25,[3]计算结果表!$B$1:$AA$25,13,0) -> 4452.94 | K25: =J25/I25-1 -> -0.19232418 | L25: =I25/C25 -> 0.13227123 | M25: =J25/E25 -> 0.10961406 | N25: =RANK(M25,$M$5:$M$25,1) -> 15 | O25: =M25-L25 -> -0.022657172 | P25: =VLOOKUP(B25,[2]计算结果表!$B$1:$AA$25,15,0) -> 3112.0354 | Q25: =VLOOKUP(B25,[3]计算结果表!$B$1:$AA$25,15,0) -> 2777.0568 | R25: =Q25/P25-1 -> -0.10763972 | S25: =P25/D25 -> 0.55670143 | T25: =Q25/F25 -> 0.44886784 | U25: =RANK(T25,$T$5:$T$25,1) -> 9 | V25: =T25-S25 -> -0.10783359 | W25: =VLOOKUP(B25,[3]计算结果表!$B$1:$T$25,18,0) -> 647.25239 | X25: =VLOOKUP(B25,[3]计算结果表!$B$1:$T$25,19,0) -> 2129.8044 | Y25: =VLOOKUP(B25,[1]分ICT资源型数据!$B$1:$P$23,11,0) -> 1936.2837 | Z25: =VLOOKUP(B25,[1]分ICT资源型数据!$B$1:$P$23,12,0) -> 3160.6951 | AA25: =W25/(Y25/11*12) -> 0.3064193 | AB25: =RANK(AA25,$AA$5:$AA$25,1) -> 16 | AC25: =X25/(Z25/11*12) -> 0.61768714 | AD25: =RANK(AC25,$AC$5:$AC$25,1) -> 7 | AE25: =VLOOKUP(B25,[2]计算结果表!$B$1:$T$25,16,0) -> 2401.2409 | AF25: =VLOOKUP(B25,[3]计算结果表!$B$1:$T$25,16,0) -> 1675.8832 | AG25: =AF25/AE25-1 -> -0.30207621 | AH25: =AE25/(C25-D25) -> 0.066532101 | AI25: =AF25/(E25-F25) -> 0.048665191 | AJ25: =RANK(AI25,$AI$5:$AI$25,1) -> 17 | AK25: =AI25-AH25 -> -0.01786691 | AL25: =VLOOKUP(B25,'[5]查询结果(2025年1月)'!$A$2:$M$29,13,0) -> 3137.5197 | AM25: =VLOOKUP(B25,'[4]查询结果(2026年1月)'!$A$2:$M$29,13,0) -> 1717.0265 | AN25: =AM25/AL25-1 -> -0.45274398 | AO25: =RANK(AN25,$AN$5:$AN$25,1) -> 1 | AP25: =AL25/I25 -> 0.56908442 | AQ25: =AM25/J25 -> 0.38559391 | AR25: =RANK(AQ25,$AQ$5:$AQ$25,1) -> 20 | AS25: =VLOOKUP(B25,'[7]查询结果(2025年1月)'!$A$2:$M$25,13,0) -> 1674.3851 | AT25: =VLOOKUP(B25,'[6]查询结果(2026年1月)'!$A$2:$M$25,13,0) -> 796.18991 | AU25: =AT25/Q25 -> 0.28670278 | AV25: =RANK(AU25,$AU$5:$AU$25,1) -> 20 | AW25: =AT25/AS25-1 -> -0.52448818 | AX25: =RANK(AW25,$AW$5:$AW$25,1) -> 1 | AY25: =VLOOKUP(B25,[2]计算结果表!$B$1:$T$25,17,0) -> 4569.0668 | AZ25: =VLOOKUP(B25,[3]计算结果表!$B$1:$T$25,17,0) -> 3572.3511 | BA25: =AZ25/AY25-1 -> -0.21814427 | BB25: =AY25/C25 -> 0.10961832 | BC25: =AZ25/E25 -> 0.087937387 | BD25: =RANK(BC25,$BC$5:$BC$25,0) -> 5 | BE25: =BC25-BB25 -> -0.021680934 | BF25: =VLOOKUP(B25,[2]计算结果表!$B$1:$T$25,9,0) -> -13.527662 | BG25: =VLOOKUP(B25,[3]计算结果表!$B$1:$T$25,9,0) -> 128.65198 | BH25: =BG25/BF25-1 -> -10.510289 | BI25: =BF25/I25 -> -0.0024536521 | BJ25: =BG25/J25 -> 0.028891469 | BK25: =RANK(BJ25,$BJ$5:$BJ$25,1) -> 6 | BL25: =VLOOKUP(B25,[8]市州营业收现率202501完成!$B$1:$AH$28,6,0) -> 3518.3671 | BM25: =VLOOKUP(B25,[9]市州营业收现率1月完成!$B$1:$AI$28,7,0) -> 1888.9082 | BN25: =VLOOKUP(B25,[8]市州营业收现率202501完成!$B$1:$AH$28,5,0) -> 1.0173207 | BO25: =VLOOKUP(B25,[9]市州营业收现率1月完成!$B$1:$AI$28,5,0) -> 0.50355393 | BP25: =RANK(BO25,$BO$5:$BO$25,0) -> 19
A26: 22 | B26: 市州合计 | C26: =SUM(C5:C25) -> 3051812 | D26: =SUM(D5:D25) -> 429644.34 | E26: =SUM(E5:E25) -> 3108676.9 | F26: =SUM(F5:F25) -> 486690.27 | I26: =SUM(I5:I25) -> 216671.22 | J26: =SUM(J5:J25) -> 285398.86 | K26: =J26/I26-1 -> 0.3171978 | L26: =I26/C26 -> 0.070997566 | M26: =J26/E26 -> 0.091807179 | O26: =M26-L26 -> 0.020809614 | P26: =SUM(P5:P25) -> 131867.99 | Q26: =SUM(Q5:Q25) -> 200433.19 | R26: =Q26/P26-1 -> 0.51995331 | S26: =P26/D26 -> 0.30692361 | T26: =Q26/F26 -> 0.41182905 | V26: =T26-S26 -> 0.10490544 | W26: =SUM(W5:W25) -> 35541.565 | X26: =SUM(X5:X25) -> 164891.62 | Y26: =SUM(Y5:Y25) -> 171371.33 | Z26: =SUM(Z5:Z25) -> 256134.06 | AA26: =W26/(Y26/11*12) -> 0.19011213 | AC26: =X26/(Z26/11*12) -> 0.59012322 | AE26: =SUM(AE5:AE25) -> 84803.23 | AF26: =SUM(AF5:AF25) -> 84965.666 | AG26: =AF26/AE26-1 -> 0.0019154499 | AH26: =AE26/(C26-D26) -> 0.032340888 | AI26: =AF26/(E26-F26) -> 0.032405072 | AK26: =AI26-AH26 -> 6.4184448e-05 | AL26: =SUM(AL5:AL25) -> 38202.338 | AM26: =SUM(AM5:AM25) -> 56901.068 | AN26: =AM26/AL26-1 -> 0.4894656 | AP26: =AL26/I26 -> 0.17631478 | AQ26: =AM26/J26 -> 0.19937385 | AS26: =SUM(AS5:AS25) -> 21415.724 | AT26: =SUM(AT5:AT25) -> 36358.532 | AU26: =AT26/Q26 -> 0.18139976 | AW26: =AT26/AS26-1 -> 0.69774939 | AY26: =SUM(AY5:AY25) -> 236350.02 | AZ26: =SUM(AZ5:AZ25) -> 234475.57 | BA26: =AZ26/AY26-1 -> -0.0079308055 | BB26: =AY26/C26 -> 0.0774458 | BC26: =AZ26/E26 -> 0.075426164 | BE26: =BC26-BB26 -> -0.0020196355 | BF26: =SUM(BF5:BF25) -> 2513.7683 | BG26: =SUM(BG5:BG25) -> 9289.7517 | BH26: =BG26/BF26-1 -> 2.6955481 | BI26: =BF26/I26 -> 0.011601764 | BJ26: =BG26/J26 -> 0.032550066 | BL26: =VLOOKUP(B26,[8]市州营业收现率202501完成!$B$1:$AH$28,6,0) -> 236589.33 | BM26: =VLOOKUP(B26,[9]市州营业收现率1月完成!$B$1:$AI$28,7,0) -> 203501.84 | BN26: =VLOOKUP(B26,[8]市州营业收现率202501完成!$B$1:$AH$28,5,0) -> 0.89038607 | BO26: =VLOOKUP(B26,[9]市州营业收现率1月完成!$B$1:$AI$28,5,0) -> 0.80384945
