Workbook

Sheet 2025年12月 
A1: 2025年12月市州应收账款情况表
A2: 序号 | B2: 单位 | C2: 2024年收入完成（不含云及IDC直销收入） | E2: 2025年收入预算（不含云及IDC运营中心直销客户的IDC收入） | I2: 应收账款总额占收比 | P2: 产数应收账款占产数收入比 | W2: 分资源型/ICT应收占收比 （注：资源型应收=组网专线+IDC ICT应收=产数应收+合同资产-资源应收 资源型收入=组网专线+IDC-云锦IDC收入 ICT应收=产数收入-组网专线-IDC） | AE2: 基础应收账款占基础收入比 | AL2: 一年以上应收账款占应收总额比 | AS2: 一年以上产数应收 | AY2: 预收账款占收比 | BF2: 营业收现率
C3: 收入完成 | D3: 产数收入完成 | E3: 收入 | F3: 产数收入 | G3: 收入同比 | H3: 产数收入同比 | I3: 202412 应收总额 | J3: 202512 应收总额 | K3: 应收总额同比增幅 | L3: 202412 占收比 | M3: 202512 占收比 | N3: 排名 | O3: 占收比同比 | P3: 202412 应收产数 | Q3: 202512 应收产数 | R3: 产数应收账款增幅 | S3: 202412 产数占收比 | T3: 202512 产数占收比 | U3: 排名 | V3: 产数占收比同比 | W3: 202512资源型应收账款总额 | X3: 202512产数ICT应收账款总额 | Y3: 202512资源型收入（剔除云锦IDC收入） | Z3: 202512产数ICT收入 | AA3: 202512资源型应收占收比 | AB3: 排名 | AC3: 202512产数ICT应收占收比 | AD3: 排名 | AE3: 202412 基础应收 | AF3: 202512 基础应收 | AG3: 基础应收同比增幅 | AH3: 202412 基础占收比 | AI3: 202512 基础占收比 | AJ3: 排名 | AK3: 基础占收比同比 | AL3: 202412 一年以上应收 | AM3: 202512 一年以上应收 | AN3: 一年以上同比增幅 | AO3: 排名 | AP3: 202412 一年以上占应收总额比 | AQ3: 202512 一年以上占应收总额比 | AR3: 排名 | AS3: 202412一年以上产数应收 | AT3: 202512一年以上产数应收 | AU3: 202512一年以上产数应收账款结构占比 | AV3: 排名 | AW3: 202512一年以上产数应收同比增幅 | AX3: 排名 | AY3: 202412 预收账款总额 | AZ3: 202512 预收账款总额 | BA3: 同比增幅 | BB3: 202412 占收比 | BC3: 202512 占收比 | BD3: 排名 | BE3: 占收比同比 | BF3: 202412经营活动现金流入完成 | BG3: 202512经营活动现金流入完成 | BH3: 202412营业收现率 | BI3: 202512营业收现率 | BJ3: 排名
A5: 1 | B5: 成都 | C5: 1022865.1 | D5: 196366.64 | E5: =VLOOKUP(B5,[6]Sheet1!$A$2:$I$24,5,0) -> 1035002.1 | F5: =VLOOKUP(B5,[6]Sheet1!$A$2:$I$24,7,0) -> 180143.51 | G5: =E5/C5-1 -> 0.011865679 | H5: =F5/D5-1 -> -0.082616562 | I5: =VLOOKUP(B5,[3]计算结果表!$B$1:$P$29,2,0) -> 47796.331 | J5: =VLOOKUP(B5,[2]计算结果表!$B$1:$R$30,13,0) -> 65648.641 | K5: =J5/I5-1 -> 0.37350798 | L5: =I5/C5 -> 0.046727892 | M5: =J5/E5 -> 0.06342851 | N5: =RANK(M5,$M$5:$M$25,1) -> 3 | O5: =M5-L5 -> 0.016700618 | P5: =VLOOKUP(B5,[3]计算结果表!$B$1:$P$29,13,0) -> 39848.97 | Q5: =VLOOKUP(B5,[2]计算结果表!$B$1:$R$30,15,0) -> 49949.914 | R5: =Q5/P5-1 -> 0.25348068 | S5: =P5/D5 -> 0.20293146 | T5: =Q5/F5 -> 0.27727846 | U5: =RANK(T5,$T$5:$T$25,1) -> 2 | V5: =T5-S5 -> 0.074346997 | W5: =VLOOKUP(B5,[2]计算结果表!$V$1:$Z$25,2,0)+VLOOKUP(B5,[2]计算结果表!$V$1:$Z$25,4,0) -> 5116.9173 | X5: =VLOOKUP(B5,[2]计算结果表!$V$1:$Z$25,3,0)+VLOOKUP(B5,[2]计算结果表!$V$1:$Z$25,5,0)+VLOOKUP(B5,[2]计算结果表!$B$1:$R$28,5,0) -> 44832.996 | Y5: =VLOOKUP(B5,[6]Sheet1!$A$2:$I$24,8,0) -> 75593.769 | Z5: =VLOOKUP(B5,[6]Sheet1!$A$2:$I$24,9,0) -> 104549.74 | AA5: =W5/(Y5) -> 0.06768967 | AB5: =RANK(AA5,$AA$5:$AA$25,1) -> 1 | AC5: =X5/Z5 -> 0.42881979 | AD5: =RANK(AC5,$AC$5:$AC$25,1) -> 3 | AE5: =VLOOKUP(B5,[3]计算结果表!$B$1:$P$29,14,0) -> 20914.229 | AF5: =VLOOKUP(B5,[2]计算结果表!$B$1:$R$30,16,0) -> 15698.728 | AG5: =AF5/AE5-1 -> -0.24937574 | AH5: =AE5/(C5-D5) -> 0.025304619 | AI5: =AF5/(E5-F5) -> 0.018364122 | AJ5: =RANK(AI5,$AI$5:$AI$25,1) -> 5 | AK5: =AI5-AH5 -> -0.0069404969 | AL5: 6300 | AM5: =VLOOKUP(B5,[1]Sheet1!$B$28:$F$52,4,0) -> 15814.298 | AN5: =AM5/AL5-1 -> 1.510206 | AO5: =RANK(AN5,$AN$5:$AN$25,1) -> 13 | AP5: =AL5/I5 -> 0.13180928 | AQ5: =AM5/#REF! -> #REF! | AR5: =RANK(AQ5,$AQ$5:$AQ$25,1) -> #REF! | AS5: 5120.2217 | AT5: =VLOOKUP(B5,[1]Sheet1!$B$28:$F$52,2,0) -> 9565.4404 | AU5: =AT5/Q5 -> 0.19150064 | AV5: =RANK(AU5,$AU$5:$AU$25,1) -> 15 | AW5: =AT5/AS5-1 -> 0.86816921 | AX5: =RANK(AW5,$AW$5:$AW$25,1) -> 9 | AY5: =VLOOKUP(B5,[3]计算结果表!$B$1:$P$29,15,0) -> 105126.28 | AZ5: =VLOOKUP(B5,[2]计算结果表!$B$1:$R$30,17,0) -> 104859.49 | BA5: =AZ5/AY5-1 -> -0.0025377812 | BB5: =AY5/C5 -> 0.10277628 | BC5: =AZ5/E5 -> 0.10131331 | BD5: =RANK(BC5,$BC$5:$BC$25,0) -> 3 | BE5: =BC5-BB5 -> -0.001462975 | BF5: =VLOOKUP(B5,[5]市州营业收现率202412完成!$B$1:$AH$28,6,0) -> 1075493 | BG5: =VLOOKUP(B5,[4]市州营业收现率12月完成!$B$1:$AI$28,7,0) -> 1117224.7 | BH5: =VLOOKUP(B5,[5]市州营业收现率202412完成!$B$1:$AH$28,5,0) -> 1.0514515 | BI5: =VLOOKUP(B5,[4]市州营业收现率12月完成!$B$1:$AI$28,5,0) -> 1.0794419 | BJ5: =RANK(BI5,$BI$5:$BI$25,0) -> 3
A6: 2 | B6: 绵阳 | C6: 186112.88 | D6: 22534.638 | E6: =VLOOKUP(B6,[6]Sheet1!$A$2:$I$24,5,0) -> 181679.31 | F6: =VLOOKUP(B6,[6]Sheet1!$A$2:$I$24,7,0) -> 18516.339 | G6: =E6/C6-1 -> -0.023821903 | H6: =F6/D6-1 -> -0.17831655 | I6: =VLOOKUP(B6,[3]计算结果表!$B$1:$P$29,2,0) -> 8492.4819 | J6: =VLOOKUP(B6,[2]计算结果表!$B$1:$R$30,13,0) -> 12485.355 | K6: =J6/I6-1 -> 0.47016563 | L6: =I6/C6 -> 0.045630813 | M6: =J6/E6 -> 0.068721941 | N6: =RANK(M6,$M$5:$M$25,1) -> 4 | O6: =M6-L6 -> 0.023091127 | P6: =VLOOKUP(B6,[3]计算结果表!$B$1:$P$29,13,0) -> 4043.9849 | Q6: =VLOOKUP(B6,[2]计算结果表!$B$1:$R$30,15,0) -> 7794.5834 | R6: =Q6/P6-1 -> 0.92745116 | S6: =P6/D6 -> 0.1794564 | T6: =Q6/F6 -> 0.42095705 | U6: =RANK(T6,$T$5:$T$25,1) -> 5 | V6: =T6-S6 -> 0.24150065 | W6: =VLOOKUP(B6,[2]计算结果表!$V$1:$Z$25,2,0)+VLOOKUP(B6,[2]计算结果表!$V$1:$Z$25,4,0) -> 1020.7057 | X6: =VLOOKUP(B6,[2]计算结果表!$V$1:$Z$25,3,0)+VLOOKUP(B6,[2]计算结果表!$V$1:$Z$25,5,0)+VLOOKUP(B6,[2]计算结果表!$B$1:$R$28,5,0) -> 6773.8777 | Y6: =VLOOKUP(B6,[6]Sheet1!$A$2:$I$24,8,0) -> 8170.1152 | Z6: =VLOOKUP(B6,[6]Sheet1!$A$2:$I$24,9,0) -> 10346.224 | AA6: =W6/(Y6) -> 0.12493162 | AB6: =RANK(AA6,$AA$5:$AA$25,1) -> 5 | AC6: =X6/Z6 -> 0.65471982 | AD6: =RANK(AC6,$AC$5:$AC$25,1) -> 9 | AE6: =VLOOKUP(B6,[3]计算结果表!$B$1:$P$29,14,0) -> 4953.997 | AF6: =VLOOKUP(B6,[2]计算结果表!$B$1:$R$30,16,0) -> 4690.7716 | AG6: =AF6/AE6-1 -> -0.053133941 | AH6: =AE6/(C6-D6) -> 0.030285183 | AI6: =AF6/(E6-F6) -> 0.028748995 | AJ6: =RANK(AI6,$AI$5:$AI$25,1) -> 12 | AK6: =AI6-AH6 -> -0.0015361882 | AL6: 698.12151 | AM6: =VLOOKUP(B6,[1]Sheet1!$B$28:$F$52,4,0) -> 1675.2615 | AN6: =AM6/AL6-1 -> 1.3996704 | AO6: =RANK(AN6,$AN$5:$AN$25,1) -> 12 | AP6: =AL6/I6 -> 0.082204651 | AQ6: =AM6/#REF! -> #REF! | AR6: =RANK(AQ6,$AQ$5:$AQ$25,1) -> #REF! | AS6: 316.43461 | AT6: =VLOOKUP(B6,[1]Sheet1!$B$28:$F$52,2,0) -> 1055.0061 | AU6: =AT6/Q6 -> 0.13535119 | AV6: =RANK(AU6,$AU$5:$AU$25,1) -> 9 | AW6: =AT6/AS6-1 -> 2.3340415 | AX6: =RANK(AW6,$AW$5:$AW$25,1) -> 14 | AY6: =VLOOKUP(B6,[3]计算结果表!$B$1:$P$29,15,0) -> 12652.487 | AZ6: =VLOOKUP(B6,[2]计算结果表!$B$1:$R$30,17,0) -> 13569.427 | BA6: =AZ6/AY6-1 -> 0.07247113 | BB6: =AY6/C6 -> 0.067982865 | BC6: =AZ6/E6 -> 0.074688891 | BD6: =RANK(BC6,$BC$5:$BC$25,0) -> 12 | BE6: =BC6-BB6 -> 0.0067060266 | BF6: =VLOOKUP(B6,[5]市州营业收现率202412完成!$B$1:$AH$28,6,0) -> 184023.79 | BG6: =VLOOKUP(B6,[4]市州营业收现率12月完成!$B$1:$AI$28,7,0) -> 188666.64 | BH6: =VLOOKUP(B6,[5]市州营业收现率202412完成!$B$1:$AH$28,5,0) -> 0.98877514 | BI6: =VLOOKUP(B6,[4]市州营业收现率12月完成!$B$1:$AI$28,5,0) -> 1.0384597 | BJ6: =RANK(BI6,$BI$5:$BI$25,0) -> 13
A7: 3 | B7: 南充 | C7: 182016.22 | D7: 16400.826 | E7: =VLOOKUP(B7,[6]Sheet1!$A$2:$I$24,5,0) -> 179641.91 | F7: =VLOOKUP(B7,[6]Sheet1!$A$2:$I$24,7,0) -> 12469.679 | G7: =E7/C7-1 -> -0.013044497 | H7: =F7/D7-1 -> -0.23969204 | I7: =VLOOKUP(B7,[3]计算结果表!$B$1:$P$29,2,0) -> 9361.3862 | J7: =VLOOKUP(B7,[2]计算结果表!$B$1:$R$30,13,0) -> 16910.449 | K7: =J7/I7-1 -> 0.80640438 | L7: =I7/C7 -> 0.051431604 | M7: =J7/E7 -> 0.094134209 | N7: =RANK(M7,$M$5:$M$25,1) -> 11 | O7: =M7-L7 -> 0.042702604 | P7: =VLOOKUP(B7,[3]计算结果表!$B$1:$P$29,13,0) -> 6204.2775 | Q7: =VLOOKUP(B7,[2]计算结果表!$B$1:$R$30,15,0) -> 9703.4284 | R7: =Q7/P7-1 -> 0.56399007 | S7: =P7/D7 -> 0.37829055 | T7: =Q7/F7 -> 0.77816186 | U7: =RANK(T7,$T$5:$T$25,1) -> 20 | V7: =T7-S7 -> 0.39987132 | W7: =VLOOKUP(B7,[2]计算结果表!$V$1:$Z$25,2,0)+VLOOKUP(B7,[2]计算结果表!$V$1:$Z$25,4,0) -> 984.45277 | X7: =VLOOKUP(B7,[2]计算结果表!$V$1:$Z$25,3,0)+VLOOKUP(B7,[2]计算结果表!$V$1:$Z$25,5,0)+VLOOKUP(B7,[2]计算结果表!$B$1:$R$28,5,0) -> 8718.9757 | Y7: =VLOOKUP(B7,[6]Sheet1!$A$2:$I$24,8,0) -> 5627.9188 | Z7: =VLOOKUP(B7,[6]Sheet1!$A$2:$I$24,9,0) -> 6841.76 | AA7: =W7/(Y7) -> 0.17492306 | AB7: =RANK(AA7,$AA$5:$AA$25,1) -> 7 | AC7: =X7/Z7 -> 1.2743761 | AD7: =RANK(AC7,$AC$5:$AC$25,1) -> 18 | AE7: =VLOOKUP(B7,[3]计算结果表!$B$1:$P$29,14,0) -> 5797.6865 | AF7: =VLOOKUP(B7,[2]计算结果表!$B$1:$R$30,16,0) -> 7207.0206 | AG7: =AF7/AE7-1 -> 0.2430856 | AH7: =AE7/(C7-D7) -> 0.03500693 | AI7: =AF7/(E7-F7) -> 0.04311135 | AJ7: =RANK(AI7,$AI$5:$AI$25,1) -> 17 | AK7: =AI7-AH7 -> 0.0081044202 | AL7: 2864.9321 | AM7: =VLOOKUP(B7,[1]Sheet1!$B$28:$F$52,4,0) -> 2929.7696 | AN7: =AM7/AL7-1 -> 0.022631426 | AO7: =RANK(AN7,$AN$5:$AN$25,1) -> 4 | AP7: =AL7/I7 -> 0.30603717 | AQ7: =AM7/#REF! -> #REF! | AR7: =RANK(AQ7,$AQ$5:$AQ$25,1) -> #REF! | AS7: 2574.0586 | AT7: =VLOOKUP(B7,[1]Sheet1!$B$28:$F$52,2,0) -> 2420.8433 | AU7: =AT7/Q7 -> 0.2494833 | AV7: =RANK(AU7,$AU$5:$AU$25,1) -> 17 | AW7: =AT7/AS7-1 -> -0.059522839 | AX7: =RANK(AW7,$AW$5:$AW$25,1) -> 3 | AY7: =VLOOKUP(B7,[3]计算结果表!$B$1:$P$29,15,0) -> 7938.0273 | AZ7: =VLOOKUP(B7,[2]计算结果表!$B$1:$R$30,17,0) -> 9996.2278 | BA7: =AZ7/AY7-1 -> 0.25928363 | BB7: =AY7/C7 -> 0.043611648 | BC7: =AZ7/E7 -> 0.055645299 | BD7: =RANK(BC7,$BC$5:$BC$25,0) -> 19 | BE7: =BC7-BB7 -> 0.012033651 | BF7: =VLOOKUP(B7,[5]市州营业收现率202412完成!$B$1:$AH$28,6,0) -> 175308.57 | BG7: =VLOOKUP(B7,[4]市州营业收现率12月完成!$B$1:$AI$28,7,0) -> 189823.62 | BH7: =VLOOKUP(B7,[5]市州营业收现率202412完成!$B$1:$AH$28,5,0) -> 0.96314808 | BI7: =VLOOKUP(B7,[4]市州营业收现率12月完成!$B$1:$AI$28,5,0) -> 1.0566778 | BJ7: =RANK(BI7,$BI$5:$BI$25,0) -> 9
A8: 4 | B8: 泸州 | C8: 163512.15 | D8: 16643.254 | E8: =VLOOKUP(B8,[6]Sheet1!$A$2:$I$24,5,0) -> 162553.55 | F8: =VLOOKUP(B8,[6]Sheet1!$A$2:$I$24,7,0) -> 16331.369 | G8: =E8/C8-1 -> -0.005862571 | H8: =F8/D8-1 -> -0.01873939 | I8: =VLOOKUP(B8,[3]计算结果表!$B$1:$P$29,2,0) -> 8830.6939 | J8: =VLOOKUP(B8,[2]计算结果表!$B$1:$R$30,13,0) -> 13588.012 | K8: =J8/I8-1 -> 0.53872532 | L8: =I8/C8 -> 0.054006347 | M8: =J8/E8 -> 0.083590992 | N8: =RANK(M8,$M$5:$M$25,1) -> 7 | O8: =M8-L8 -> 0.029584645 | P8: =VLOOKUP(B8,[3]计算结果表!$B$1:$P$29,13,0) -> 6070.8391 | Q8: =VLOOKUP(B8,[2]计算结果表!$B$1:$R$30,15,0) -> 8880.2879 | R8: =Q8/P8-1 -> 0.46277766 | S8: =P8/D8 -> 0.36476276 | T8: =Q8/F8 -> 0.54375648 | U8: =RANK(T8,$T$5:$T$25,1) -> 11 | V8: =T8-S8 -> 0.17899372 | W8: =VLOOKUP(B8,[2]计算结果表!$V$1:$Z$25,2,0)+VLOOKUP(B8,[2]计算结果表!$V$1:$Z$25,4,0) -> 1601.0825 | X8: =VLOOKUP(B8,[2]计算结果表!$V$1:$Z$25,3,0)+VLOOKUP(B8,[2]计算结果表!$V$1:$Z$25,5,0)+VLOOKUP(B8,[2]计算结果表!$B$1:$R$28,5,0) -> 7279.2054 | Y8: =VLOOKUP(B8,[6]Sheet1!$A$2:$I$24,8,0) -> 5281.2143 | Z8: =VLOOKUP(B8,[6]Sheet1!$A$2:$I$24,9,0) -> 11050.155 | AA8: =W8/(Y8) -> 0.3031656 | AB8: =RANK(AA8,$AA$5:$AA$25,1) -> 15 | AC8: =X8/Z8 -> 0.65874239 | AD8: =RANK(AC8,$AC$5:$AC$25,1) -> 10 | AE8: =VLOOKUP(B8,[3]计算结果表!$B$1:$P$29,14,0) -> 4239.1276 | AF8: =VLOOKUP(B8,[2]计算结果表!$B$1:$R$30,16,0) -> 4707.7244 | AG8: =AF8/AE8-1 -> 0.11054088 | AH8: =AE8/(C8-D8) -> 0.028863344 | AI8: =AF8/(E8-F8) -> 0.032195693 | AJ8: =RANK(AI8,$AI$5:$AI$25,1) -> 13 | AK8: =AI8-AH8 -> 0.0033323488 | AL8: 1645.8947 | AM8: =VLOOKUP(B8,[1]Sheet1!$B$28:$F$52,4,0) -> 2113.8636 | AN8: =AM8/AL8-1 -> 0.28432495 | AO8: =RANK(AN8,$AN$5:$AN$25,1) -> 5 | AP8: =AL8/I8 -> 0.1863834 | AQ8: =AM8/#REF! -> #REF! | AR8: =RANK(AQ8,$AQ$5:$AQ$25,1) -> #REF! | AS8: 1048.6926 | AT8: =VLOOKUP(B8,[1]Sheet1!$B$28:$F$52,2,0) -> 1091.913 | AU8: =AT8/Q8 -> 0.12295919 | AV8: =RANK(AU8,$AU$5:$AU$25,1) -> 7 | AW8: =AT8/AS8-1 -> 0.04121356 | AX8: =RANK(AW8,$AW$5:$AW$25,1) -> 4 | AY8: =VLOOKUP(B8,[3]计算结果表!$B$1:$P$29,15,0) -> 8174.0978 | AZ8: =VLOOKUP(B8,[2]计算结果表!$B$1:$R$30,17,0) -> 11893.448 | BA8: =AZ8/AY8-1 -> 0.45501665 | BB8: =AY8/C8 -> 0.049990767 | BC8: =AZ8/E8 -> 0.073166341 | BD8: =RANK(BC8,$BC$5:$BC$25,0) -> 13 | BE8: =BC8-BB8 -> 0.023175574 | BF8: =VLOOKUP(B8,[5]市州营业收现率202412完成!$B$1:$AH$28,6,0) -> 161860.91 | BG8: =VLOOKUP(B8,[4]市州营业收现率12月完成!$B$1:$AI$28,7,0) -> 170099.09 | BH8: =VLOOKUP(B8,[5]市州营业收现率202412完成!$B$1:$AH$28,5,0) -> 0.98990141 | BI8: =VLOOKUP(B8,[4]市州营业收现率12月完成!$B$1:$AI$28,5,0) -> 1.0464188 | BJ8: =RANK(BI8,$BI$5:$BI$25,0) -> 11
A9: 5 | B9: 凉山 | C9: 138671.02 | D9: 20777.368 | E9: =VLOOKUP(B9,[6]Sheet1!$A$2:$I$24,5,0) -> 140988.95 | F9: =VLOOKUP(B9,[6]Sheet1!$A$2:$I$24,7,0) -> 21848.297 | G9: =E9/C9-1 -> 0.016715332 | H9: =F9/D9-1 -> 0.051543085 | I9: =VLOOKUP(B9,[3]计算结果表!$B$1:$P$29,2,0) -> 7086.1498 | J9: =VLOOKUP(B9,[2]计算结果表!$B$1:$R$30,13,0) -> 14171.425 | K9: =J9/I9-1 -> 0.99987656 | L9: =I9/C9 -> 0.051100438 | M9: =J9/E9 -> 0.10051444 | N9: =RANK(M9,$M$5:$M$25,1) -> 14 | O9: =M9-L9 -> 0.049413998 | P9: =VLOOKUP(B9,[3]计算结果表!$B$1:$P$29,13,0) -> 4614.4637 | Q9: =VLOOKUP(B9,[2]计算结果表!$B$1:$R$30,15,0) -> 9386.5704 | R9: =Q9/P9-1 -> 1.0341628 | S9: =P9/D9 -> 0.22209087 | T9: =Q9/F9 -> 0.4296248 | U9: =RANK(T9,$T$5:$T$25,1) -> 7 | V9: =T9-S9 -> 0.20753393 | W9: =VLOOKUP(B9,[2]计算结果表!$V$1:$Z$25,2,0)+VLOOKUP(B9,[2]计算结果表!$V$1:$Z$25,4,0) -> 2049.7143 | X9: =VLOOKUP(B9,[2]计算结果表!$V$1:$Z$25,3,0)+VLOOKUP(B9,[2]计算结果表!$V$1:$Z$25,5,0)+VLOOKUP(B9,[2]计算结果表!$B$1:$R$28,5,0) -> 7336.8561 | Y9: =VLOOKUP(B9,[6]Sheet1!$A$2:$I$24,8,0) -> 9430.2202 | Z9: =VLOOKUP(B9,[6]Sheet1!$A$2:$I$24,9,0) -> 12418.077 | AA9: =W9/(Y9) -> 0.21735593 | AB9: =RANK(AA9,$AA$5:$AA$25,1) -> 10 | AC9: =X9/Z9 -> 0.59082063 | AD9: =RANK(AC9,$AC$5:$AC$25,1) -> 6 | AE9: =VLOOKUP(B9,[3]计算结果表!$B$1:$P$29,14,0) -> 2813.9861 | AF9: =VLOOKUP(B9,[2]计算结果表!$B$1:$R$30,16,0) -> 4784.8546 | AG9: =AF9/AE9-1 -> 0.70038317 | AH9: =AE9/(C9-D9) -> 0.023868852 | AI9: =AF9/(E9-F9) -> 0.040161392 | AJ9: =RANK(AI9,$AI$5:$AI$25,1) -> 16 | AK9: =AI9-AH9 -> 0.016292541 | AL9: 826.75468 | AM9: =VLOOKUP(B9,[1]Sheet1!$B$28:$F$52,4,0) -> 2225.9156 | AN9: =AM9/AL9-1 -> 1.6923532 | AO9: =RANK(AN9,$AN$5:$AN$25,1) -> 16 | AP9: =AL9/I9 -> 0.11667192 | AQ9: =AM9/#REF! -> #REF! | AR9: =RANK(AQ9,$AQ$5:$AQ$25,1) -> #REF! | AS9: 181.48445 | AT9: =VLOOKUP(B9,[1]Sheet1!$B$28:$F$52,2,0) -> 1809.4405 | AU9: =AT9/Q9 -> 0.19276908 | AV9: =RANK(AU9,$AU$5:$AU$25,1) -> 16 | AW9: =AT9/AS9-1 -> 8.9702233 | AX9: =RANK(AW9,$AW$5:$AW$25,1) -> 21 | AY9: =VLOOKUP(B9,[3]计算结果表!$B$1:$P$29,15,0) -> 14870.445 | AZ9: =VLOOKUP(B9,[2]计算结果表!$B$1:$R$30,17,0) -> 13482.477 | BA9: =AZ9/AY9-1 -> -0.093337386 | BB9: =AY9/C9 -> 0.10723542 | BC9: =AZ9/E9 -> 0.095627894 | BD9: =RANK(BC9,$BC$5:$BC$25,0) -> 5 | BE9: =BC9-BB9 -> -0.011607526 | BF9: =VLOOKUP(B9,[5]市州营业收现率202412完成!$B$1:$AH$28,6,0) -> 135962.55 | BG9: =VLOOKUP(B9,[4]市州营业收现率12月完成!$B$1:$AI$28,7,0) -> 143456.89 | BH9: =VLOOKUP(B9,[5]市州营业收现率202412完成!$B$1:$AH$28,5,0) -> 0.98046837 | BI9: =VLOOKUP(B9,[4]市州营业收现率12月完成!$B$1:$AI$28,5,0) -> 1.0175045 | BJ9: =RANK(BI9,$BI$5:$BI$25,0) -> 16
A10: 6 | B10: 宜宾 | C10: 138807.87 | D10: 15780.567 | E10: =VLOOKUP(B10,[6]Sheet1!$A$2:$I$24,5,0) -> 140557.38 | F10: =VLOOKUP(B10,[6]Sheet1!$A$2:$I$24,7,0) -> 15542.303 | G10: =E10/C10-1 -> 0.012603831 | H10: =F10/D10-1 -> -0.01509859 | I10: =VLOOKUP(B10,[3]计算结果表!$B$1:$P$29,2,0) -> 5731.0392 | J10: =VLOOKUP(B10,[2]计算结果表!$B$1:$R$30,13,0) -> 12902.441 | K10: =J10/I10-1 -> 1.2513266 | L10: =I10/C10 -> 0.041287568 | M10: =J10/E10 -> 0.091794834 | N10: =RANK(M10,$M$5:$M$25,1) -> 10 | O10: =M10-L10 -> 0.050507266 | P10: =VLOOKUP(B10,[3]计算结果表!$B$1:$P$29,13,0) -> 3266.0717 | Q10: =VLOOKUP(B10,[2]计算结果表!$B$1:$R$30,15,0) -> 8639.5112 | R10: =Q10/P10-1 -> 1.6452301 | S10: =P10/D10 -> 0.20696796 | T10: =Q10/F10 -> 0.55587074 | U10: =RANK(T10,$T$5:$T$25,1) -> 12 | V10: =T10-S10 -> 0.34890278 | W10: =VLOOKUP(B10,[2]计算结果表!$V$1:$Z$25,2,0)+VLOOKUP(B10,[2]计算结果表!$V$1:$Z$25,4,0) -> 1593.3915 | X10: =VLOOKUP(B10,[2]计算结果表!$V$1:$Z$25,3,0)+VLOOKUP(B10,[2]计算结果表!$V$1:$Z$25,5,0)+VLOOKUP(B10,[2]计算结果表!$B$1:$R$28,5,0) -> 7046.1197 | Y10: =VLOOKUP(B10,[6]Sheet1!$A$2:$I$24,8,0) -> 5046.3622 | Z10: =VLOOKUP(B10,[6]Sheet1!$A$2:$I$24,9,0) -> 10495.94 | AA10: =W10/(Y10) -> 0.31575053 | AB10: =RANK(AA10,$AA$5:$AA$25,1) -> 18 | AC10: =X10/Z10 -> 0.67131858 | AD10: =RANK(AC10,$AC$5:$AC$25,1) -> 11 | AE10: =VLOOKUP(B10,[3]计算结果表!$B$1:$P$29,14,0) -> 2609.9943 | AF10: =VLOOKUP(B10,[2]计算结果表!$B$1:$R$30,16,0) -> 4262.93 | AG10: =AF10/AE10-1 -> 0.63331007 | AH10: =AE10/(C10-D10) -> 0.021214757 | AI10: =AF10/(E10-F10) -> 0.034099327 | AJ10: =RANK(AI10,$AI$5:$AI$25,1) -> 14 | AK10: =AI10-AH10 -> 0.01288457 | AL10: 476.34727 | AM10: =VLOOKUP(B10,[1]Sheet1!$B$28:$F$52,4,0) -> 1332.5851 | AN10: =AM10/AL10-1 -> 1.7975077 | AO10: =RANK(AN10,$AN$5:$AN$25,1) -> 17 | AP10: =AL10/I10 -> 0.083117084 | AQ10: =AM10/#REF! -> #REF! | AR10: =RANK(AQ10,$AQ$5:$AQ$25,1) -> #REF! | AS10: 202.42965 | AT10: =VLOOKUP(B10,[1]Sheet1!$B$28:$F$52,2,0) -> 902.16111 | AU10: =AT10/Q10 -> 0.1044227 | AV10: =RANK(AU10,$AU$5:$AU$25,1) -> 2 | AW10: =AT10/AS10-1 -> 3.4566648 | AX10: =RANK(AW10,$AW$5:$AW$25,1) -> 18 | AY10: =VLOOKUP(B10,[3]计算结果表!$B$1:$P$29,15,0) -> 9218.3307 | AZ10: =VLOOKUP(B10,[2]计算结果表!$B$1:$R$30,17,0) -> 7908.8259 | BA10: =AZ10/AY10-1 -> -0.14205444 | BB10: =AY10/C10 -> 0.066410722 | BC10: =AZ10/E10 -> 0.056267597 | BD10: =RANK(BC10,$BC$5:$BC$25,0) -> 18 | BE10: =BC10-BB10 -> -0.010143125 | BF10: =VLOOKUP(B10,[5]市州营业收现率202412完成!$B$1:$AH$28,6,0) -> 152540.92 | BG10: =VLOOKUP(B10,[4]市州营业收现率12月完成!$B$1:$AI$28,7,0) -> 140566.97 | BH10: =VLOOKUP(B10,[5]市州营业收现率202412完成!$B$1:$AH$28,5,0) -> 1.0989357 | BI10: =VLOOKUP(B10,[4]市州营业收现率12月完成!$B$1:$AI$28,5,0) -> 1.0000682 | BJ10: =RANK(BI10,$BI$5:$BI$25,0) -> 20
A11: 7 | B11: 达州 | C11: 121838.88 | D11: 15065.656 | E11: =VLOOKUP(B11,[6]Sheet1!$A$2:$I$24,5,0) -> 120354.81 | F11: =VLOOKUP(B11,[6]Sheet1!$A$2:$I$24,7,0) -> 12304.33 | G11: =E11/C11-1 -> -0.012180599 | H11: =F11/D11-1 -> -0.18328613 | I11: =VLOOKUP(B11,[3]计算结果表!$B$1:$P$29,2,0) -> 7000.0014 | J11: =VLOOKUP(B11,[2]计算结果表!$B$1:$R$30,13,0) -> 12750.042 | K11: =J11/I11-1 -> 0.82143414 | L11: =I11/C11 -> 0.057452937 | M11: =J11/E11 -> 0.10593712 | N11: =RANK(M11,$M$5:$M$25,1) -> 16 | O11: =M11-L11 -> 0.048484181 | P11: =VLOOKUP(B11,[3]计算结果表!$B$1:$P$29,13,0) -> 4486.7774 | Q11: =VLOOKUP(B11,[2]计算结果表!$B$1:$R$30,15,0) -> 7580.2141 | R11: =Q11/P11-1 -> 0.68945626 | S11: =P11/D11 -> 0.29781494 | T11: =Q11/F11 -> 0.6160607 | U11: =RANK(T11,$T$5:$T$25,1) -> 16 | V11: =T11-S11 -> 0.31824575 | W11: =VLOOKUP(B11,[2]计算结果表!$V$1:$Z$25,2,0)+VLOOKUP(B11,[2]计算结果表!$V$1:$Z$25,4,0) -> 1810.8283 | X11: =VLOOKUP(B11,[2]计算结果表!$V$1:$Z$25,3,0)+VLOOKUP(B11,[2]计算结果表!$V$1:$Z$25,5,0)+VLOOKUP(B11,[2]计算结果表!$B$1:$R$28,5,0) -> 5769.3857 | Y11: =VLOOKUP(B11,[6]Sheet1!$A$2:$I$24,8,0) -> 6111.6109 | Z11: =VLOOKUP(B11,[6]Sheet1!$A$2:$I$24,9,0) -> 6192.7191 | AA11: =W11/(Y11) -> 0.29629313 | AB11: =RANK(AA11,$AA$5:$AA$25,1) -> 14 | AC11: =X11/Z11 -> 0.93164015 | AD11: =RANK(AC11,$AC$5:$AC$25,1) -> 16 | AE11: =VLOOKUP(B11,[3]计算结果表!$B$1:$P$29,14,0) -> 4759.9747 | AF11: =VLOOKUP(B11,[2]计算结果表!$B$1:$R$30,16,0) -> 5169.8275 | AG11: =AF11/AE11-1 -> 0.086103992 | AH11: =AE11/(C11-D11) -> 0.044580228 | AI11: =AF11/(E11-F11) -> 0.04784641 | AJ11: =RANK(AI11,$AI$5:$AI$25,1) -> 18 | AK11: =AI11-AH11 -> 0.0032661817 | AL11: 2069.3315 | AM11: =VLOOKUP(B11,[1]Sheet1!$B$28:$F$52,4,0) -> 4332.747 | AN11: =AM11/AL11-1 -> 1.0937906 | AO11: =RANK(AN11,$AN$5:$AN$25,1) -> 10 | AP11: =AL11/I11 -> 0.29561873 | AQ11: =AM11/#REF! -> #REF! | AR11: =RANK(AQ11,$AQ$5:$AQ$25,1) -> #REF! | AS11: 1093.1597 | AT11: =VLOOKUP(B11,[1]Sheet1!$B$28:$F$52,2,0) -> 3214.8603 | AU11: =AT11/Q11 -> 0.42411207 | AV11: =RANK(AU11,$AU$5:$AU$25,1) -> 21 | AW11: =AT11/AS11-1 -> 1.9408881 | AX11: =RANK(AW11,$AW$5:$AW$25,1) -> 12 | AY11: =VLOOKUP(B11,[3]计算结果表!$B$1:$P$29,15,0) -> 6705.6499 | AZ11: =VLOOKUP(B11,[2]计算结果表!$B$1:$R$30,17,0) -> 8197.2258 | BA11: =AZ11/AY11-1 -> 0.22243569 | BB11: =AY11/C11 -> 0.055037029 | BC11: =AZ11/E11 -> 0.068108835 | BD11: =RANK(BC11,$BC$5:$BC$25,0) -> 14 | BE11: =BC11-BB11 -> 0.013071806 | BF11: =VLOOKUP(B11,[5]市州营业收现率202412完成!$B$1:$AH$28,6,0) -> 118296.77 | BG11: =VLOOKUP(B11,[4]市州营业收现率12月完成!$B$1:$AI$28,7,0) -> 125757.34 | BH11: =VLOOKUP(B11,[5]市州营业收现率202412完成!$B$1:$AH$28,5,0) -> 0.97092791 | BI11: =VLOOKUP(B11,[4]市州营业收现率12月完成!$B$1:$AI$28,5,0) -> 1.0448884 | BJ11: =RANK(BI11,$BI$5:$BI$25,0) -> 12
A12: 8 | B12: 乐山 | C12: 118805.11 | D12: 16584.622 | E12: =VLOOKUP(B12,[6]Sheet1!$A$2:$I$24,5,0) -> 120556.02 | F12: =VLOOKUP(B12,[6]Sheet1!$A$2:$I$24,7,0) -> 16066.625 | G12: =E12/C12-1 -> 0.014737688 | H12: =F12/D12-1 -> -0.031233582 | I12: =VLOOKUP(B12,[3]计算结果表!$B$1:$P$29,2,0) -> 8866.8129 | J12: =VLOOKUP(B12,[2]计算结果表!$B$1:$R$30,13,0) -> 13095.459 | K12: =J12/I12-1 -> 0.47690711 | L12: =I12/C12 -> 0.074633262 | M12: =J12/E12 -> 0.10862551 | N12: =RANK(M12,$M$5:$M$25,1) -> 18 | O12: =M12-L12 -> 0.033992244 | P12: =VLOOKUP(B12,[3]计算结果表!$B$1:$P$29,13,0) -> 7638.3707 | Q12: =VLOOKUP(B12,[2]计算结果表!$B$1:$R$30,15,0) -> 10777.343 | R12: =Q12/P12-1 -> 0.41094788 | S12: =P12/D12 -> 0.46056948 | T12: =Q12/F12 -> 0.67079073 | U12: =RANK(T12,$T$5:$T$25,1) -> 17 | V12: =T12-S12 -> 0.21022125 | W12: =VLOOKUP(B12,[2]计算结果表!$V$1:$Z$25,2,0)+VLOOKUP(B12,[2]计算结果表!$V$1:$Z$25,4,0) -> 1358.2988 | X12: =VLOOKUP(B12,[2]计算结果表!$V$1:$Z$25,3,0)+VLOOKUP(B12,[2]计算结果表!$V$1:$Z$25,5,0)+VLOOKUP(B12,[2]计算结果表!$B$1:$R$28,5,0) -> 9419.0441 | Y12: =VLOOKUP(B12,[6]Sheet1!$A$2:$I$24,8,0) -> 5977.0417 | Z12: =VLOOKUP(B12,[6]Sheet1!$A$2:$I$24,9,0) -> 10089.583 | AA12: =W12/(Y12) -> 0.2272527 | AB12: =RANK(AA12,$AA$5:$AA$25,1) -> 12 | AC12: =X12/Z12 -> 0.93354146 | AD12: =RANK(AC12,$AC$5:$AC$25,1) -> 17 | AE12: =VLOOKUP(B12,[3]计算结果表!$B$1:$P$29,14,0) -> 2332.4422 | AF12: =VLOOKUP(B12,[2]计算结果表!$B$1:$R$30,16,0) -> 2318.116 | AG12: =AF12/AE12-1 -> -0.0061421261 | AH12: =AE12/(C12-D12) -> 0.022817756 | AI12: =AF12/(E12-F12) -> 0.022185179 | AJ12: =RANK(AI12,$AI$5:$AI$25,1) -> 6 | AK12: =AI12-AH12 -> -0.00063257695 | AL12: 1030.6579 | AM12: =VLOOKUP(B12,[1]Sheet1!$B$28:$F$52,4,0) -> 3297.2882 | AN12: =AM12/AL12-1 -> 2.1992073 | AO12: =RANK(AN12,$AN$5:$AN$25,1) -> 19 | AP12: =AL12/I12 -> 0.11623769 | AQ12: =AM12/#REF! -> #REF! | AR12: =RANK(AQ12,$AQ$5:$AQ$25,1) -> #REF! | AS12: 696.25907 | AT12: =VLOOKUP(B12,[1]Sheet1!$B$28:$F$52,2,0) -> 2845.8183 | AU12: =AT12/Q12 -> 0.26405565 | AV12: =RANK(AU12,$AU$5:$AU$25,1) -> 18 | AW12: =AT12/AS12-1 -> 3.087298 | AX12: =RANK(AW12,$AW$5:$AW$25,1) -> 16 | AY12: =VLOOKUP(B12,[3]计算结果表!$B$1:$P$29,15,0) -> 8442.5494 | AZ12: =VLOOKUP(B12,[2]计算结果表!$B$1:$R$30,17,0) -> 7505.0391 | BA12: =AZ12/AY12-1 -> -0.11104587 | BB12: =AY12/C12 -> 0.071062174 | BC12: =AZ12/E12 -> 0.062253539 | BD12: =RANK(BC12,$BC$5:$BC$25,0) -> 17 | BE12: =BC12-BB12 -> -0.0088086344 | BF12: =VLOOKUP(B12,[5]市州营业收现率202412完成!$B$1:$AH$28,6,0) -> 116901.19 | BG12: =VLOOKUP(B12,[4]市州营业收现率12月完成!$B$1:$AI$28,7,0) -> 124954.25 | BH12: =VLOOKUP(B12,[5]市州营业收现率202412完成!$B$1:$AH$28,5,0) -> 0.9839744 | BI12: =VLOOKUP(B12,[4]市州营业收现率12月完成!$B$1:$AI$28,5,0) -> 1.0364828 | BJ12: =RANK(BI12,$BI$5:$BI$25,0) -> 14
A13: 9 | B13: 眉山 | C13: 119439.99 | D13: 17531.071 | E13: =VLOOKUP(B13,[6]Sheet1!$A$2:$I$24,5,0) -> 120948.42 | F13: =VLOOKUP(B13,[6]Sheet1!$A$2:$I$24,7,0) -> 19113.598 | G13: =E13/C13-1 -> 0.012629166 | H13: =F13/D13-1 -> 0.090269848 | I13: =VLOOKUP(B13,[3]计算结果表!$B$1:$P$29,2,0) -> 3290.8218 | J13: =VLOOKUP(B13,[2]计算结果表!$B$1:$R$30,13,0) -> 11028.141 | K13: =J13/I13-1 -> 2.3511814 | L13: =I13/C13 -> 0.027552094 | M13: =J13/E13 -> 0.09118053 | N13: =RANK(M13,$M$5:$M$25,1) -> 9 | O13: =M13-L13 -> 0.063628436 | P13: =VLOOKUP(B13,[3]计算结果表!$B$1:$P$29,13,0) -> 1953.0108 | Q13: =VLOOKUP(B13,[2]计算结果表!$B$1:$R$30,15,0) -> 8138.8904 | R13: =Q13/P13-1 -> 3.1673555 | S13: =P13/D13 -> 0.11140283 | T13: =Q13/F13 -> 0.42581676 | U13: =RANK(T13,$T$5:$T$25,1) -> 6 | V13: =T13-S13 -> 0.31441394 | W13: =VLOOKUP(B13,[2]计算结果表!$V$1:$Z$25,2,0)+VLOOKUP(B13,[2]计算结果表!$V$1:$Z$25,4,0) -> 607.29715 | X13: =VLOOKUP(B13,[2]计算结果表!$V$1:$Z$25,3,0)+VLOOKUP(B13,[2]计算结果表!$V$1:$Z$25,5,0)+VLOOKUP(B13,[2]计算结果表!$B$1:$R$28,5,0) -> 7531.5932 | Y13: =VLOOKUP(B13,[6]Sheet1!$A$2:$I$24,8,0) -> 5213.5967 | Z13: =VLOOKUP(B13,[6]Sheet1!$A$2:$I$24,9,0) -> 13900.001 | AA13: =W13/(Y13) -> 0.11648334 | AB13: =RANK(AA13,$AA$5:$AA$25,1) -> 3 | AC13: =X13/Z13 -> 0.5418412 | AD13: =RANK(AC13,$AC$5:$AC$25,1) -> 5 | AE13: =VLOOKUP(B13,[3]计算结果表!$B$1:$P$29,14,0) -> 2325.3332 | AF13: =VLOOKUP(B13,[2]计算结果表!$B$1:$R$30,16,0) -> 2889.2506 | AG13: =AF13/AE13-1 -> 0.24251035 | AH13: =AE13/(C13-D13) -> 0.022817759 | AI13: =AF13/(E13-F13) -> 0.028371931 | AJ13: =RANK(AI13,$AI$5:$AI$25,1) -> 11 | AK13: =AI13-AH13 -> 0.0055541724 | AL13: 198.34581 | AM13: =VLOOKUP(B13,[1]Sheet1!$B$28:$F$52,4,0) -> 697.49064 | AN13: =AM13/AL13-1 -> 2.5165384 | AO13: =RANK(AN13,$AN$5:$AN$25,1) -> 20 | AP13: =AL13/I13 -> 0.060272423 | AQ13: =AM13/#REF! -> #REF! | AR13: =RANK(AQ13,$AQ$5:$AQ$25,1) -> #REF! | AS13: 100.98742 | AT13: =VLOOKUP(B13,[1]Sheet1!$B$28:$F$52,2,0) -> 497.56831 | AU13: =AT13/Q13 -> 0.061134662 | AV13: =RANK(AU13,$AU$5:$AU$25,1) -> 1 | AW13: =AT13/AS13-1 -> 3.9270325 | AX13: =RANK(AW13,$AW$5:$AW$25,1) -> 19 | AY13: =VLOOKUP(B13,[3]计算结果表!$B$1:$P$29,15,0) -> 10741.12 | AZ13: =VLOOKUP(B13,[2]计算结果表!$B$1:$R$30,17,0) -> 7556.0301 | BA13: =AZ13/AY13-1 -> -0.29653238 | BB13: =AY13/C13 -> 0.089929009 | BC13: =AZ13/E13 -> 0.062473162 | BD13: =RANK(BC13,$BC$5:$BC$25,0) -> 16 | BE13: =BC13-BB13 -> -0.027455847 | BF13: =VLOOKUP(B13,[5]市州营业收现率202412完成!$B$1:$AH$28,6,0) -> 122533.99 | BG13: =VLOOKUP(B13,[4]市州营业收现率12月完成!$B$1:$AI$28,7,0) -> 118548.11 | BH13: =VLOOKUP(B13,[5]市州营业收现率202412完成!$B$1:$AH$28,5,0) -> 1.0259042 | BI13: =VLOOKUP(B13,[4]市州营业收现率12月完成!$B$1:$AI$28,5,0) -> 0.98015429 | BJ13: =RANK(BI13,$BI$5:$BI$25,0) -> 21
A14: 10 | B14: 德阳 | C14: 112625.5 | D14: 16847.36 | E14: =VLOOKUP(B14,[6]Sheet1!$A$2:$I$24,5,0) -> 108454.18 | F14: =VLOOKUP(B14,[6]Sheet1!$A$2:$I$24,7,0) -> 14837.504 | G14: =E14/C14-1 -> -0.037037112 | H14: =F14/D14-1 -> -0.11929796 | I14: =VLOOKUP(B14,[3]计算结果表!$B$1:$P$29,2,0) -> 7986.371 | J14: =VLOOKUP(B14,[2]计算结果表!$B$1:$R$30,13,0) -> 11365.975 | K14: =J14/I14-1 -> 0.42317146 | L14: =I14/C14 -> 0.070910859 | M14: =J14/E14 -> 0.10479979 | N14: =RANK(M14,$M$5:$M$25,1) -> 15 | O14: =M14-L14 -> 0.033888933 | P14: =VLOOKUP(B14,[3]计算结果表!$B$1:$P$29,13,0) -> 6107.7088 | Q14: =VLOOKUP(B14,[2]计算结果表!$B$1:$R$30,15,0) -> 8838.4023 | R14: =Q14/P14-1 -> 0.44708967 | S14: =P14/D14 -> 0.36253211 | T14: =Q14/F14 -> 0.59567986 | U14: =RANK(T14,$T$5:$T$25,1) -> 14 | V14: =T14-S14 -> 0.23314775 | W14: =VLOOKUP(B14,[2]计算结果表!$V$1:$Z$25,2,0)+VLOOKUP(B14,[2]计算结果表!$V$1:$Z$25,4,0) -> 2329.3682 | X14: =VLOOKUP(B14,[2]计算结果表!$V$1:$Z$25,3,0)+VLOOKUP(B14,[2]计算结果表!$V$1:$Z$25,5,0)+VLOOKUP(B14,[2]计算结果表!$B$1:$R$28,5,0) -> 6509.0342 | Y14: =VLOOKUP(B14,[6]Sheet1!$A$2:$I$24,8,0) -> 7589.989 | Z14: =VLOOKUP(B14,[6]Sheet1!$A$2:$I$24,9,0) -> 7247.5149 | AA14: =W14/(Y14) -> 0.30690007 | AB14: =RANK(AA14,$AA$5:$AA$25,1) -> 16 | AC14: =X14/Z14 -> 0.89810566 | AD14: =RANK(AC14,$AC$5:$AC$25,1) -> 15 | AE14: =VLOOKUP(B14,[3]计算结果表!$B$1:$P$29,14,0) -> 2397.8289 | AF14: =VLOOKUP(B14,[2]计算结果表!$B$1:$R$30,16,0) -> 2527.5729 | AG14: =AF14/AE14-1 -> 0.054108986 | AH14: =AE14/(C14-D14) -> 0.025035241 | AI14: =AF14/(E14-F14) -> 0.026999175 | AJ14: =RANK(AI14,$AI$5:$AI$25,1) -> 9 | AK14: =AI14-AH14 -> 0.0019639338 | AL14: 745.24889 | AM14: =VLOOKUP(B14,[1]Sheet1!$B$28:$F$52,4,0) -> 1445.2406 | AN14: =AM14/AL14-1 -> 0.93927235 | AO14: =RANK(AN14,$AN$5:$AN$25,1) -> 9 | AP14: =AL14/I14 -> 0.093315086 | AQ14: =AM14/#REF! -> #REF! | AR14: =RANK(AQ14,$AQ$5:$AQ$25,1) -> #REF! | AS14: 515.04498 | AT14: =VLOOKUP(B14,[1]Sheet1!$B$28:$F$52,2,0) -> 1120.1675 | AU14: =AT14/Q14 -> 0.12673869 | AV14: =RANK(AU14,$AU$5:$AU$25,1) -> 8 | AW14: =AT14/AS14-1 -> 1.1748926 | AX14: =RANK(AW14,$AW$5:$AW$25,1) -> 11 | AY14: =VLOOKUP(B14,[3]计算结果表!$B$1:$P$29,15,0) -> 8556.9357 | AZ14: =VLOOKUP(B14,[2]计算结果表!$B$1:$R$30,17,0) -> 9022.3324 | BA14: =AZ14/AY14-1 -> 0.054388241 | BB14: =AY14/C14 -> 0.075976893 | BC14: =AZ14/E14 -> 0.08319027 | BD14: =RANK(BC14,$BC$5:$BC$25,0) -> 9 | BE14: =BC14-BB14 -> 0.007213377 | BF14: =VLOOKUP(B14,[5]市州营业收现率202412完成!$B$1:$AH$28,6,0) -> 112332.57 | BG14: =VLOOKUP(B14,[4]市州营业收现率12月完成!$B$1:$AI$28,7,0) -> 113788.68 | BH14: =VLOOKUP(B14,[5]市州营业收现率202412完成!$B$1:$AH$28,5,0) -> 0.99739906 | BI14: =VLOOKUP(B14,[4]市州营业收现率12月完成!$B$1:$AI$28,5,0) -> 1.0491867 | BJ14: =RANK(BI14,$BI$5:$BI$25,0) -> 10
A15: 11 | B15: 内江 | C15: 86652.333 | D15: 9254.439 | E15: =VLOOKUP(B15,[6]Sheet1!$A$2:$I$24,5,0) -> 87486.809 | F15: =VLOOKUP(B15,[6]Sheet1!$A$2:$I$24,7,0) -> 8336.977 | G15: =E15/C15-1 -> 0.0096301698 | H15: =F15/D15-1 -> -0.099137504 | I15: =VLOOKUP(B15,[3]计算结果表!$B$1:$P$29,2,0) -> 4842.6367 | J15: =VLOOKUP(B15,[2]计算结果表!$B$1:$R$30,13,0) -> 6191.9086 | K15: =J15/I15-1 -> 0.2786234 | L15: =I15/C15 -> 0.055885821 | M15: =J15/E15 -> 0.07077534 | N15: =RANK(M15,$M$5:$M$25,1) -> 5 | O15: =M15-L15 -> 0.014889519 | P15: =VLOOKUP(B15,[3]计算结果表!$B$1:$P$29,13,0) -> 4238.897 | Q15: =VLOOKUP(B15,[2]计算结果表!$B$1:$R$30,15,0) -> 3991.0078 | R15: =Q15/P15-1 -> -0.05847965 | S15: =P15/D15 -> 0.45803932 | T15: =Q15/F15 -> 0.47871162 | U15: =RANK(T15,$T$5:$T$25,1) -> 9 | V15: =T15-S15 -> 0.020672296 | W15: =VLOOKUP(B15,[2]计算结果表!$V$1:$Z$25,2,0)+VLOOKUP(B15,[2]计算结果表!$V$1:$Z$25,4,0) -> 475.01431 | X15: =VLOOKUP(B15,[2]计算结果表!$V$1:$Z$25,3,0)+VLOOKUP(B15,[2]计算结果表!$V$1:$Z$25,5,0)+VLOOKUP(B15,[2]计算结果表!$B$1:$R$28,5,0) -> 3515.9935 | Y15: =VLOOKUP(B15,[6]Sheet1!$A$2:$I$24,8,0) -> 3135.4968 | Z15: =VLOOKUP(B15,[6]Sheet1!$A$2:$I$24,9,0) -> 5201.4802 | AA15: =W15/(Y15) -> 0.15149571 | AB15: =RANK(AA15,$AA$5:$AA$25,1) -> 6 | AC15: =X15/Z15 -> 0.67596018 | AD15: =RANK(AC15,$AC$5:$AC$25,1) -> 12 | AE15: =VLOOKUP(B15,[3]计算结果表!$B$1:$P$29,14,0) -> 2238.3723 | AF15: =VLOOKUP(B15,[2]计算结果表!$B$1:$R$30,16,0) -> 2200.9009 | AG15: =AF15/AE15-1 -> -0.016740496 | AH15: =AE15/(C15-D15) -> 0.028920326 | AI15: =AF15/(E15-F15) -> 0.027806766 | AJ15: =RANK(AI15,$AI$5:$AI$25,1) -> 10 | AK15: =AI15-AH15 -> -0.0011135602 | AL15: 1755.0152 | AM15: =VLOOKUP(B15,[1]Sheet1!$B$28:$F$52,4,0) -> 977.28354 | AN15: =AM15/AL15-1 -> -0.44314811 | AO15: =RANK(AN15,$AN$5:$AN$25,1) -> 2 | AP15: =AL15/I15 -> 0.36240902 | AQ15: =AM15/#REF! -> #REF! | AR15: =RANK(AQ15,$AQ$5:$AQ$25,1) -> #REF! | AS15: 1510.4555 | AT15: =VLOOKUP(B15,[1]Sheet1!$B$28:$F$52,2,0) -> 721.19031 | AU15: =AT15/Q15 -> 0.18070381 | AV15: =RANK(AU15,$AU$5:$AU$25,1) -> 14 | AW15: =AT15/AS15-1 -> -0.52253455 | AX15: =RANK(AW15,$AW$5:$AW$25,1) -> 1 | AY15: =VLOOKUP(B15,[3]计算结果表!$B$1:$P$29,15,0) -> 4456.5493 | AZ15: =VLOOKUP(B15,[2]计算结果表!$B$1:$R$30,17,0) -> 5539.0729 | BA15: =AZ15/AY15-1 -> 0.24290624 | BB15: =AY15/C15 -> 0.051430229 | BC15: =AZ15/E15 -> 0.063313235 | BD15: =RANK(BC15,$BC$5:$BC$25,0) -> 15 | BE15: =BC15-BB15 -> 0.011883006 | BF15: =VLOOKUP(B15,[5]市州营业收现率202412完成!$B$1:$AH$28,6,0) -> 85392.157 | BG15: =VLOOKUP(B15,[4]市州营业收现率12月完成!$B$1:$AI$28,7,0) -> 93158.829 | BH15: =VLOOKUP(B15,[5]市州营业收现率202412完成!$B$1:$AH$28,5,0) -> 0.98545711 | BI15: =VLOOKUP(B15,[4]市州营业收现率12月完成!$B$1:$AI$28,5,0) -> 1.0648329 | BJ15: =RANK(BI15,$BI$5:$BI$25,0) -> 5
A16: 12 | B16: 巴中 | C16: 82743.629 | D16: 11544.911 | E16: =VLOOKUP(B16,[6]Sheet1!$A$2:$I$24,5,0) -> 77707.532 | F16: =VLOOKUP(B16,[6]Sheet1!$A$2:$I$24,7,0) -> 7596.7086 | G16: =E16/C16-1 -> -0.060863853 | H16: =F16/D16-1 -> -0.34198637 | I16: =VLOOKUP(B16,[3]计算结果表!$B$1:$P$29,2,0) -> 6883.3837 | J16: =VLOOKUP(B16,[2]计算结果表!$B$1:$R$30,13,0) -> 10447.296 | K16: =J16/I16-1 -> 0.51775585 | L16: =I16/C16 -> 0.08318929 | M16: =J16/E16 -> 0.1344438 | N16: =RANK(M16,$M$5:$M$25,1) -> 21 | O16: =M16-L16 -> 0.05125451 | P16: =VLOOKUP(B16,[3]计算结果表!$B$1:$P$29,13,0) -> 6808.0977 | Q16: =VLOOKUP(B16,[2]计算结果表!$B$1:$R$30,15,0) -> 8736.906 | R16: =Q16/P16-1 -> 0.2833109 | S16: =P16/D16 -> 0.58970553 | T16: =Q16/F16 -> 1.150091 | U16: =RANK(T16,$T$5:$T$25,1) -> 21 | V16: =T16-S16 -> 0.56038545 | W16: =VLOOKUP(B16,[2]计算结果表!$V$1:$Z$25,2,0)+VLOOKUP(B16,[2]计算结果表!$V$1:$Z$25,4,0) -> 1020.6973 | X16: =VLOOKUP(B16,[2]计算结果表!$V$1:$Z$25,3,0)+VLOOKUP(B16,[2]计算结果表!$V$1:$Z$25,5,0)+VLOOKUP(B16,[2]计算结果表!$B$1:$R$28,5,0) -> 7716.2087 | Y16: =VLOOKUP(B16,[6]Sheet1!$A$2:$I$24,8,0) -> 2433.9114 | Z16: =VLOOKUP(B16,[6]Sheet1!$A$2:$I$24,9,0) -> 5162.7972 | AA16: =W16/(Y16) -> 0.41936502 | AB16: =RANK(AA16,$AA$5:$AA$25,1) -> 21 | AC16: =X16/Z16 -> 1.4945791 | AD16: =RANK(AC16,$AC$5:$AC$25,1) -> 21 | AE16: =VLOOKUP(B16,[3]计算结果表!$B$1:$P$29,14,0) -> 1902.4281 | AF16: =VLOOKUP(B16,[2]计算结果表!$B$1:$R$30,16,0) -> 1710.3899 | AG16: =AF16/AE16-1 -> -0.10094373 | AH16: =AE16/(C16-D16) -> 0.026719977 | AI16: =AF16/(E16-F16) -> 0.024395519 | AJ16: =RANK(AI16,$AI$5:$AI$25,1) -> 8 | AK16: =AI16-AH16 -> -0.0023244584 | AL16: 770.00084 | AM16: =VLOOKUP(B16,[1]Sheet1!$B$28:$F$52,4,0) -> 3768.0771 | AN16: =AM16/AL16-1 -> 3.8936013 | AO16: =RANK(AN16,$AN$5:$AN$25,1) -> 21 | AP16: =AL16/I16 -> 0.11186371 | AQ16: =AM16/#REF! -> #REF! | AR16: =RANK(AQ16,$AQ$5:$AQ$25,1) -> #REF! | AS16: 730.62073 | AT16: =VLOOKUP(B16,[1]Sheet1!$B$28:$F$52,2,0) -> 2850.2519 | AU16: =AT16/Q16 -> 0.32623127 | AV16: =RANK(AU16,$AU$5:$AU$25,1) -> 20 | AW16: =AT16/AS16-1 -> 2.9011375 | AX16: =RANK(AW16,$AW$5:$AW$25,1) -> 15 | AY16: =VLOOKUP(B16,[3]计算结果表!$B$1:$P$29,15,0) -> 5790.256 | AZ16: =VLOOKUP(B16,[2]计算结果表!$B$1:$R$30,17,0) -> 6760.9964 | BA16: =AZ16/AY16-1 -> 0.16765069 | BB16: =AY16/C16 -> 0.06997827 | BC16: =AZ16/E16 -> 0.087005676 | BD16: =RANK(BC16,$BC$5:$BC$25,0) -> 7 | BE16: =BC16-BB16 -> 0.017027406 | BF16: =VLOOKUP(B16,[5]市州营业收现率202412完成!$B$1:$AH$28,6,0) -> 77350.602 | BG16: =VLOOKUP(B16,[4]市州营业收现率12月完成!$B$1:$AI$28,7,0) -> 82146.767 | BH16: =VLOOKUP(B16,[5]市州营业收现率202412完成!$B$1:$AH$28,5,0) -> 0.93482246 | BI16: =VLOOKUP(B16,[4]市州营业收现率12月完成!$B$1:$AI$28,5,0) -> 1.0571275 | BJ16: =RANK(BI16,$BI$5:$BI$25,0) -> 8
... A25: 21 | B25: 攀枝花 | C25: 39056.358 | D25: 4575.0906 | E25: =VLOOKUP(B25,[6]Sheet1!$A$2:$I$24,5,0) -> 41681.598 | F25: =VLOOKUP(B25,[6]Sheet1!$A$2:$I$24,7,0) -> 5590.1337 | G25: =E25/C25-1 -> 0.067216723 | H25: =F25/D25-1 -> 0.22186297 | I25: =VLOOKUP(B25,[3]计算结果表!$B$1:$P$29,2,0) -> 4551.7585 | J25: =VLOOKUP(B25,[2]计算结果表!$B$1:$R$30,13,0) -> 4138.8467 | K25: =J25/I25-1 -> -0.090714783 | L25: =I25/C25 -> 0.11654334 | M25: =J25/E25 -> 0.099296738 | N25: =RANK(M25,$M$5:$M$25,1) -> 13 | O25: =M25-L25 -> -0.017246606 | P25: =VLOOKUP(B25,[3]计算结果表!$B$1:$P$29,13,0) -> 2946.3106 | Q25: =VLOOKUP(B25,[2]计算结果表!$B$1:$R$30,15,0) -> 2736.3523 | R25: =Q25/P25-1 -> -0.071261445 | S25: =P25/D25 -> 0.64398958 | T25: =Q25/F25 -> 0.48949675 | U25: =RANK(T25,$T$5:$T$25,1) -> 10 | V25: =T25-S25 -> -0.15449283 | W25: =VLOOKUP(B25,[2]计算结果表!$V$1:$Z$25,2,0)+VLOOKUP(B25,[2]计算结果表!$V$1:$Z$25,4,0) -> 608.15047 | X25: =VLOOKUP(B25,[2]计算结果表!$V$1:$Z$25,3,0)+VLOOKUP(B25,[2]计算结果表!$V$1:$Z$25,5,0)+VLOOKUP(B25,[2]计算结果表!$B$1:$R$28,5,0) -> 2128.2018 | Y25: =VLOOKUP(B25,[6]Sheet1!$A$2:$I$24,8,0) -> 2118.1028 | Z25: =VLOOKUP(B25,[6]Sheet1!$A$2:$I$24,9,0) -> 3472.0309 | AA25: =W25/(Y25) -> 0.28712037 | AB25: =RANK(AA25,$AA$5:$AA$25,1) -> 13 | AC25: =X25/Z25 -> 0.61295589 | AD25: =RANK(AC25,$AC$5:$AC$25,1) -> 7 | AE25: =VLOOKUP(B25,[3]计算结果表!$B$1:$P$29,14,0) -> 2228.3442 | AF25: =VLOOKUP(B25,[2]计算结果表!$B$1:$R$30,16,0) -> 1402.4944 | AG25: =AF25/AE25-1 -> -0.3706114 | AH25: =AE25/(C25-D25) -> 0.064624777 | AI25: =AF25/(E25-F25) -> 0.03885945 | AJ25: =RANK(AI25,$AI$5:$AI$25,1) -> 15 | AK25: =AI25-AH25 -> -0.025765327 | AL25: 3170.013 | AM25: =VLOOKUP(B25,[1]Sheet1!$B$28:$F$52,4,0) -> 1635.4397 | AN25: =AM25/AL25-1 -> -0.48409054 | AO25: =RANK(AN25,$AN$5:$AN$25,1) -> 1 | AP25: =AL25/I25 -> 0.69643698 | AQ25: =AM25/#REF! -> #REF! | AR25: =RANK(AQ25,$AQ$5:$AQ$25,1) -> #REF! | AS25: 1726.2684 | AT25: =VLOOKUP(B25,[1]Sheet1!$B$28:$F$52,2,0) -> 829.5616 | AU25: =AT25/Q25 -> 0.3031633 | AV25: =RANK(AU25,$AU$5:$AU$25,1) -> 19 | AW25: =AT25/AS25-1 -> -0.51944808 | AX25: =RANK(AW25,$AW$5:$AW$25,1) -> 2 | AY25: =VLOOKUP(B25,[3]计算结果表!$B$1:$P$29,15,0) -> 4470.9864 | AZ25: =VLOOKUP(B25,[2]计算结果表!$B$1:$R$30,17,0) -> 4145.1223 | BA25: =AZ25/AY25-1 -> -0.07288416 | BB25: =AY25/C25 -> 0.11447525 | BC25: =AZ25/E25 -> 0.099447297 | BD25: =RANK(BC25,$BC$5:$BC$25,0) -> 4 | BE25: =BC25-BB25 -> -0.015027954 | BF25: =VLOOKUP(B25,[5]市州营业收现率202412完成!$B$1:$AH$28,6,0) -> 41027.872 | BG25: =VLOOKUP(B25,[4]市州营业收现率12月完成!$B$1:$AI$28,7,0) -> 47134.499 | BH25: =VLOOKUP(B25,[5]市州营业收现率202412完成!$B$1:$AH$28,5,0) -> 1.0504787 | BI25: =VLOOKUP(B25,[4]市州营业收现率12月完成!$B$1:$AI$28,5,0) -> 1.1308227 | BJ25: =RANK(BI25,$BI$5:$BI$25,0) -> 1
A26: 22 | B26: 市州合计 | C26: =SUM(C5:C25) -> 3042057.2 | D26: =SUM(D5:D25) -> 462938.61 | E26: =SUM(E5:E25) -> 3051812 | F26: =SUM(F5:F25) -> 429644.34 | I26: =SUM(I5:I25) -> 159380.69 | J26: =SUM(J5:J25) -> 252748.69 | K26: =J26/I26-1 -> 0.58581753 | L26: =I26/C26 -> 0.052392404 | M26: =J26/E26 -> 0.082819222 | O26: =M26-L26 -> 0.030426818 | P26: =SUM(P5:P25) -> 119053.82 | Q26: =SUM(Q5:Q25) -> 181786.99 | R26: =Q26/P26-1 -> 0.52693113 | S26: =P26/D26 -> 0.25716979 | T26: =Q26/F26 -> 0.42311041 | V26: =T26-S26 -> 0.16594062 | W26: =SUM(W5:W25) -> 29083.743 | X26: =SUM(X5:X25) -> 152703.25 | Y26: =SUM(Y5:Y25) -> 176691.03 | Z26: =SUM(Z5:Z25) -> 252953.3 | AA26: =W26/(Y26/11*12) -> 0.1508854 | AC26: =X26/(Z26/11*12) -> 0.55337477 | AE26: =SUM(AE5:AE25) -> 72281.951 | AF26: =SUM(AF5:AF25) -> 70961.703 | AG26: =AF26/AE26-1 -> -0.018265241 | AH26: =AE26/(C26-D26) -> 0.028025834 | AI26: =AF26/(E26-F26) -> 0.02706223 | AK26: =AI26-AH26 -> -0.00096360461 | AL26: =SUM(AL5:AL25) -> 26692.471 | AM26: =SUM(AM5:AM25) -> 49717.521 | AN26: =AM26/AL26-1 -> 0.86260463 | AP26: =AL26/I26 -> 0.16747619 | AQ26: =AM26/#REF! -> #REF! | AS26: =SUM(AS5:AS25) -> 18036.386 | AT26: =SUM(AT5:AT25) -> 33985.686 | AU26: =AT26/Q26 -> 0.18695334 | AW26: =AT26/AS26-1 -> 0.88428463 | AY26: =SUM(AY5:AY25) -> 247318.97 | AZ26: =SUM(AZ5:AZ25) -> 254765.16 | BA26: =AZ26/AY26-1 -> 0.030107656 | BB26: =AY26/C26 -> 0.081299907 | BC26: =AZ26/E26 -> 0.083479967 | BE26: =BC26-BB26 -> 0.0021800596 | BF26: =VLOOKUP(B26,[5]市州营业收现率202412完成!$B$1:$AH$28,6,0) -> 3089855.2 | BG26: =VLOOKUP(B26,[4]市州营业收现率12月完成!$B$1:$AI$28,7,0) -> 3212100.3 | BH26: =VLOOKUP(B26,[5]市州营业收现率202412完成!$B$1:$AH$28,5,0) -> 1.0157124 | BI26: =VLOOKUP(B26,[4]市州营业收现率12月完成!$B$1:$AI$28,5,0) -> 1.0525224
