Workbook

Sheet 假设面板
A1: Hermès 2026-2030 财务预测 — 核心假设
A2: 蓝色字体=可调整假设输入; 黄色底色=关键假设需关注
A3: 假设项目 | B3: 数值 | C3: 说明/来源
A4: ===== 营收增长假设 =====
A5: 2026年营收增速 (%) | B5: 5.5 | C5: 基于2025年+5.5%趋势; 历史20Y CAGR=13.2%, 近期减速
A6: 2027年营收增速 (%) | B6: 5 | C6: 假设增速逐步正常化
A7: 2028年营收增速 (%) | B7: 4.8 | C7: 成熟市场增速放缓
A8: 2029年营收增速 (%) | B8: 4.5 | C8: 品牌延展与提价支撑
A9: 2030年营收增速 (%) | B9: 4.2 | C9: 稳态增长假设
A11: ===== 成本结构假设 =====
A12: 毛利率 (%) | B12: 70 | C12: 历史稳定在~70% (皮革手工成本刚性)
A13: SG&A 占营收比 (%) | B13: 29 | C13: 2025年约29.0%; 假设规模效应持平
A14: D&A 占营收比 (%) | B14: 5 | C14: 折旧摊销占营收比 (店铺+工坊投资)
A15: 有效税率 (%) | B15: 27 | C15: 法国企业所得税率+全球混合税率
A17: ===== 门店扩张假设 =====
A18: 2026年净增门店数 | B18: 5 | C18: 每年净增5-8家 (谨慎扩张策略)
A19: 2027年净增门店数 | B19: 5
A20: 2028年净增门店数 | B20: 6
A21: 2029年净增门店数 | B21: 6
A22: 2030年净增门店数 | B22: 8 | C22: 加速亚太布局
A24: ===== 员工增长假设 =====
A25: 员工年增速 (%) | B25: 5 | C25: 历史5Y CAGR ~7.7%; 假设减缓
A27: ===== 宏观假设 =====
A28: EUR/USD 汇率 | B28: 1.08 | C28: 2025年末汇率; 假设稳定
A29: 全球奢侈品市场增速 (%) | B29: 4 | C29: Bain & Company 行业预测中值

Sheet 利润表预测
A1: Hermès 利润表预测 (2026-2030)
A2: 单位: EUR million; 蓝色=硬编码输入; 公式自动计算
A3: (EUR million) | B3: 2025A 实际 | C3: 2026E | D3: 2027E | E3: 2028E | F3: 2029E | G3: 2030E
A4: Revenue | B4: 16002 | C4: =B4*(1+假设面板!B5/100) | D4: =C4*(1+假设面板!B6/100) | E4: =D4*(1+假设面板!B7/100) | F4: =E4*(1+假设面板!B8/100) | G4: =F4*(1+假设面板!B9/100)
A5: YoY Growth (%) | C5: =(C4/B4-1)*100 | D5: =(D4/C4-1)*100 | E5: =(E4/D4-1)*100 | F5: =(F4/E4-1)*100 | G5: =(G4/F4-1)*100
A6: COGS | B6: 4801 | C6: =C4*(1-假设面板!B12/100) | D6: =D4*(1-假设面板!B12/100) | E6: =E4*(1-假设面板!B12/100) | F6: =F4*(1-假设面板!B12/100) | G6: =G4*(1-假设面板!B12/100)
A7: Gross Profit | B7: =B4-B6 | C7: =C4-C6 | D7: =D4-D6 | E7: =E4-E6 | F7: =F4-F6 | G7: =G4-G6
A8: Gross Margin (%) | B8: =B7/B4*100 | C8: =C7/C4*100 | D8: =D7/D4*100 | E8: =E7/E4*100 | F8: =F7/F4*100 | G8: =G7/G4*100
A9: SG&A | B9: 4641 | C9: =C4*假设面板!B13/100 | D9: =D4*假设面板!B13/100 | E9: =E4*假设面板!B13/100 | F9: =F4*假设面板!B13/100 | G9: =G4*假设面板!B13/100
A10: D&A | B10: 800 | C10: =C4*假设面板!B14/100 | D10: =D4*假设面板!B14/100 | E10: =E4*假设面板!B14/100 | F10: =F4*假设面板!B14/100 | G10: =G4*假设面板!B14/100
A11: Operating Income (EBIT) | B11: =B7-B9-B10 | C11: =C7-C9-C10 | D11: =D7-D9-D10 | E11: =E7-E9-E10 | F11: =F7-F9-F10 | G11: =G7-G9-G10
A12: Operating Margin (%) | B12: =B11/B4*100 | C12: =C11/C4*100 | D12: =D11/D4*100 | E12: =E11/E4*100 | F12: =F11/F4*100 | G12: =G11/G4*100
A13: Interest & Other | B13: 100 | C13: 100 | D13: 100 | E13: 100 | F13: 100 | G13: 100
A14: Pre-Tax Income | B14: =B11+B13 | C14: =C11+C13 | D14: =D11+D13 | E14: =E11+E13 | F14: =F11+F13 | G14: =G11+G13
A15: Income Tax | B15: =B14*0.27 | C15: =C14*假设面板!B15/100 | D15: =D14*假设面板!B15/100 | E15: =E14*假设面板!B15/100 | F15: =F14*假设面板!B15/100 | G15: =G14*假设面板!B15/100
A16: Net Income | B16: =B14-B15 | C16: =C14-C15 | D16: =D14-D15 | E16: =E14-E15 | F16: =F14-F15 | G16: =G14-G15
A17: Net Margin (%) | B17: =B16/B4*100 | C17: =C16/C4*100 | D17: =D16/D4*100 | E17: =E16/E4*100 | F17: =F16/F4*100 | G17: =G16/G4*100
A18: EPS (EUR) | B18: =B16/B19 | C18: =C16/C19 | D18: =D16/D19 | E18: =E16/E19 | F18: =F16/F19 | G18: =G16/G19
A19: Shares Outstanding (m) | B19: 83.5 | C19: 83.5 | D19: 83.5 | E19: 83.5 | F19: 83.5 | G19: 83.5

Sheet 门店与人力
A1: Hermès 门店网络与人力预测 (2026-2030)
B2: 2025A | C2: 2026E | D2: 2027E | E2: 2028E | F2: 2029E | G2: 2030E
A3: 门店数 Stores | B3: 294 | C3: =B3+C4 | D3: =C3+D4 | E3: =D3+E4 | F3: =E3+F4 | G3: =F3+G4
A4: 净增 Net Adds | C4: =假设面板!B17 | D4: =假设面板!B18 | E4: =假设面板!B19 | F4: =假设面板!B20 | G4: =假设面板!B21
A5: 门店增速 (%) | C5: =(C3/B3-1)*100 | D5: =(D3/C3-1)*100 | E5: =(E3/D3-1)*100 | F5: =(F3/E3-1)*100 | G5: =(G3/F3-1)*100
A6: 单店营收 Rev/Store (EUR m) | B6: 54.4 | C6: =利润表预测!C4/C3 | D6: =利润表预测!D4/D3 | E6: =利润表预测!E4/E3 | F6: =利润表预测!F4/F3 | G6: =利润表预测!G4/G3
A8: 员工数 Employees | B8: 26494 | C8: =B8*(1+假设面板!B23/100) | D8: =C8*(1+假设面板!B23/100) | E8: =D8*(1+假设面板!B23/100) | F8: =E8*(1+假设面板!B23/100) | G8: =F8*(1+假设面板!B23/100)
A9: 净增 Net Adds | C9: =C8-B8 | D9: =D8-C8 | E9: =E8-D8 | F9: =F8-E8 | G9: =G8-F8
A10: 员工增速 (%) | C10: =(C8/B8-1)*100 | D10: =(D8/C8-1)*100 | E10: =(E8/D8-1)*100 | F10: =(F8/E8-1)*100 | G10: =(G8/F8-1)*100
A11: 人均营收 Rev/Emp (kEUR) | B11: 604 | C11: =利润表预测!C4*1000/C8 | D11: =利润表预测!D4*1000/D8 | E11: =利润表预测!E4*1000/E8 | F11: =利润表预测!F4*1000/F8 | G11: =利润表预测!G4*1000/G8
A13: 工坊数 Ateliers | B13: 22 | C13: =IF(B13="","",B13+1) | D13: =IF(C13="","",C13+1) | E13: =IF(D13="","",D13+1) | F13: =IF(E13="","",E13+1) | G13: =IF(F13="","",F13+1)
A14: 产能指数 (2025=100) | C14: =C13/22*100 | D14: =D13/22*100 | E14: =E13/22*100 | F14: =F13/22*100 | G14: =G13/22*100

Sheet 预测总览
A1: Hermès 2026-2030 预测总览
A2: Key Metrics | B2: 2025A | C2: 2026E | D2: 2027E | E2: 2028E | F2: 2029E | G2: 2030E
A3: 营收 Revenue (EUR m) | B3: =利润表预测!B4 | C3: =利润表预测!C4 | D3: =利润表预测!D4 | E3: =利润表预测!E4 | F3: =利润表预测!F4 | G3: =利润表预测!G4
A4: 营收增速 Rev Growth (%) | B4: — | C4: =利润表预测!C5 | D4: =利润表预测!D5 | E4: =利润表预测!E5 | F4: =利润表预测!F5 | G4: =利润表预测!G5
A5: 营业利润 EBIT (EUR m) | B5: =利润表预测!B11 | C5: =利润表预测!C11 | D5: =利润表预测!D11 | E5: =利润表预测!E11 | F5: =利润表预测!F11 | G5: =利润表预测!G11
A6: 营业利润率 Op. Margin (%) | B6: =利润表预测!B12 | C6: =利润表预测!C12 | D6: =利润表预测!D12 | E6: =利润表预测!E12 | F6: =利润表预测!F12 | G6: =利润表预测!G12
A7: 净利润 Net Income (EUR m) | B7: =利润表预测!B16 | C7: =利润表预测!C16 | D7: =利润表预测!D16 | E7: =利润表预测!E16 | F7: =利润表预测!F16 | G7: =利润表预测!G16
A8: 净利率 Net Margin (%) | B8: =利润表预测!B17 | C8: =利润表预测!C17 | D8: =利润表预测!D17 | E8: =利润表预测!E17 | F8: =利润表预测!F17 | G8: =利润表预测!G17
A9: EPS (EUR) | B9: =利润表预测!B18 | C9: =利润表预测!C18 | D9: =利润表预测!D18 | E9: =利润表预测!E18 | F9: =利润表预测!F18 | G9: =利润表预测!G18
A10: 门店数 Stores | B10: =门店与人力!B3 | C10: =门店与人力!C3 | D10: =门店与人力!D3 | E10: =门店与人力!E3 | F10: =门店与人力!F3 | G10: =门店与人力!G3
A11: 员工数 Employees | B11: =门店与人力!B8 | C11: =门店与人力!C8 | D11: =门店与人力!D8 | E11: =门店与人力!E8 | F11: =门店与人力!F8 | G11: =门店与人力!G8
A12: 单店营收 Rev/Store (EUR m) | B12: =门店与人力!B6 | C12: =门店与人力!C6 | D12: =门店与人力!D6 | E12: =门店与人力!E6 | F12: =门店与人力!F6 | G12: =门店与人力!G6
A13: 人均营收 Rev/Emp (kEUR) | B13: =门店与人力!B11 | C13: =门店与人力!C11 | D13: =门店与人力!D11 | E13: =门店与人力!E11 | F13: =门店与人力!F11 | G13: =门店与人力!G11
A14: 工坊数 Ateliers | B14: =门店与人力!B13 | C14: =门店与人力!C13 | D14: =门店与人力!D13 | E14: =门店与人力!E13 | F14: =门店与人力!F13 | G14: =门店与人力!G13
A15: 5Y Revenue CAGR (%) | G15: =((G4/利润表预测!B4)^(1/5)-1)*100
A16: 5Y Net Income CAGR (%) | G16: =((G6/利润表预测!B16)^(1/5)-1)*100

Sheet 情景分析
A1: Hermès 情景分析: 2030年关键指标
A2: 蓝色=手工假设; 基于核心假设的不同情景推演
A3: 指标 | B3: 保守情景 (增速-2pp) | C3: 基准情景 | D3: 乐观情景 (增速+2pp)
A4: Revenue CAGR 2026-30 (%) | B4: 3 | C4: 4.8 | D4: 6.5
A5: 2030E Revenue (EUR m) | B5: 18600 | C5: 20300 | D5: 22100
A6: 2030E Op. Margin (%) | B6: 38 | C6: 40.5 | D6: 42
A7: 2030E Net Income (EUR m) | B7: 4900 | C7: 5700 | D7: 6600
A8: 2030E Stores | B8: 310 | C8: 319 | D8: 330
A9: 2030E Employees | B9: 32000 | C9: 33800 | D9: 35500
A10: 2030E EPS (EUR) | B10: 58.7 | C10: 68.3 | D10: 79
A11: 2030E Implied Mkt Cap (EUR bn) | B11: 176 | C11: 260 | D11: 355
A12: Implied P/E (x) | B12: 30 | C12: 38 | D12: 45
